{"date":"2019-03-19T06:50:30.715Z","map":"de_mirage","team1_name":"team_Samaly","team2_name":"team_noctias","team1_players":{"76561198139429381":"FriZZleBeeF","76561198062153950":"Jordan2EZGG","76561198842037276":"Samaly","76561198120286262":"ESLHOTDOG","76561197961085746":"gehrke"},"team2_players":{"76561198162875654":"confoozed","76561198033939559":"noctias","76561198020317127":"buhbang","76561197993761807":"PeachyPear","76561198038246134":"sunkisd"},"rounds":[{"round_start_time":107.4140625,"round_end_time":177.2578125,"t":"team_Samaly","ct":"team_noctias","winner":"team_Samaly","players":{"0":{"kills":0,"headshots":0,"assists":0,"time_alive":-1,"damage":0,"objective":false,"entry":false,"entry_weapon":null},"76561197993761807":{"kills":2,"headshots":2,"assists":0,"time_alive":37.28125,"damage":213,"objective":false,"entry":true,"entry_weapon":"usp_silencer_off","wp_usp_silencer_off":2,"wp_usp_silencer_off_hs":2},"undefined":{"kills":0,"headshots":0,"assists":6,"time_alive":-1,"damage":0,"objective":false,"entry":false,"entry_weapon":null},"76561197961085746":{"kills":0,"headshots":0,"assists":0,"time_alive":20.484375,"damage":0,"objective":false,"entry":false,"entry_weapon":null},"76561198842037276":{"kills":0,"headshots":0,"assists":0,"time_alive":30.9375,"damage":0,"objective":false,"entry":false,"entry_weapon":null},"76561198062153950":{"kills":3,"headshots":2,"assists":0,"time_alive":-1,"damage":300,"objective":false,"entry":false,"entry_weapon":null,"wp_glock":3,"wp_glock_hs":2},"76561198120286262":{"kills":2,"headshots":1,"assists":0,"time_alive":-1,"damage":112,"objective":false,"entry":false,"entry_weapon":null,"wp_glock":1,"wp_glock_hs":1,"wp_hkp2000":1,"wp_hkp2000_hs":0},"76561198020317127":{"kills":0,"headshots":0,"assists":0,"time_alive":38.640625,"damage":0,"objective":false,"entry":false,"entry_weapon":null},"76561198139429381":{"kills":0,"headshots":0,"assists":1,"time_alive":-1,"damage":88,"objective":true,"entry":false,"entry_weapon":null},"76561198162875654":{"kills":0,"headshots":0,"assists":0,"time_alive":51.59375,"damage":31,"objective":false,"entry":false,"entry_weapon":null},"76561198033939559":{"kills":0,"headshots":0,"assists":0,"time_alive":69.0625,"damage":0,"objective":false,"entry":false,"entry_weapon":null},"76561198038246134":{"kills":0,"headshots":0,"assists":0,"time_alive":69.84375,"damage":0,"objective":false,"entry":false,"entry_weapon":null}}},{"round_start_time":182.2734375,"round_end_time":240.2265625,"t":"team_Samaly","ct":"team_noctias","winner":"team_Samaly","players":{"0":{"kills":0,"headshots":0,"assists":0,"time_alive":-1,"damage":0,"objective":false,"entry":false,"entry_weapon":null},"76561198020317127":{"kills":1,"headshots":1,"assists":0,"time_alive":32.796875,"damage":100,"objective":false,"entry":true,"entry_weapon":"hkp2000","wp_hkp2000":1,"wp_hkp2000_hs":1},"undefined":{"kills":0,"headshots":0,"assists":4,"time_alive":-1,"damage":0,"objective":false,"entry":false,"entry_weapon":null},"76561197961085746":{"kills":0,"headshots":0,"assists":0,"time_alive":27,"damage":0,"objective":false,"entry":false,"entry_weapon":null},"76561198842037276":{"kills":1,"headshots":0,"assists":1,"time_alive":49.546875,"damage":126,"objective":false,"entry":false,"entry_weapon":null,"wp_mac10":1,"wp_mac10_hs":0},"76561198139429381":{"kills":2,"headshots":0,"assists":0,"time_alive":-1,"damage":72,"objective":true,"entry":false,"entry_weapon":null,"wp_hegrenade":1,"wp_hegrenade_hs":0,"wp_ump45":1,"wp_ump45_hs":0},"76561198062153950":{"kills":0,"headshots":0,"assists":1,"time_alive":43.015625,"damage":42,"objective":false,"entry":false,"entry_weapon":null},"76561198033939559":{"kills":0,"headshots":0,"assists":1,"time_alive":40.359375,"damage":42,"objective":false,"entry":false,"entry_weapon":null},"76561197993761807":{"kills":2,"headshots":1,"assists":0,"time_alive":57.953125,"damage":88,"objective":false,"entry":false,"entry_weapon":null,"wp_ump45":2,"wp_ump45_hs":1},"76561198120286262":{"kills":2,"headshots":1,"assists":0,"time_alive":-1,"damage":260,"objective":false,"entry":false,"entry_weapon":null,"wp_mac10":2,"wp_mac10_hs":1},"76561198162875654":{"kills":0,"headshots":0,"assists":1,"time_alive":43.015625,"damage":87,"objective":false,"entry":false,"entry_weapon":null},"76561198038246134":{"kills":0,"headshots":0,"assists":0,"time_alive":45.25,"damage":36,"objective":false,"entry":false,"entry_weapon":null}}},{"round_start_time":245.2265625,"round_end_time":387.0625,"t":"team_Samaly","ct":"team_noctias","winner":"team_Samaly","players":{"0":{"kills":0,"headshots":0,"assists":0,"time_alive":-1,"damage":0,"objective":false,"entry":false,"entry_weapon":null},"76561198038246134":{"kills":3,"headshots":0,"assists":1,"time_alive":131.1484375,"damage":317,"objective":false,"entry":true,"entry_weapon":"famas","wp_famas":3,"wp_famas_hs":0},"undefined":{"kills":0,"headshots":0,"assists":6,"time_alive":-1,"damage":0,"objective":false,"entry":false,"entry_weapon":null},"76561198842037276":{"kills":0,"headshots":0,"assists":0,"time_alive":24.8046875,"damage":33,"objective":false,"entry":false,"entry_weapon":null},"76561198033939559":{"kills":1,"headshots":0,"assists":0,"time_alive":29.9609375,"damage":5,"objective":false,"entry":false,"entry_weapon":null,"wp_m4a1":1,"wp_m4a1_hs":0},"76561198139429381":{"kills":0,"headshots":0,"assists":0,"time_alive":26.6953125,"damage":5,"objective":false,"entry":false,"entry_weapon":null},"76561198120286262":{"kills":2,"headshots":2,"assists":1,"time_alive":122.8046875,"damage":272,"objective":false,"entry":false,"entry_weapon":null,"wp_ak47":2,"wp_ak47_hs":2},"76561197961085746":{"kills":0,"headshots":0,"assists":0,"time_alive":52.5078125,"damage":26,"objective":false,"entry":false,"entry_weapon":null},"76561198162875654":{"kills":0,"headshots":0,"assists":1,"time_alive":69.5078125,"damage":78,"objective":false,"entry":false,"entry_weapon":null},"76561198062153950":{"kills":3,"headshots":1,"assists":0,"time_alive":-1,"damage":164,"objective":true,"entry":false,"entry_weapon":null,"wp_ak47":3,"wp_ak47_hs":1},"76561197993761807":{"kills":0,"headshots":0,"assists":0,"time_alive":131.3515625,"damage":0,"objective":false,"entry":false,"entry_weapon":null},"76561198020317127":{"kills":0,"headshots":0,"assists":0,"time_alive":141.8359375,"damage":49,"objective":false,"entry":false,"entry_weapon":null}}},{"round_start_time":392.078125,"round_end_time":516.0859375,"t":"team_Samaly","ct":"team_noctias","winner":"team_Samaly","players":{"0":{"kills":0,"headshots":0,"assists":0,"time_alive":-1,"damage":0,"objective":false,"entry":false,"entry_weapon":null},"76561197961085746":{"kills":1,"headshots":1,"assists":0,"time_alive":32.5703125,"damage":142,"objective":false,"entry":true,"entry_weapon":"ak47","wp_ak47":1,"wp_ak47_hs":1},"undefined":{"kills":0,"headshots":0,"assists":6,"time_alive":-1,"damage":0,"objective":false,"entry":false,"entry_weapon":null},"76561198033939559":{"kills":0,"headshots":0,"assists":0,"time_alive":20.3359375,"damage":0,"objective":false,"entry":false,"entry_weapon":null},"76561198162875654":{"kills":2,"headshots":2,"assists":0,"time_alive":-1,"damage":226,"objective":false,"entry":false,"entry_weapon":null,"wp_deagle":2,"wp_deagle_hs":2},"76561198120286262":{"kills":1,"headshots":0,"assists":0,"time_alive":43.8984375,"damage":100,"objective":false,"entry":false,"entry_weapon":null,"wp_ak47":1,"wp_ak47_hs":0},"76561198020317127":{"kills":0,"headshots":0,"assists":0,"time_alive":38.0078125,"damage":0,"objective":false,"entry":false,"entry_weapon":null},"76561198062153950":{"kills":1,"headshots":0,"assists":0,"time_alive":-1,"damage":8,"objective":false,"entry":false,"entry_weapon":null,"wp_ak47":1,"wp_ak47_hs":0},"76561198842037276":{"kills":0,"headshots":0,"assists":1,"time_alive":121.5546875,"damage":50,"objective":true,"entry":false,"entry_weapon":null},"76561197993761807":{"kills":0,"headshots":0,"assists":0,"time_alive":38.0390625,"damage":13,"objective":false,"entry":false,"entry_weapon":null},"76561198038246134":{"kills":2,"headshots":2,"assists":0,"time_alive":-1,"damage":161,"objective":false,"entry":false,"entry_weapon":null,"wp_deagle":1,"wp_deagle_hs":1,"wp_ak47":1,"wp_ak47_hs":1},"76561198139429381":{"kills":0,"headshots":0,"assists":0,"time_alive":74.6015625,"damage":0,"objective":false,"entry":false,"entry_weapon":null}}},{"round_start_time":521.0859375,"round_end_time":592.1328125,"t":"team_Samaly","ct":"team_noctias","winner":"team_Samaly","players":{"0":{"kills":0,"headshots":0,"assists":0,"time_alive":-1,"damage":0,"objective":false,"entry":false,"entry_weapon":null},"76561198033939559":{"kills":1,"headshots":0,"assists":0,"time_alive":48.296875,"damage":80,"objective":false,"entry":true,"entry_weapon":"m4a1","wp_m4a1":1,"wp_m4a1_hs":0},"undefined":{"kills":0,"headshots":0,"assists":6,"time_alive":-1,"damage":0,"objective":false,"entry":false,"entry_weapon":null},"76561198842037276":{"kills":0,"headshots":0,"assists":0,"time_alive":38.015625,"damage":0,"objective":false,"entry":false,"entry_weapon":null},"76561198062153950":{"kills":1,"headshots":1,"assists":0,"time_alive":66.328125,"damage":100,"objective":false,"entry":false,"entry_weapon":null,"wp_ak47":1,"wp_ak47_hs":1},"76561198038246134":{"kills":0,"headshots":0,"assists":2,"time_alive":39.21875,"damage":123,"objective":false,"entry":false,"entry_weapon":null},"76561198139429381":{"kills":3,"headshots":2,"assists":0,"time_alive":-1,"damage":300,"objective":false,"entry":false,"entry_weapon":null,"wp_ak47":3,"wp_ak47_hs":2},"76561198162875654":{"kills":1,"headshots":0,"assists":0,"time_alive":56.28125,"damage":88,"objective":false,"entry":false,"entry_weapon":null,"wp_ak47":1,"wp_ak47_hs":0},"76561197961085746":{"kills":0,"headshots":0,"assists":0,"time_alive":54.65625,"damage":0,"objective":false,"entry":false,"entry_weapon":null},"76561198120286262":{"kills":1,"headshots":0,"assists":0,"time_alive":-1,"damage":82,"objective":false,"entry":false,"entry_weapon":null,"wp_ak47":1,"wp_ak47_hs":0},"76561197993761807":{"kills":0,"headshots":0,"assists":0,"time_alive":61.953125,"damage":0,"objective":false,"entry":false,"entry_weapon":null},"76561198020317127":{"kills":1,"headshots":0,"assists":0,"time_alive":71.046875,"damage":116,"objective":false,"entry":false,"entry_weapon":null,"wp_awp":1,"wp_awp_hs":0}}},{"round_start_time":597.1484375,"round_end_time":680.6484375,"t":"team_Samaly","ct":"team_noctias","winner":"team_noctias","players":{"0":{"kills":0,"headshots":0,"assists":0,"time_alive":-1,"damage":0,"objective":false,"entry":false,"entry_weapon":null},"76561198139429381":{"kills":1,"headshots":1,"assists":0,"time_alive":83.5,"damage":100,"objective":false,"entry":true,"entry_weapon":"ak47","wp_ak47":1,"wp_ak47_hs":1},"undefined":{"kills":0,"headshots":0,"assists":6,"time_alive":-1,"damage":0,"objective":false,"entry":false,"entry_weapon":null},"76561197993761807":{"kills":0,"headshots":0,"assists":1,"time_alive":25.640625,"damage":57,"objective":false,"entry":false,"entry_weapon":null},"76561198842037276":{"kills":1,"headshots":1,"assists":0,"time_alive":65.515625,"damage":127,"objective":false,"entry":false,"entry_weapon":null,"wp_ak47":1,"wp_ak47_hs":1},"76561198033939559":{"kills":0,"headshots":0,"assists":0,"time_alive":45.5625,"damage":0,"objective":false,"entry":false,"entry_weapon":null},"76561198020317127":{"kills":3,"headshots":2,"assists":0,"time_alive":-1,"damage":300,"objective":false,"entry":false,"entry_weapon":null,"wp_m4a1":3,"wp_m4a1_hs":2},"76561198120286262":{"kills":0,"headshots":0,"assists":0,"time_alive":48.765625,"damage":0,"objective":false,"entry":false,"entry_weapon":null},"76561198062153950":{"kills":0,"headshots":0,"assists":0,"time_alive":60.125,"damage":54,"objective":false,"entry":false,"entry_weapon":null},"76561198162875654":{"kills":1,"headshots":0,"assists":0,"time_alive":-1,"damage":100,"objective":false,"entry":false,"entry_weapon":null,"wp_awp":1,"wp_awp_hs":0},"76561197961085746":{"kills":0,"headshots":0,"assists":0,"time_alive":65.96875,"damage":0,"objective":false,"entry":false,"entry_weapon":null},"76561198038246134":{"kills":1,"headshots":0,"assists":0,"time_alive":-1,"damage":43,"objective":false,"entry":false,"entry_weapon":null,"wp_m4a1":1,"wp_m4a1_hs":0}}},{"round_start_time":685.6484375,"round_end_time":781.671875,"t":"team_Samaly","ct":"team_noctias","winner":"team_Samaly","players":{"0":{"kills":0,"headshots":0,"assists":0,"time_alive":-1,"damage":0,"objective":false,"entry":false,"entry_weapon":null},"76561198842037276":{"kills":1,"headshots":1,"assists":0,"time_alive":37.4453125,"damage":100,"objective":false,"entry":true,"entry_weapon":"deagle","wp_deagle":1,"wp_deagle_hs":1},"undefined":{"kills":0,"headshots":0,"assists":8,"time_alive":-1,"damage":0,"objective":false,"entry":false,"entry_weapon":null},"76561197993761807":{"kills":0,"headshots":0,"assists":0,"time_alive":20.1953125,"damage":0,"objective":false,"entry":false,"entry_weapon":null},"76561198162875654":{"kills":2,"headshots":0,"assists":0,"time_alive":51.7734375,"damage":200,"objective":false,"entry":false,"entry_weapon":null,"wp_awp":2,"wp_awp_hs":0},"76561198139429381":{"kills":3,"headshots":3,"assists":0,"time_alive":78.9921875,"damage":328,"objective":false,"entry":false,"entry_weapon":null,"wp_ak47":3,"wp_ak47_hs":3},"76561198020317127":{"kills":0,"headshots":0,"assists":0,"time_alive":38.7265625,"damage":27,"objective":false,"entry":false,"entry_weapon":null},"76561198120286262":{"kills":0,"headshots":0,"assists":0,"time_alive":44.9453125,"damage":0,"objective":false,"entry":false,"entry_weapon":null},"76561198062153950":{"kills":0,"headshots":0,"assists":0,"time_alive":-1,"damage":0,"objective":true,"entry":false,"entry_weapon":null},"76561198033939559":{"kills":0,"headshots":0,"assists":0,"time_alive":60.3359375,"damage":0,"objective":false,"entry":false,"entry_weapon":null},"76561198038246134":{"kills":2,"headshots":1,"assists":0,"time_alive":-1,"damage":173,"objective":false,"entry":false,"entry_weapon":null,"wp_ak47":2,"wp_ak47_hs":1},"76561197961085746":{"kills":0,"headshots":0,"assists":0,"time_alive":64.4609375,"damage":30,"objective":false,"entry":false,"entry_weapon":null}}},{"round_start_time":786.671875,"round_end_time":851.8984375,"t":"team_Samaly","ct":"team_noctias","winner":"team_Samaly","players":{"0":{"kills":0,"headshots":0,"assists":0,"time_alive":-1,"damage":0,"objective":false,"entry":false,"entry_weapon":null},"76561198842037276":{"kills":3,"headshots":0,"assists":0,"time_alive":61.2578125,"damage":300,"objective":false,"entry":true,"entry_weapon":"ak47","wp_ak47":3,"wp_ak47_hs":0},"undefined":{"kills":0,"headshots":0,"assists":8,"time_alive":-1,"damage":0,"objective":false,"entry":false,"entry_weapon":null},"76561198033939559":{"kills":0,"headshots":0,"assists":0,"time_alive":22.6484375,"damage":0,"objective":false,"entry":false,"entry_weapon":null},"76561198162875654":{"kills":0,"headshots":0,"assists":0,"time_alive":30.7890625,"damage":0,"objective":false,"entry":false,"entry_weapon":null},"76561198038246134":{"kills":0,"headshots":0,"assists":0,"time_alive":46.2109375,"damage":0,"objective":false,"entry":false,"entry_weapon":null},"76561198020317127":{"kills":1,"headshots":0,"assists":0,"time_alive":57.3984375,"damage":203,"objective":false,"entry":false,"entry_weapon":null,"wp_deagle":1,"wp_deagle_hs":0},"76561198062153950":{"kills":0,"headshots":0,"assists":0,"time_alive":47.0078125,"damage":0,"objective":false,"entry":false,"entry_weapon":null},"76561198139429381":{"kills":2,"headshots":1,"assists":0,"time_alive":-1,"damage":199,"objective":false,"entry":false,"entry_weapon":null,"wp_ak47":2,"wp_ak47_hs":1},"76561197993761807":{"kills":2,"headshots":0,"assists":0,"time_alive":65.2265625,"damage":200,"objective":false,"entry":false,"entry_weapon":null,"wp_awp":2,"wp_awp_hs":0},"76561197961085746":{"kills":0,"headshots":0,"assists":0,"time_alive":65.0234375,"damage":0,"objective":false,"entry":false,"entry_weapon":null},"76561198120286262":{"kills":0,"headshots":0,"assists":0,"time_alive":-1,"damage":1,"objective":false,"entry":false,"entry_weapon":null}}},{"round_start_time":856.9140625,"round_end_time":897.84375,"t":"team_Samaly","ct":"team_noctias","winner":"team_Samaly","players":{"0":{"kills":0,"headshots":0,"assists":0,"time_alive":-1,"damage":0,"objective":false,"entry":false,"entry_weapon":null},"76561198139429381":{"kills":1,"headshots":1,"assists":0,"time_alive":24.8984375,"damage":100,"objective":false,"entry":true,"entry_weapon":"awp","wp_awp":1,"wp_awp_hs":1},"undefined":{"kills":0,"headshots":0,"assists":7,"time_alive":-1,"damage":0,"objective":false,"entry":false,"entry_weapon":null},"76561198162875654":{"kills":0,"headshots":0,"assists":0,"time_alive":20.8046875,"damage":0,"objective":false,"entry":false,"entry_weapon":null},"76561197993761807":{"kills":2,"headshots":0,"assists":0,"time_alive":40.9296875,"damage":199,"objective":false,"entry":false,"entry_weapon":null,"wp_p250":1,"wp_p250_hs":0,"wp_awp":1,"wp_awp_hs":0},"76561197961085746":{"kills":1,"headshots":1,"assists":0,"time_alive":-1,"damage":100,"objective":false,"entry":false,"entry_weapon":null,"wp_ak47":1,"wp_ak47_hs":1},"76561198033939559":{"kills":0,"headshots":0,"assists":0,"time_alive":27.0078125,"damage":0,"objective":false,"entry":false,"entry_weapon":null},"76561198120286262":{"kills":1,"headshots":1,"assists":0,"time_alive":-1,"damage":100,"objective":false,"entry":false,"entry_weapon":null,"wp_ak47":1,"wp_ak47_hs":1},"76561198020317127":{"kills":0,"headshots":0,"assists":0,"time_alive":28.9765625,"damage":52,"objective":false,"entry":false,"entry_weapon":null},"76561198062153950":{"kills":0,"headshots":0,"assists":0,"time_alive":36.4140625,"damage":0,"objective":false,"entry":false,"entry_weapon":null},"76561198842037276":{"kills":2,"headshots":1,"assists":0,"time_alive":-1,"damage":200,"objective":false,"entry":false,"entry_weapon":null,"wp_ak47":2,"wp_ak47_hs":1},"76561198038246134":{"kills":0,"headshots":0,"assists":0,"time_alive":38.1953125,"damage":41,"objective":false,"entry":false,"entry_weapon":null}}},{"round_start_time":902.8984375,"round_end_time":983.09375,"t":"team_Samaly","ct":"team_noctias","winner":"team_noctias","players":{"0":{"kills":0,"headshots":0,"assists":0,"time_alive":-1,"damage":0,"objective":false,"entry":false,"entry_weapon":null},"76561197993761807":{"kills":3,"headshots":0,"assists":0,"time_alive":-1,"damage":300,"objective":false,"entry":true,"entry_weapon":"awp","wp_awp":3,"wp_awp_hs":0},"undefined":{"kills":0,"headshots":0,"assists":5,"time_alive":-1,"damage":0,"objective":false,"entry":false,"entry_weapon":null},"76561197961085746":{"kills":0,"headshots":0,"assists":0,"time_alive":20.6328125,"damage":0,"objective":false,"entry":false,"entry_weapon":null},"76561198139429381":{"kills":0,"headshots":0,"assists":0,"time_alive":60.3828125,"damage":0,"objective":false,"entry":false,"entry_weapon":null},"76561198842037276":{"kills":1,"headshots":1,"assists":0,"time_alive":67.0859375,"damage":100,"objective":false,"entry":false,"entry_weapon":null,"wp_ak47":1,"wp_ak47_hs":1},"76561198038246134":{"kills":0,"headshots":0,"assists":1,"time_alive":64.3984375,"damage":84,"objective":false,"entry":false,"entry_weapon":null},"76561198033939559":{"kills":1,"headshots":0,"assists":0,"time_alive":-1,"damage":16,"objective":false,"entry":false,"entry_weapon":null,"wp_m4a1":1,"wp_m4a1_hs":0},"76561198162875654":{"kills":1,"headshots":1,"assists":0,"time_alive":-1,"damage":100,"objective":false,"entry":false,"entry_weapon":null,"wp_awp":1,"wp_awp_hs":1},"76561198120286262":{"kills":0,"headshots":0,"assists":0,"time_alive":78.0703125,"damage":0,"objective":false,"entry":false,"entry_weapon":null},"76561198062153950":{"kills":0,"headshots":0,"assists":0,"time_alive":80.1953125,"damage":26,"objective":false,"entry":false,"entry_weapon":null},"76561198020317127":{"kills":0,"headshots":0,"assists":0,"time_alive":-1,"damage":0,"objective":false,"entry":false,"entry_weapon":null}}},{"round_start_time":988.1484375,"round_end_time":1065.8203125,"t":"team_Samaly","ct":"team_noctias","winner":"team_Samaly","players":{"0":{"kills":0,"headshots":0,"assists":0,"time_alive":-1,"damage":0,"objective":false,"entry":false,"entry_weapon":null},"76561197993761807":{"kills":1,"headshots":0,"assists":0,"time_alive":25.171875,"damage":100,"objective":false,"entry":true,"entry_weapon":"awp","wp_awp":1,"wp_awp_hs":0},"undefined":{"kills":0,"headshots":0,"assists":6,"time_alive":-1,"damage":0,"objective":false,"entry":false,"entry_weapon":null},"76561198842037276":{"kills":0,"headshots":0,"assists":0,"time_alive":21.125,"damage":0,"objective":false,"entry":false,"entry_weapon":null},"76561198120286262":{"kills":2,"headshots":0,"assists":1,"time_alive":-1,"damage":286,"objective":false,"entry":false,"entry_weapon":null,"wp_awp":2,"wp_awp_hs":0},"76561198020317127":{"kills":1,"headshots":1,"assists":0,"time_alive":44.1875,"damage":100,"objective":false,"entry":false,"entry_weapon":null,"wp_ak47":1,"wp_ak47_hs":1},"76561198139429381":{"kills":0,"headshots":0,"assists":1,"time_alive":42.640625,"damage":68,"objective":false,"entry":false,"entry_weapon":null},"76561198062153950":{"kills":1,"headshots":1,"assists":0,"time_alive":59.609375,"damage":32,"objective":true,"entry":false,"entry_weapon":null,"wp_ak47":1,"wp_ak47_hs":1},"76561197961085746":{"kills":2,"headshots":0,"assists":0,"time_alive":-1,"damage":114,"objective":false,"entry":false,"entry_weapon":null,"wp_ak47":2,"wp_ak47_hs":0},"76561198038246134":{"kills":0,"headshots":0,"assists":0,"time_alive":52.46875,"damage":0,"objective":false,"entry":false,"entry_weapon":null},"76561198033939559":{"kills":1,"headshots":0,"assists":0,"time_alive":70.875,"damage":77,"objective":false,"entry":false,"entry_weapon":null,"wp_m4a1":1,"wp_m4a1_hs":0},"76561198162875654":{"kills":0,"headshots":0,"assists":0,"time_alive":77.671875,"damage":75,"objective":false,"entry":false,"entry_weapon":null}}},{"round_start_time":1070.8984375,"round_end_time":1177.5703125,"t":"team_Samaly","ct":"team_noctias","winner":"team_Samaly","players":{"0":{"kills":0,"headshots":0,"assists":0,"time_alive":-1,"damage":0,"objective":false,"entry":false,"entry_weapon":null},"76561198842037276":{"kills":1,"headshots":0,"assists":0,"time_alive":60.90625,"damage":65,"objective":false,"entry":true,"entry_weapon":"ak47","wp_ak47":1,"wp_ak47_hs":0},"76561198139429381":{"kills":0,"headshots":0,"assists":1,"time_alive":58.40625,"damage":53,"objective":false,"entry":false,"entry_weapon":null},"76561198033939559":{"kills":0,"headshots":0,"assists":0,"time_alive":48.25,"damage":0,"objective":false,"entry":false,"entry_weapon":null},"76561197993761807":{"kills":1,"headshots":0,"assists":0,"time_alive":89.671875,"damage":100,"objective":false,"entry":false,"entry_weapon":null,"wp_usp_silencer":1,"wp_usp_silencer_hs":0},"undefined":{"kills":0,"headshots":0,"assists":3,"time_alive":-1,"damage":0,"objective":false,"entry":false,"entry_weapon":null},"76561197961085746":{"kills":0,"headshots":0,"assists":1,"time_alive":55.921875,"damage":73,"objective":false,"entry":false,"entry_weapon":null},"76561198038246134":{"kills":2,"headshots":0,"assists":0,"time_alive":106.671875,"damage":107,"objective":false,"entry":false,"entry_weapon":null,"wp_p250":2,"wp_p250_hs":0},"76561198162875654":{"kills":0,"headshots":0,"assists":1,"time_alive":97.96875,"damage":149,"objective":false,"entry":false,"entry_weapon":null},"76561198062153950":{"kills":3,"headshots":2,"assists":0,"time_alive":-1,"damage":156,"objective":true,"entry":false,"entry_weapon":null,"wp_ak47":3,"wp_ak47_hs":2},"76561198120286262":{"kills":1,"headshots":0,"assists":2,"time_alive":-1,"damage":137,"objective":false,"entry":false,"entry_weapon":null,"wp_ak47":1,"wp_ak47_hs":0},"76561198020317127":{"kills":0,"headshots":0,"assists":0,"time_alive":61.390625,"damage":0,"objective":false,"entry":false,"entry_weapon":null}}},{"round_start_time":1182.5703125,"round_end_time":1281.7265625,"t":"team_Samaly","ct":"team_noctias","winner":"team_Samaly","players":{"0":{"kills":0,"headshots":0,"assists":0,"time_alive":-1,"damage":0,"objective":false,"entry":false,"entry_weapon":null},"76561198842037276":{"kills":1,"headshots":1,"assists":1,"time_alive":31.484375,"damage":185,"objective":false,"entry":true,"entry_weapon":"sg556","wp_sg556":1,"wp_sg556_hs":1},"undefined":{"kills":0,"headshots":0,"assists":6,"time_alive":-1,"damage":0,"objective":false,"entry":false,"entry_weapon":null},"76561198038246134":{"kills":0,"headshots":0,"assists":0,"time_alive":21.21875,"damage":0,"objective":false,"entry":false,"entry_weapon":null},"76561198062153950":{"kills":1,"headshots":0,"assists":0,"time_alive":34.890625,"damage":100,"objective":false,"entry":false,"entry_weapon":null,"wp_ak47":1,"wp_ak47_hs":0},"76561198020317127":{"kills":0,"headshots":0,"assists":1,"time_alive":30.8125,"damage":53,"objective":false,"entry":false,"entry_weapon":null},"76561198033939559":{"kills":1,"headshots":0,"assists":0,"time_alive":56.359375,"damage":100,"objective":false,"entry":false,"entry_weapon":null,"wp_deagle":1,"wp_deagle_hs":0},"76561198162875654":{"kills":1,"headshots":0,"assists":0,"time_alive":37.015625,"damage":85,"objective":false,"entry":false,"entry_weapon":null,"wp_deagle":1,"wp_deagle_hs":0},"76561198120286262":{"kills":1,"headshots":0,"assists":0,"time_alive":88.203125,"damage":100,"objective":false,"entry":false,"entry_weapon":null,"wp_ak47":1,"wp_ak47_hs":0},"76561197961085746":{"kills":1,"headshots":0,"assists":0,"time_alive":97.59375,"damage":15,"objective":false,"entry":false,"entry_weapon":null,"wp_awp":1,"wp_awp_hs":0},"76561198139429381":{"kills":0,"headshots":0,"assists":0,"time_alive":-1,"damage":18,"objective":true,"entry":false,"entry_weapon":null},"76561197993761807":{"kills":2,"headshots":1,"assists":0,"time_alive":-1,"damage":162,"objective":false,"entry":false,"entry_weapon":null,"wp_usp_silencer":2,"wp_usp_silencer_hs":1}}},{"round_start_time":1286.7265625,"round_end_time":1410.796875,"t":"team_Samaly","ct":"team_noctias","winner":"team_Samaly","players":{"0":{"kills":0,"headshots":0,"assists":0,"time_alive":-1,"damage":0,"objective":false,"entry":false,"entry_weapon":null},"76561198842037276":{"kills":2,"headshots":1,"assists":0,"time_alive":-1,"damage":284,"objective":false,"entry":true,"entry_weapon":"ak47","wp_ak47":1,"wp_ak47_hs":1,"wp_knife_m9_bayonet":1,"wp_knife_m9_bayonet_hs":0},"undefined":{"kills":0,"headshots":0,"assists":6,"time_alive":-1,"damage":0,"objective":false,"entry":false,"entry_weapon":null},"76561198033939559":{"kills":0,"headshots":0,"assists":0,"time_alive":41.6015625,"damage":24,"objective":false,"entry":false,"entry_weapon":null},"76561198139429381":{"kills":1,"headshots":1,"assists":0,"time_alive":67.4296875,"damage":100,"objective":false,"entry":false,"entry_weapon":null,"wp_ak47":1,"wp_ak47_hs":1},"76561198038246134":{"kills":0,"headshots":0,"assists":0,"time_alive":66.5546875,"damage":61,"objective":false,"entry":false,"entry_weapon":null},"76561197993761807":{"kills":1,"headshots":0,"assists":0,"time_alive":74.9765625,"damage":79,"objective":false,"entry":false,"entry_weapon":null,"wp_awp":1,"wp_awp_hs":0},"76561198162875654":{"kills":1,"headshots":1,"assists":0,"time_alive":-1,"damage":100,"objective":false,"entry":false,"entry_weapon":null,"wp_awp":1,"wp_awp_hs":1},"76561198062153950":{"kills":0,"headshots":0,"assists":0,"time_alive":74.9296875,"damage":0,"objective":false,"entry":false,"entry_weapon":null},"76561198120286262":{"kills":0,"headshots":0,"assists":0,"time_alive":-1,"damage":0,"objective":true,"entry":false,"entry_weapon":null},"76561197961085746":{"kills":1,"headshots":0,"assists":0,"time_alive":-1,"damage":100,"objective":false,"entry":false,"entry_weapon":null,"wp_awp":1,"wp_awp_hs":0},"76561198020317127":{"kills":0,"headshots":0,"assists":0,"time_alive":93.1015625,"damage":0,"objective":false,"entry":false,"entry_weapon":null}}},{"round_start_time":1415.796875,"round_end_time":1496.9453125,"t":"team_Samaly","ct":"team_noctias","winner":"team_Samaly","players":{"0":{"kills":0,"headshots":0,"assists":0,"time_alive":-1,"damage":0,"objective":false,"entry":false,"entry_weapon":null},"76561197961085746":{"kills":3,"headshots":1,"assists":0,"time_alive":50.1640625,"damage":300,"objective":false,"entry":true,"entry_weapon":"awp","wp_awp":3,"wp_awp_hs":1},"undefined":{"kills":0,"headshots":0,"assists":6,"time_alive":-1,"damage":0,"objective":false,"entry":false,"entry_weapon":null},"76561198033939559":{"kills":0,"headshots":0,"assists":0,"time_alive":29.1328125,"damage":61,"objective":false,"entry":false,"entry_weapon":null},"76561198038246134":{"kills":1,"headshots":1,"assists":0,"time_alive":40.1015625,"damage":100,"objective":false,"entry":false,"entry_weapon":null,"wp_m4a1":1,"wp_m4a1_hs":1},"76561198062153950":{"kills":0,"headshots":0,"assists":0,"time_alive":39.7578125,"damage":0,"objective":false,"entry":false,"entry_weapon":null},"76561197993761807":{"kills":0,"headshots":0,"assists":0,"time_alive":45.0234375,"damage":0,"objective":false,"entry":false,"entry_weapon":null},"76561198162875654":{"kills":1,"headshots":0,"assists":1,"time_alive":65.7578125,"damage":173,"objective":false,"entry":false,"entry_weapon":null,"wp_awp":1,"wp_awp_hs":0},"76561198020317127":{"kills":1,"headshots":0,"assists":0,"time_alive":81.1484375,"damage":16,"objective":false,"entry":false,"entry_weapon":null,"wp_mag7":1,"wp_mag7_hs":0},"76561198139429381":{"kills":0,"headshots":0,"assists":0,"time_alive":57.7265625,"damage":0,"objective":false,"entry":false,"entry_weapon":null},"76561198842037276":{"kills":1,"headshots":0,"assists":0,"time_alive":-1,"damage":36,"objective":false,"entry":false,"entry_weapon":null,"wp_awp":1,"wp_awp_hs":0},"76561198120286262":{"kills":1,"headshots":0,"assists":1,"time_alive":-1,"damage":155,"objective":true,"entry":false,"entry_weapon":null,"wp_ak47":1,"wp_ak47_hs":0}}},{"round_start_time":1511.9453125,"round_end_time":1553.96875,"t":"team_Samaly","ct":"team_noctias","winner":"team_Samaly","players":{"0":{"kills":0,"headshots":0,"assists":0,"time_alive":-1,"damage":0,"objective":false,"entry":false,"entry_weapon":null},"76561198062153950":{"kills":2,"headshots":2,"assists":0,"time_alive":-1,"damage":216,"objective":false,"entry":true,"entry_weapon":"usp_silencer","wp_usp_silencer":2,"wp_usp_silencer_hs":2},"undefined":{"kills":0,"headshots":0,"assists":6,"time_alive":-1,"damage":0,"objective":false,"entry":false,"entry_weapon":null},"76561198162875654":{"kills":0,"headshots":0,"assists":0,"time_alive":26.6171875,"damage":36,"objective":false,"entry":false,"entry_weapon":null},"76561198120286262":{"kills":3,"headshots":3,"assists":0,"time_alive":-1,"damage":284,"objective":false,"entry":false,"entry_weapon":null,"wp_usp_silencer":3,"wp_usp_silencer_hs":3},"76561198020317127":{"kills":0,"headshots":0,"assists":0,"time_alive":28.2890625,"damage":0,"objective":false,"entry":false,"entry_weapon":null},"76561198033939559":{"kills":0,"headshots":0,"assists":0,"time_alive":30.8515625,"damage":0,"objective":false,"entry":false,"entry_weapon":null},"76561198038246134":{"kills":1,"headshots":1,"assists":0,"time_alive":42.0234375,"damage":88,"objective":false,"entry":false,"entry_weapon":null,"wp_glock":1,"wp_glock_hs":1},"76561198139429381":{"kills":0,"headshots":0,"assists":0,"time_alive":33.9921875,"damage":0,"objective":false,"entry":false,"entry_weapon":null},"76561197993761807":{"kills":0,"headshots":0,"assists":0,"time_alive":39.0859375,"damage":12,"objective":false,"entry":false,"entry_weapon":null},"76561198842037276":{"kills":0,"headshots":0,"assists":0,"time_alive":-1,"damage":0,"objective":false,"entry":false,"entry_weapon":null},"76561197961085746":{"kills":0,"headshots":0,"assists":0,"time_alive":-1,"damage":0,"objective":false,"entry":false,"entry_weapon":null}}},{"round_start_time":1558.96875,"round_end_time":1622.71875,"t":"team_noctias","ct":"team_Samaly","winner":"team_noctias","players":{"0":{"kills":0,"headshots":0,"assists":0,"time_alive":-1,"damage":0,"objective":false,"entry":false,"entry_weapon":null},"76561197993761807":{"kills":4,"headshots":2,"assists":0,"time_alive":-1,"damage":221,"objective":false,"entry":true,"entry_weapon":"glock","wp_glock":1,"wp_glock_hs":0,"wp_ump45":3,"wp_ump45_hs":2},"76561198038246134":{"kills":0,"headshots":0,"assists":2,"time_alive":62,"damage":109,"objective":false,"entry":false,"entry_weapon":null},"76561197961085746":{"kills":0,"headshots":0,"assists":1,"time_alive":43.6875,"damage":153,"objective":false,"entry":false,"entry_weapon":null},"76561198842037276":{"kills":1,"headshots":0,"assists":0,"time_alive":63.75,"damage":96,"objective":false,"entry":false,"entry_weapon":null,"wp_famas":1,"wp_famas_hs":0},"undefined":{"kills":0,"headshots":0,"assists":6,"time_alive":-1,"damage":0,"objective":false,"entry":false,"entry_weapon":null},"76561198020317127":{"kills":0,"headshots":0,"assists":0,"time_alive":43.828125,"damage":52,"objective":false,"entry":false,"entry_weapon":null},"76561198062153950":{"kills":1,"headshots":1,"assists":0,"time_alive":48.625,"damage":84,"objective":false,"entry":false,"entry_weapon":null,"wp_m4a1":1,"wp_m4a1_hs":1},"76561198162875654":{"kills":0,"headshots":0,"assists":0,"time_alive":46.0625,"damage":10,"objective":false,"entry":false,"entry_weapon":null},"76561198033939559":{"kills":1,"headshots":1,"assists":0,"time_alive":55.53125,"damage":108,"objective":true,"entry":false,"entry_weapon":null,"wp_glock":1,"wp_glock_hs":1},"76561198139429381":{"kills":1,"headshots":1,"assists":0,"time_alive":56.390625,"damage":84,"objective":false,"entry":false,"entry_weapon":null,"wp_ump45":1,"wp_ump45_hs":1},"76561198120286262":{"kills":1,"headshots":0,"assists":0,"time_alive":63.21875,"damage":58,"objective":false,"entry":false,"entry_weapon":null,"wp_m4a1":1,"wp_m4a1_hs":0}}},{"round_start_time":1627.7734375,"round_end_time":1707.203125,"t":"team_noctias","ct":"team_Samaly","winner":"team_noctias","players":{"0":{"kills":0,"headshots":0,"assists":0,"time_alive":-1,"damage":0,"objective":false,"entry":false,"entry_weapon":null},"76561198020317127":{"kills":1,"headshots":1,"assists":0,"time_alive":45.7109375,"damage":100,"objective":false,"entry":true,"entry_weapon":"ak47","wp_ak47":1,"wp_ak47_hs":1},"undefined":{"kills":0,"headshots":0,"assists":5,"time_alive":-1,"damage":0,"objective":false,"entry":false,"entry_weapon":null},"76561198842037276":{"kills":0,"headshots":0,"assists":1,"time_alive":26.5234375,"damage":69,"objective":false,"entry":false,"entry_weapon":null},"76561198162875654":{"kills":2,"headshots":1,"assists":0,"time_alive":-1,"damage":200,"objective":false,"entry":false,"entry_weapon":null,"wp_ak47":2,"wp_ak47_hs":1},"76561197961085746":{"kills":0,"headshots":0,"assists":0,"time_alive":42.4140625,"damage":0,"objective":false,"entry":false,"entry_weapon":null},"76561198062153950":{"kills":1,"headshots":0,"assists":0,"time_alive":50.3515625,"damage":31,"objective":false,"entry":false,"entry_weapon":null,"wp_deagle":1,"wp_deagle_hs":0},"76561198033939559":{"kills":1,"headshots":1,"assists":0,"time_alive":-1,"damage":100,"objective":false,"entry":false,"entry_weapon":null,"wp_ak47":1,"wp_ak47_hs":1},"76561198120286262":{"kills":0,"headshots":0,"assists":0,"time_alive":63.9609375,"damage":60,"objective":false,"entry":false,"entry_weapon":null},"76561198038246134":{"kills":0,"headshots":0,"assists":0,"time_alive":-1,"damage":0,"objective":true,"entry":false,"entry_weapon":null},"76561197993761807":{"kills":1,"headshots":0,"assists":0,"time_alive":-1,"damage":100,"objective":false,"entry":false,"entry_weapon":null,"wp_famas":1,"wp_famas_hs":0},"76561198139429381":{"kills":0,"headshots":0,"assists":0,"time_alive":79.4296875,"damage":53,"objective":false,"entry":false,"entry_weapon":null}}},{"round_start_time":1712.21875,"round_end_time":1762.0703125,"t":"team_noctias","ct":"team_Samaly","winner":"team_noctias","players":{"0":{"kills":0,"headshots":0,"assists":0,"time_alive":-1,"damage":0,"objective":false,"entry":false,"entry_weapon":null},"76561198033939559":{"kills":1,"headshots":1,"assists":0,"time_alive":35.2421875,"damage":100,"objective":false,"entry":true,"entry_weapon":"sg556","wp_sg556":1,"wp_sg556_hs":1},"undefined":{"kills":0,"headshots":0,"assists":7,"time_alive":-1,"damage":0,"objective":false,"entry":false,"entry_weapon":null},"76561197961085746":{"kills":0,"headshots":0,"assists":0,"time_alive":20.5078125,"damage":0,"objective":false,"entry":false,"entry_weapon":null},"76561198842037276":{"kills":1,"headshots":0,"assists":0,"time_alive":49.8515625,"damage":100,"objective":false,"entry":false,"entry_weapon":null,"wp_cz75a":1,"wp_cz75a_hs":0},"76561198162875654":{"kills":0,"headshots":0,"assists":0,"time_alive":27.5859375,"damage":0,"objective":false,"entry":false,"entry_weapon":null},"76561198020317127":{"kills":2,"headshots":2,"assists":0,"time_alive":-1,"damage":237,"objective":false,"entry":false,"entry_weapon":null,"wp_ak47":2,"wp_ak47_hs":2},"76561198062153950":{"kills":0,"headshots":0,"assists":0,"time_alive":31.9453125,"damage":0,"objective":false,"entry":false,"entry_weapon":null},"76561198120286262":{"kills":1,"headshots":1,"assists":0,"time_alive":46.1171875,"damage":100,"objective":false,"entry":false,"entry_weapon":null,"wp_fiveseven":1,"wp_fiveseven_hs":1},"76561198038246134":{"kills":2,"headshots":1,"assists":0,"time_alive":-1,"damage":163,"objective":false,"entry":false,"entry_weapon":null,"wp_ak47":2,"wp_ak47_hs":1},"76561198139429381":{"kills":0,"headshots":0,"assists":0,"time_alive":47.8671875,"damage":0,"objective":false,"entry":false,"entry_weapon":null},"76561197993761807":{"kills":0,"headshots":0,"assists":0,"time_alive":-1,"damage":0,"objective":false,"entry":false,"entry_weapon":null}}},{"round_start_time":1767.0859375,"round_end_time":1846.765625,"t":"team_noctias","ct":"team_Samaly","winner":"team_noctias","players":{"0":{"kills":0,"headshots":0,"assists":0,"time_alive":-1,"damage":0,"objective":false,"entry":false,"entry_weapon":null},"76561197961085746":{"kills":1,"headshots":0,"assists":0,"time_alive":68.7734375,"damage":100,"objective":false,"entry":true,"entry_weapon":"awp","wp_awp":1,"wp_awp_hs":0},"undefined":{"kills":0,"headshots":0,"assists":5,"time_alive":-1,"damage":0,"objective":false,"entry":false,"entry_weapon":null},"76561197993761807":{"kills":0,"headshots":0,"assists":0,"time_alive":22.2109375,"damage":0,"objective":false,"entry":false,"entry_weapon":null},"76561198062153950":{"kills":1,"headshots":0,"assists":0,"time_alive":25.7109375,"damage":122,"objective":false,"entry":false,"entry_weapon":null,"wp_m4a1":1,"wp_m4a1_hs":0},"76561198020317127":{"kills":0,"headshots":0,"assists":0,"time_alive":23.5703125,"damage":0,"objective":false,"entry":false,"entry_weapon":null},"76561198033939559":{"kills":1,"headshots":0,"assists":2,"time_alive":40.1796875,"damage":239,"objective":false,"entry":false,"entry_weapon":null,"wp_ak47":1,"wp_ak47_hs":0},"76561198842037276":{"kills":1,"headshots":0,"assists":1,"time_alive":43.4765625,"damage":125,"objective":false,"entry":false,"entry_weapon":null,"wp_mp9":1,"wp_mp9_hs":0},"76561198162875654":{"kills":2,"headshots":0,"assists":0,"time_alive":77.5859375,"damage":63,"objective":false,"entry":false,"entry_weapon":null,"wp_awp":2,"wp_awp_hs":0},"76561198038246134":{"kills":2,"headshots":1,"assists":1,"time_alive":-1,"damage":198,"objective":true,"entry":false,"entry_weapon":null,"wp_ak47":2,"wp_ak47_hs":1},"76561198139429381":{"kills":0,"headshots":0,"assists":0,"time_alive":61.1171875,"damage":0,"objective":false,"entry":false,"entry_weapon":null},"76561198120286262":{"kills":1,"headshots":0,"assists":0,"time_alive":79.6796875,"damage":107,"objective":false,"entry":false,"entry_weapon":null,"wp_ak47":1,"wp_ak47_hs":0}}},{"round_start_time":1851.8203125,"round_end_time":1943.203125,"t":"team_noctias","ct":"team_Samaly","winner":"team_noctias","players":{"0":{"kills":0,"headshots":0,"assists":0,"time_alive":-1,"damage":0,"objective":false,"entry":false,"entry_weapon":null},"76561198033939559":{"kills":1,"headshots":0,"assists":0,"time_alive":57.796875,"damage":100,"objective":false,"entry":true,"entry_weapon":"ak47","wp_ak47":1,"wp_ak47_hs":0},"undefined":{"kills":0,"headshots":0,"assists":5,"time_alive":-1,"damage":0,"objective":false,"entry":false,"entry_weapon":null},"76561198842037276":{"kills":0,"headshots":0,"assists":0,"time_alive":30.625,"damage":0,"objective":false,"entry":false,"entry_weapon":null},"76561198020317127":{"kills":1,"headshots":0,"assists":0,"time_alive":-1,"damage":140,"objective":false,"entry":false,"entry_weapon":null,"wp_ak47":1,"wp_ak47_hs":0},"76561198062153950":{"kills":0,"headshots":0,"assists":0,"time_alive":31.890625,"damage":28,"objective":false,"entry":false,"entry_weapon":null},"76561197993761807":{"kills":2,"headshots":1,"assists":0,"time_alive":-1,"damage":160,"objective":false,"entry":false,"entry_weapon":null,"wp_ak47":2,"wp_ak47_hs":1},"76561197961085746":{"kills":0,"headshots":0,"assists":0,"time_alive":42.203125,"damage":51,"objective":false,"entry":false,"entry_weapon":null},"76561198038246134":{"kills":0,"headshots":0,"assists":0,"time_alive":-1,"damage":0,"objective":true,"entry":false,"entry_weapon":null},"76561198139429381":{"kills":1,"headshots":0,"assists":0,"time_alive":83.8125,"damage":100,"objective":false,"entry":false,"entry_weapon":null,"wp_deagle":1,"wp_deagle_hs":0},"76561198162875654":{"kills":0,"headshots":0,"assists":0,"time_alive":-1,"damage":0,"objective":false,"entry":false,"entry_weapon":null},"76561198120286262":{"kills":0,"headshots":0,"assists":0,"time_alive":-1,"damage":0,"objective":false,"entry":false,"entry_weapon":null}}},{"round_start_time":1948.1875,"round_end_time":2037.359375,"t":"team_noctias","ct":"team_Samaly","winner":"team_noctias","players":{"0":{"kills":0,"headshots":0,"assists":0,"time_alive":-1,"damage":0,"objective":false,"entry":false,"entry_weapon":null},"76561198162875654":{"kills":4,"headshots":0,"assists":0,"time_alive":-1,"damage":346,"objective":false,"entry":true,"entry_weapon":"awp","wp_awp":4,"wp_awp_hs":0},"undefined":{"kills":0,"headshots":0,"assists":8,"time_alive":-1,"damage":0,"objective":false,"entry":false,"entry_weapon":null},"76561198842037276":{"kills":0,"headshots":0,"assists":0,"time_alive":27.359375,"damage":0,"objective":false,"entry":false,"entry_weapon":null},"76561197961085746":{"kills":1,"headshots":1,"assists":0,"time_alive":43.453125,"damage":100,"objective":false,"entry":false,"entry_weapon":null,"wp_m4a1_silencer":1,"wp_m4a1_silencer_hs":1},"76561197993761807":{"kills":0,"headshots":0,"assists":0,"time_alive":43.171875,"damage":0,"objective":false,"entry":false,"entry_weapon":null},"76561198033939559":{"kills":1,"headshots":1,"assists":0,"time_alive":86.09375,"damage":100,"objective":false,"entry":false,"entry_weapon":null,"wp_ak47":1,"wp_ak47_hs":1},"76561198120286262":{"kills":1,"headshots":0,"assists":0,"time_alive":67.3125,"damage":127,"objective":false,"entry":false,"entry_weapon":null,"wp_m4a1":1,"wp_m4a1_hs":0},"76561198038246134":{"kills":0,"headshots":0,"assists":0,"time_alive":59.46875,"damage":0,"objective":false,"entry":false,"entry_weapon":null},"76561198139429381":{"kills":1,"headshots":0,"assists":0,"time_alive":81.3125,"damage":161,"objective":false,"entry":false,"entry_weapon":null,"wp_m4a1":1,"wp_m4a1_hs":0},"76561198020317127":{"kills":0,"headshots":0,"assists":1,"time_alive":63.375,"damage":54,"objective":false,"entry":false,"entry_weapon":null},"76561198062153950":{"kills":1,"headshots":1,"assists":0,"time_alive":89.171875,"damage":60,"objective":false,"entry":false,"entry_weapon":null,"wp_ak47":1,"wp_ak47_hs":1}}},{"round_start_time":2042.4140625,"round_end_time":2125.2421875,"t":"team_noctias","ct":"team_Samaly","winner":"team_noctias","players":{"0":{"kills":0,"headshots":0,"assists":0,"time_alive":-1,"damage":0,"objective":false,"entry":false,"entry_weapon":null},"76561198020317127":{"kills":1,"headshots":1,"assists":0,"time_alive":55.0625,"damage":100,"objective":false,"entry":true,"entry_weapon":"ak47","wp_ak47":1,"wp_ak47_hs":1},"undefined":{"kills":0,"headshots":0,"assists":5,"time_alive":-1,"damage":0,"objective":false,"entry":false,"entry_weapon":null},"76561198062153950":{"kills":0,"headshots":0,"assists":0,"time_alive":33.90625,"damage":0,"objective":false,"entry":false,"entry_weapon":null},"76561198162875654":{"kills":1,"headshots":0,"assists":0,"time_alive":-1,"damage":25,"objective":false,"entry":false,"entry_weapon":null,"wp_awp":1,"wp_awp_hs":0},"76561198033939559":{"kills":0,"headshots":0,"assists":1,"time_alive":-1,"damage":75,"objective":false,"entry":false,"entry_weapon":null},"76561198842037276":{"kills":0,"headshots":0,"assists":0,"time_alive":49.328125,"damage":71,"objective":false,"entry":false,"entry_weapon":null},"76561197961085746":{"kills":1,"headshots":1,"assists":0,"time_alive":56.953125,"damage":100,"objective":false,"entry":false,"entry_weapon":null,"wp_deagle":1,"wp_deagle_hs":1},"76561198038246134":{"kills":1,"headshots":0,"assists":0,"time_alive":-1,"damage":132,"objective":true,"entry":false,"entry_weapon":null,"wp_ak47":1,"wp_ak47_hs":0},"76561198120286262":{"kills":0,"headshots":0,"assists":0,"time_alive":55.546875,"damage":51,"objective":false,"entry":false,"entry_weapon":null},"76561197993761807":{"kills":2,"headshots":0,"assists":0,"time_alive":-1,"damage":168,"objective":false,"entry":false,"entry_weapon":null,"wp_ak47":2,"wp_ak47_hs":0},"76561198139429381":{"kills":0,"headshots":0,"assists":0,"time_alive":82.828125,"damage":76,"objective":false,"entry":false,"entry_weapon":null}}},{"round_start_time":2130.2578125,"round_end_time":2208.46875,"t":"team_noctias","ct":"team_Samaly","winner":"team_Samaly","players":{"0":{"kills":0,"headshots":0,"assists":0,"time_alive":-1,"damage":0,"objective":false,"entry":false,"entry_weapon":null},"76561197961085746":{"kills":1,"headshots":0,"assists":0,"time_alive":71.5546875,"damage":100,"objective":false,"entry":true,"entry_weapon":"awp","wp_awp":1,"wp_awp_hs":0},"undefined":{"kills":0,"headshots":0,"assists":6,"time_alive":-1,"damage":0,"objective":false,"entry":false,"entry_weapon":null},"76561197993761807":{"kills":0,"headshots":0,"assists":0,"time_alive":21.1171875,"damage":0,"objective":false,"entry":false,"entry_weapon":null},"76561198162875654":{"kills":2,"headshots":0,"assists":0,"time_alive":78.1796875,"damage":174,"objective":false,"entry":false,"entry_weapon":null,"wp_awp":2,"wp_awp_hs":0},"76561198062153950":{"kills":0,"headshots":0,"assists":1,"time_alive":29.7578125,"damage":47,"objective":false,"entry":false,"entry_weapon":null},"76561198139429381":{"kills":2,"headshots":0,"assists":0,"time_alive":73.4140625,"damage":200,"objective":false,"entry":false,"entry_weapon":null,"wp_m4a1":2,"wp_m4a1_hs":0},"76561198033939559":{"kills":0,"headshots":0,"assists":0,"time_alive":34.9453125,"damage":0,"objective":false,"entry":false,"entry_weapon":null},"76561198020317127":{"kills":0,"headshots":0,"assists":1,"time_alive":68.3984375,"damage":80,"objective":false,"entry":false,"entry_weapon":null},"76561198038246134":{"kills":1,"headshots":0,"assists":0,"time_alive":78.2109375,"damage":46,"objective":false,"entry":false,"entry_weapon":null,"wp_ak47":1,"wp_ak47_hs":0},"76561198842037276":{"kills":1,"headshots":0,"assists":0,"time_alive":-1,"damage":53,"objective":false,"entry":false,"entry_weapon":null,"wp_knife_m9_bayonet":1,"wp_knife_m9_bayonet_hs":0},"76561198120286262":{"kills":1,"headshots":1,"assists":0,"time_alive":-1,"damage":100,"objective":false,"entry":false,"entry_weapon":null,"wp_m4a1":1,"wp_m4a1_hs":1}}},{"round_start_time":2213.5234375,"round_end_time":2273.7109375,"t":"team_noctias","ct":"team_Samaly","winner":"team_noctias","players":{"0":{"kills":0,"headshots":0,"assists":0,"time_alive":-1,"damage":0,"objective":false,"entry":false,"entry_weapon":null},"76561198162875654":{"kills":1,"headshots":0,"assists":0,"time_alive":57.828125,"damage":106,"objective":false,"entry":true,"entry_weapon":"ak47","wp_ak47":1,"wp_ak47_hs":0},"undefined":{"kills":0,"headshots":0,"assists":4,"time_alive":-1,"damage":0,"objective":false,"entry":false,"entry_weapon":null},"76561198842037276":{"kills":0,"headshots":0,"assists":1,"time_alive":27.234375,"damage":96,"objective":false,"entry":false,"entry_weapon":null},"76561198033939559":{"kills":2,"headshots":0,"assists":0,"time_alive":-1,"damage":146,"objective":false,"entry":false,"entry_weapon":null,"wp_ak47":2,"wp_ak47_hs":0},"76561198139429381":{"kills":0,"headshots":0,"assists":0,"time_alive":38.359375,"damage":0,"objective":false,"entry":false,"entry_weapon":null},"76561198020317127":{"kills":1,"headshots":0,"assists":1,"time_alive":-1,"damage":138,"objective":false,"entry":false,"entry_weapon":null,"wp_ak47":1,"wp_ak47_hs":0},"76561197961085746":{"kills":0,"headshots":0,"assists":0,"time_alive":46.84375,"damage":0,"objective":false,"entry":false,"entry_weapon":null},"76561198120286262":{"kills":2,"headshots":0,"assists":0,"time_alive":60.1875,"damage":126,"objective":false,"entry":false,"entry_weapon":null,"wp_m4a1":2,"wp_m4a1_hs":0},"76561197993761807":{"kills":0,"headshots":0,"assists":0,"time_alive":57.25,"damage":0,"objective":false,"entry":false,"entry_weapon":null},"76561198038246134":{"kills":1,"headshots":0,"assists":1,"time_alive":-1,"damage":110,"objective":false,"entry":false,"entry_weapon":null,"wp_ak47":1,"wp_ak47_hs":0},"76561198062153950":{"kills":0,"headshots":0,"assists":0,"time_alive":59.34375,"damage":84,"objective":false,"entry":false,"entry_weapon":null}}},{"round_start_time":2278.765625,"round_end_time":2367.25,"t":"team_noctias","ct":"team_Samaly","winner":"team_Samaly","players":{"0":{"kills":0,"headshots":0,"assists":0,"time_alive":-1,"damage":0,"objective":false,"entry":false,"entry_weapon":null},"76561198842037276":{"kills":3,"headshots":2,"assists":1,"time_alive":73.53125,"damage":359,"objective":false,"entry":true,"entry_weapon":"deagle","wp_deagle":3,"wp_deagle_hs":2},"undefined":{"kills":0,"headshots":0,"assists":6,"time_alive":-1,"damage":0,"objective":false,"entry":false,"entry_weapon":null},"76561197993761807":{"kills":0,"headshots":0,"assists":0,"time_alive":20.71875,"damage":26,"objective":false,"entry":false,"entry_weapon":null},"76561198162875654":{"kills":1,"headshots":0,"assists":0,"time_alive":35.796875,"damage":100,"objective":false,"entry":false,"entry_weapon":null,"wp_ak47":1,"wp_ak47_hs":0},"76561197961085746":{"kills":0,"headshots":0,"assists":0,"time_alive":35.71875,"damage":0,"objective":false,"entry":false,"entry_weapon":null},"76561198020317127":{"kills":1,"headshots":0,"assists":0,"time_alive":65.28125,"damage":50,"objective":false,"entry":false,"entry_weapon":null,"wp_ak47":1,"wp_ak47_hs":0},"76561198038246134":{"kills":1,"headshots":0,"assists":1,"time_alive":88.484375,"damage":97,"objective":false,"entry":false,"entry_weapon":null,"wp_ak47":1,"wp_ak47_hs":0},"76561198062153950":{"kills":0,"headshots":0,"assists":0,"time_alive":48.59375,"damage":0,"objective":false,"entry":false,"entry_weapon":null},"76561198033939559":{"kills":1,"headshots":1,"assists":1,"time_alive":73.546875,"damage":127,"objective":false,"entry":false,"entry_weapon":null,"wp_ak47":1,"wp_ak47_hs":1},"76561198120286262":{"kills":2,"headshots":0,"assists":0,"time_alive":-1,"damage":103,"objective":false,"entry":false,"entry_weapon":null,"wp_deagle":1,"wp_deagle_hs":0,"wp_hegrenade":1,"wp_hegrenade_hs":0},"76561198139429381":{"kills":0,"headshots":0,"assists":0,"time_alive":86.953125,"damage":37,"objective":false,"entry":false,"entry_weapon":null}}}],"rounds_end":[{"round_start_time":177.2578125,"round_end_time":182.2734375,"t":"team_Samaly","ct":"team_noctias","winner":null,"players":{"0":{"kills":0,"headshots":0,"assists":0,"time_alive":-1,"damage":0,"objective":false,"entry":false,"entry_weapon":null},"76561198162875654":{"kills":0,"headshots":0,"assists":0,"time_alive":-1,"damage":0,"objective":false,"entry":false,"entry_weapon":null},"76561198033939559":{"kills":0,"headshots":0,"assists":0,"time_alive":-1,"damage":0,"objective":false,"entry":false,"entry_weapon":null},"76561198139429381":{"kills":0,"headshots":0,"assists":0,"time_alive":-1,"damage":0,"objective":false,"entry":false,"entry_weapon":null},"76561198020317127":{"kills":0,"headshots":0,"assists":0,"time_alive":-1,"damage":0,"objective":false,"entry":false,"entry_weapon":null},"76561197993761807":{"kills":0,"headshots":0,"assists":0,"time_alive":-1,"damage":0,"objective":false,"entry":false,"entry_weapon":null},"76561198062153950":{"kills":0,"headshots":0,"assists":0,"time_alive":-1,"damage":0,"objective":false,"entry":false,"entry_weapon":null},"76561198038246134":{"kills":0,"headshots":0,"assists":0,"time_alive":-1,"damage":0,"objective":false,"entry":false,"entry_weapon":null},"76561198842037276":{"kills":0,"headshots":0,"assists":0,"time_alive":-1,"damage":0,"objective":false,"entry":false,"entry_weapon":null},"76561198120286262":{"kills":0,"headshots":0,"assists":0,"time_alive":-1,"damage":0,"objective":false,"entry":false,"entry_weapon":null},"76561197961085746":{"kills":0,"headshots":0,"assists":0,"time_alive":-1,"damage":0,"objective":false,"entry":false,"entry_weapon":null}}},{"round_start_time":240.2265625,"round_end_time":245.2265625,"t":"team_Samaly","ct":"team_noctias","winner":null,"players":{"0":{"kills":0,"headshots":0,"assists":0,"time_alive":-1,"damage":0,"objective":false,"entry":false,"entry_weapon":null},"76561198162875654":{"kills":0,"headshots":0,"assists":0,"time_alive":-1,"damage":0,"objective":false,"entry":false,"entry_weapon":null},"76561198033939559":{"kills":0,"headshots":0,"assists":0,"time_alive":-1,"damage":0,"objective":false,"entry":false,"entry_weapon":null},"76561198139429381":{"kills":0,"headshots":0,"assists":0,"time_alive":-1,"damage":0,"objective":false,"entry":false,"entry_weapon":null},"76561198020317127":{"kills":0,"headshots":0,"assists":0,"time_alive":-1,"damage":0,"objective":false,"entry":false,"entry_weapon":null},"76561197993761807":{"kills":0,"headshots":0,"assists":0,"time_alive":-1,"damage":0,"objective":false,"entry":false,"entry_weapon":null},"76561198062153950":{"kills":0,"headshots":0,"assists":0,"time_alive":-1,"damage":0,"objective":false,"entry":false,"entry_weapon":null},"76561198038246134":{"kills":0,"headshots":0,"assists":0,"time_alive":-1,"damage":0,"objective":false,"entry":false,"entry_weapon":null},"76561198842037276":{"kills":0,"headshots":0,"assists":0,"time_alive":-1,"damage":0,"objective":false,"entry":false,"entry_weapon":null},"76561198120286262":{"kills":0,"headshots":0,"assists":0,"time_alive":-1,"damage":0,"objective":false,"entry":false,"entry_weapon":null},"76561197961085746":{"kills":0,"headshots":0,"assists":0,"time_alive":-1,"damage":0,"objective":false,"entry":false,"entry_weapon":null}}},{"round_start_time":387.0625,"round_end_time":392.078125,"t":"team_Samaly","ct":"team_noctias","winner":null,"players":{"0":{"kills":0,"headshots":0,"assists":0,"time_alive":-1,"damage":0,"objective":false,"entry":false,"entry_weapon":null},"76561198162875654":{"kills":0,"headshots":0,"assists":0,"time_alive":-1,"damage":0,"objective":false,"entry":false,"entry_weapon":null},"76561198033939559":{"kills":0,"headshots":0,"assists":0,"time_alive":-1,"damage":0,"objective":false,"entry":false,"entry_weapon":null},"76561198139429381":{"kills":0,"headshots":0,"assists":0,"time_alive":-1,"damage":0,"objective":false,"entry":false,"entry_weapon":null},"76561198020317127":{"kills":0,"headshots":0,"assists":0,"time_alive":-1,"damage":0,"objective":false,"entry":false,"entry_weapon":null},"76561197993761807":{"kills":0,"headshots":0,"assists":0,"time_alive":-1,"damage":0,"objective":false,"entry":false,"entry_weapon":null},"76561198062153950":{"kills":0,"headshots":0,"assists":0,"time_alive":-1,"damage":0,"objective":false,"entry":false,"entry_weapon":null},"76561198038246134":{"kills":0,"headshots":0,"assists":0,"time_alive":-1,"damage":0,"objective":false,"entry":false,"entry_weapon":null},"76561198842037276":{"kills":0,"headshots":0,"assists":0,"time_alive":-1,"damage":0,"objective":false,"entry":false,"entry_weapon":null},"76561198120286262":{"kills":0,"headshots":0,"assists":0,"time_alive":-1,"damage":0,"objective":false,"entry":false,"entry_weapon":null},"76561197961085746":{"kills":0,"headshots":0,"assists":0,"time_alive":-1,"damage":0,"objective":false,"entry":false,"entry_weapon":null}}},{"round_start_time":516.0859375,"round_end_time":521.0859375,"t":"team_Samaly","ct":"team_noctias","winner":null,"players":{"0":{"kills":0,"headshots":0,"assists":0,"time_alive":-1,"damage":0,"objective":false,"entry":false,"entry_weapon":null},"76561198162875654":{"kills":0,"headshots":0,"assists":0,"time_alive":-1,"damage":0,"objective":false,"entry":false,"entry_weapon":null},"76561198033939559":{"kills":0,"headshots":0,"assists":0,"time_alive":-1,"damage":0,"objective":false,"entry":false,"entry_weapon":null},"76561198139429381":{"kills":0,"headshots":0,"assists":0,"time_alive":-1,"damage":0,"objective":false,"entry":false,"entry_weapon":null},"76561198020317127":{"kills":0,"headshots":0,"assists":0,"time_alive":-1,"damage":0,"objective":false,"entry":false,"entry_weapon":null},"76561197993761807":{"kills":0,"headshots":0,"assists":0,"time_alive":-1,"damage":0,"objective":false,"entry":false,"entry_weapon":null},"76561198062153950":{"kills":0,"headshots":0,"assists":0,"time_alive":-1,"damage":0,"objective":false,"entry":false,"entry_weapon":null},"76561198038246134":{"kills":0,"headshots":0,"assists":0,"time_alive":-1,"damage":0,"objective":false,"entry":false,"entry_weapon":null},"76561198842037276":{"kills":0,"headshots":0,"assists":0,"time_alive":-1,"damage":0,"objective":false,"entry":false,"entry_weapon":null},"76561198120286262":{"kills":0,"headshots":0,"assists":0,"time_alive":-1,"damage":0,"objective":false,"entry":false,"entry_weapon":null},"76561197961085746":{"kills":0,"headshots":0,"assists":0,"time_alive":-1,"damage":0,"objective":false,"entry":false,"entry_weapon":null}}},{"round_start_time":592.1328125,"round_end_time":597.1484375,"t":"team_Samaly","ct":"team_noctias","winner":null,"players":{"0":{"kills":0,"headshots":0,"assists":0,"time_alive":-1,"damage":0,"objective":false,"entry":false,"entry_weapon":null},"76561198162875654":{"kills":0,"headshots":0,"assists":0,"time_alive":-1,"damage":0,"objective":false,"entry":false,"entry_weapon":null},"76561198033939559":{"kills":0,"headshots":0,"assists":0,"time_alive":-1,"damage":0,"objective":false,"entry":false,"entry_weapon":null},"76561198139429381":{"kills":0,"headshots":0,"assists":0,"time_alive":-1,"damage":0,"objective":false,"entry":false,"entry_weapon":null},"76561198020317127":{"kills":0,"headshots":0,"assists":0,"time_alive":-1,"damage":0,"objective":false,"entry":false,"entry_weapon":null},"76561197993761807":{"kills":0,"headshots":0,"assists":0,"time_alive":-1,"damage":0,"objective":false,"entry":false,"entry_weapon":null},"76561198062153950":{"kills":0,"headshots":0,"assists":0,"time_alive":-1,"damage":0,"objective":false,"entry":false,"entry_weapon":null},"76561198038246134":{"kills":0,"headshots":0,"assists":0,"time_alive":-1,"damage":0,"objective":false,"entry":false,"entry_weapon":null},"76561198842037276":{"kills":0,"headshots":0,"assists":0,"time_alive":-1,"damage":0,"objective":false,"entry":false,"entry_weapon":null},"76561198120286262":{"kills":0,"headshots":0,"assists":0,"time_alive":-1,"damage":0,"objective":false,"entry":false,"entry_weapon":null},"76561197961085746":{"kills":0,"headshots":0,"assists":0,"time_alive":-1,"damage":0,"objective":false,"entry":false,"entry_weapon":null}}},{"round_start_time":680.6484375,"round_end_time":685.6484375,"t":"team_Samaly","ct":"team_noctias","winner":null,"players":{"0":{"kills":0,"headshots":0,"assists":0,"time_alive":-1,"damage":0,"objective":false,"entry":false,"entry_weapon":null},"76561198162875654":{"kills":0,"headshots":0,"assists":0,"time_alive":-1,"damage":0,"objective":false,"entry":false,"entry_weapon":null},"76561198033939559":{"kills":0,"headshots":0,"assists":0,"time_alive":-1,"damage":0,"objective":false,"entry":false,"entry_weapon":null},"76561198139429381":{"kills":0,"headshots":0,"assists":0,"time_alive":-1,"damage":0,"objective":false,"entry":false,"entry_weapon":null},"76561198020317127":{"kills":0,"headshots":0,"assists":0,"time_alive":-1,"damage":0,"objective":false,"entry":false,"entry_weapon":null},"76561197993761807":{"kills":0,"headshots":0,"assists":0,"time_alive":-1,"damage":0,"objective":false,"entry":false,"entry_weapon":null},"76561198062153950":{"kills":0,"headshots":0,"assists":0,"time_alive":-1,"damage":0,"objective":false,"entry":false,"entry_weapon":null},"76561198038246134":{"kills":0,"headshots":0,"assists":0,"time_alive":-1,"damage":0,"objective":false,"entry":false,"entry_weapon":null},"76561198842037276":{"kills":0,"headshots":0,"assists":0,"time_alive":-1,"damage":0,"objective":false,"entry":false,"entry_weapon":null},"76561198120286262":{"kills":0,"headshots":0,"assists":0,"time_alive":-1,"damage":0,"objective":false,"entry":false,"entry_weapon":null},"76561197961085746":{"kills":0,"headshots":0,"assists":0,"time_alive":-1,"damage":0,"objective":false,"entry":false,"entry_weapon":null}}},{"round_start_time":781.671875,"round_end_time":786.671875,"t":"team_Samaly","ct":"team_noctias","winner":null,"players":{"0":{"kills":0,"headshots":0,"assists":0,"time_alive":-1,"damage":0,"objective":false,"entry":false,"entry_weapon":null},"76561198162875654":{"kills":0,"headshots":0,"assists":0,"time_alive":-1,"damage":0,"objective":false,"entry":false,"entry_weapon":null},"76561198033939559":{"kills":0,"headshots":0,"assists":0,"time_alive":-1,"damage":0,"objective":false,"entry":false,"entry_weapon":null},"76561198139429381":{"kills":0,"headshots":0,"assists":0,"time_alive":-1,"damage":0,"objective":false,"entry":false,"entry_weapon":null},"76561198020317127":{"kills":0,"headshots":0,"assists":0,"time_alive":-1,"damage":0,"objective":false,"entry":false,"entry_weapon":null},"76561197993761807":{"kills":0,"headshots":0,"assists":0,"time_alive":-1,"damage":0,"objective":false,"entry":false,"entry_weapon":null},"76561198062153950":{"kills":0,"headshots":0,"assists":0,"time_alive":-1,"damage":0,"objective":false,"entry":false,"entry_weapon":null},"76561198038246134":{"kills":0,"headshots":0,"assists":0,"time_alive":-1,"damage":0,"objective":false,"entry":false,"entry_weapon":null},"76561198842037276":{"kills":0,"headshots":0,"assists":0,"time_alive":-1,"damage":0,"objective":false,"entry":false,"entry_weapon":null},"76561198120286262":{"kills":0,"headshots":0,"assists":0,"time_alive":-1,"damage":0,"objective":false,"entry":false,"entry_weapon":null},"76561197961085746":{"kills":0,"headshots":0,"assists":0,"time_alive":-1,"damage":0,"objective":false,"entry":false,"entry_weapon":null}}},{"round_start_time":851.8984375,"round_end_time":856.9140625,"t":"team_Samaly","ct":"team_noctias","winner":null,"players":{"0":{"kills":0,"headshots":0,"assists":0,"time_alive":-1,"damage":0,"objective":false,"entry":false,"entry_weapon":null},"76561198162875654":{"kills":0,"headshots":0,"assists":0,"time_alive":-1,"damage":0,"objective":false,"entry":false,"entry_weapon":null},"76561198033939559":{"kills":0,"headshots":0,"assists":0,"time_alive":-1,"damage":0,"objective":false,"entry":false,"entry_weapon":null},"76561198139429381":{"kills":0,"headshots":0,"assists":0,"time_alive":-1,"damage":0,"objective":false,"entry":false,"entry_weapon":null},"76561198020317127":{"kills":0,"headshots":0,"assists":0,"time_alive":-1,"damage":0,"objective":false,"entry":false,"entry_weapon":null},"76561197993761807":{"kills":0,"headshots":0,"assists":0,"time_alive":-1,"damage":0,"objective":false,"entry":false,"entry_weapon":null},"76561198062153950":{"kills":0,"headshots":0,"assists":0,"time_alive":-1,"damage":0,"objective":false,"entry":false,"entry_weapon":null},"76561198038246134":{"kills":0,"headshots":0,"assists":0,"time_alive":-1,"damage":0,"objective":false,"entry":false,"entry_weapon":null},"76561198842037276":{"kills":0,"headshots":0,"assists":0,"time_alive":-1,"damage":0,"objective":false,"entry":false,"entry_weapon":null},"76561198120286262":{"kills":0,"headshots":0,"assists":0,"time_alive":-1,"damage":0,"objective":false,"entry":false,"entry_weapon":null},"76561197961085746":{"kills":0,"headshots":0,"assists":0,"time_alive":-1,"damage":0,"objective":false,"entry":false,"entry_weapon":null}}},{"round_start_time":897.84375,"round_end_time":902.8984375,"t":"team_Samaly","ct":"team_noctias","winner":null,"players":{"0":{"kills":0,"headshots":0,"assists":0,"time_alive":-1,"damage":0,"objective":false,"entry":false,"entry_weapon":null},"76561198162875654":{"kills":0,"headshots":0,"assists":0,"time_alive":-1,"damage":0,"objective":false,"entry":false,"entry_weapon":null},"76561198033939559":{"kills":0,"headshots":0,"assists":0,"time_alive":-1,"damage":0,"objective":false,"entry":false,"entry_weapon":null},"76561198139429381":{"kills":0,"headshots":0,"assists":0,"time_alive":-1,"damage":0,"objective":false,"entry":false,"entry_weapon":null},"76561198020317127":{"kills":0,"headshots":0,"assists":0,"time_alive":-1,"damage":0,"objective":false,"entry":false,"entry_weapon":null},"76561197993761807":{"kills":0,"headshots":0,"assists":0,"time_alive":-1,"damage":0,"objective":false,"entry":false,"entry_weapon":null},"76561198062153950":{"kills":0,"headshots":0,"assists":0,"time_alive":-1,"damage":0,"objective":false,"entry":false,"entry_weapon":null},"76561198038246134":{"kills":0,"headshots":0,"assists":0,"time_alive":-1,"damage":0,"objective":false,"entry":false,"entry_weapon":null},"76561198842037276":{"kills":0,"headshots":0,"assists":0,"time_alive":-1,"damage":0,"objective":false,"entry":false,"entry_weapon":null},"76561198120286262":{"kills":0,"headshots":0,"assists":0,"time_alive":-1,"damage":0,"objective":false,"entry":false,"entry_weapon":null},"76561197961085746":{"kills":0,"headshots":0,"assists":0,"time_alive":-1,"damage":0,"objective":false,"entry":false,"entry_weapon":null}}},{"round_start_time":983.09375,"round_end_time":988.1484375,"t":"team_Samaly","ct":"team_noctias","winner":null,"players":{"0":{"kills":0,"headshots":0,"assists":0,"time_alive":-1,"damage":0,"objective":false,"entry":false,"entry_weapon":null},"76561198162875654":{"kills":0,"headshots":0,"assists":0,"time_alive":-1,"damage":0,"objective":false,"entry":false,"entry_weapon":null},"76561198033939559":{"kills":0,"headshots":0,"assists":0,"time_alive":-1,"damage":0,"objective":false,"entry":false,"entry_weapon":null},"76561198139429381":{"kills":0,"headshots":0,"assists":0,"time_alive":-1,"damage":0,"objective":false,"entry":false,"entry_weapon":null},"76561198020317127":{"kills":0,"headshots":0,"assists":0,"time_alive":-1,"damage":0,"objective":false,"entry":false,"entry_weapon":null},"76561197993761807":{"kills":0,"headshots":0,"assists":0,"time_alive":-1,"damage":0,"objective":false,"entry":false,"entry_weapon":null},"76561198062153950":{"kills":0,"headshots":0,"assists":0,"time_alive":-1,"damage":0,"objective":false,"entry":false,"entry_weapon":null},"76561198038246134":{"kills":0,"headshots":0,"assists":0,"time_alive":-1,"damage":0,"objective":false,"entry":false,"entry_weapon":null},"76561198842037276":{"kills":0,"headshots":0,"assists":0,"time_alive":-1,"damage":0,"objective":false,"entry":false,"entry_weapon":null},"76561198120286262":{"kills":0,"headshots":0,"assists":0,"time_alive":-1,"damage":0,"objective":false,"entry":false,"entry_weapon":null},"76561197961085746":{"kills":0,"headshots":0,"assists":0,"time_alive":-1,"damage":0,"objective":false,"entry":false,"entry_weapon":null}}},{"round_start_time":1065.8203125,"round_end_time":1070.8984375,"t":"team_Samaly","ct":"team_noctias","winner":null,"players":{"0":{"kills":0,"headshots":0,"assists":0,"time_alive":-1,"damage":0,"objective":false,"entry":false,"entry_weapon":null},"76561198162875654":{"kills":0,"headshots":0,"assists":0,"time_alive":-1,"damage":0,"objective":false,"entry":false,"entry_weapon":null},"76561198033939559":{"kills":0,"headshots":0,"assists":0,"time_alive":-1,"damage":0,"objective":false,"entry":false,"entry_weapon":null},"76561198139429381":{"kills":0,"headshots":0,"assists":0,"time_alive":-1,"damage":0,"objective":false,"entry":false,"entry_weapon":null},"76561198020317127":{"kills":0,"headshots":0,"assists":0,"time_alive":-1,"damage":0,"objective":false,"entry":false,"entry_weapon":null},"76561197993761807":{"kills":0,"headshots":0,"assists":0,"time_alive":-1,"damage":0,"objective":false,"entry":false,"entry_weapon":null},"76561198062153950":{"kills":0,"headshots":0,"assists":0,"time_alive":-1,"damage":0,"objective":false,"entry":false,"entry_weapon":null},"76561198038246134":{"kills":0,"headshots":0,"assists":0,"time_alive":-1,"damage":0,"objective":false,"entry":false,"entry_weapon":null},"76561198842037276":{"kills":0,"headshots":0,"assists":0,"time_alive":-1,"damage":0,"objective":false,"entry":false,"entry_weapon":null},"76561198120286262":{"kills":0,"headshots":0,"assists":0,"time_alive":-1,"damage":0,"objective":false,"entry":false,"entry_weapon":null},"76561197961085746":{"kills":0,"headshots":0,"assists":0,"time_alive":-1,"damage":0,"objective":false,"entry":false,"entry_weapon":null}}},{"round_start_time":1177.5703125,"round_end_time":1182.5703125,"t":"team_Samaly","ct":"team_noctias","winner":null,"players":{"0":{"kills":0,"headshots":0,"assists":0,"time_alive":-1,"damage":0,"objective":false,"entry":false,"entry_weapon":null},"76561198162875654":{"kills":0,"headshots":0,"assists":0,"time_alive":-1,"damage":0,"objective":false,"entry":false,"entry_weapon":null},"76561198033939559":{"kills":0,"headshots":0,"assists":0,"time_alive":-1,"damage":0,"objective":false,"entry":false,"entry_weapon":null},"76561198139429381":{"kills":0,"headshots":0,"assists":0,"time_alive":-1,"damage":0,"objective":false,"entry":false,"entry_weapon":null},"76561198020317127":{"kills":0,"headshots":0,"assists":0,"time_alive":-1,"damage":0,"objective":false,"entry":false,"entry_weapon":null},"76561197993761807":{"kills":0,"headshots":0,"assists":0,"time_alive":-1,"damage":0,"objective":false,"entry":false,"entry_weapon":null},"76561198062153950":{"kills":0,"headshots":0,"assists":0,"time_alive":-1,"damage":0,"objective":false,"entry":false,"entry_weapon":null},"76561198038246134":{"kills":0,"headshots":0,"assists":0,"time_alive":-1,"damage":0,"objective":false,"entry":false,"entry_weapon":null},"76561198842037276":{"kills":0,"headshots":0,"assists":0,"time_alive":-1,"damage":0,"objective":false,"entry":false,"entry_weapon":null},"76561198120286262":{"kills":0,"headshots":0,"assists":0,"time_alive":-1,"damage":0,"objective":false,"entry":false,"entry_weapon":null},"76561197961085746":{"kills":0,"headshots":0,"assists":0,"time_alive":-1,"damage":0,"objective":false,"entry":false,"entry_weapon":null}}},{"round_start_time":1281.7265625,"round_end_time":1286.7265625,"t":"team_Samaly","ct":"team_noctias","winner":null,"players":{"0":{"kills":0,"headshots":0,"assists":0,"time_alive":-1,"damage":0,"objective":false,"entry":false,"entry_weapon":null},"76561198162875654":{"kills":0,"headshots":0,"assists":0,"time_alive":-1,"damage":0,"objective":false,"entry":false,"entry_weapon":null},"76561198033939559":{"kills":0,"headshots":0,"assists":0,"time_alive":-1,"damage":0,"objective":false,"entry":false,"entry_weapon":null},"76561198139429381":{"kills":0,"headshots":0,"assists":0,"time_alive":-1,"damage":0,"objective":false,"entry":false,"entry_weapon":null},"76561198020317127":{"kills":0,"headshots":0,"assists":0,"time_alive":-1,"damage":0,"objective":false,"entry":false,"entry_weapon":null},"76561197993761807":{"kills":0,"headshots":0,"assists":0,"time_alive":-1,"damage":0,"objective":false,"entry":false,"entry_weapon":null},"76561198062153950":{"kills":0,"headshots":0,"assists":0,"time_alive":-1,"damage":0,"objective":false,"entry":false,"entry_weapon":null},"76561198038246134":{"kills":0,"headshots":0,"assists":0,"time_alive":-1,"damage":0,"objective":false,"entry":false,"entry_weapon":null},"76561198842037276":{"kills":0,"headshots":0,"assists":0,"time_alive":-1,"damage":0,"objective":false,"entry":false,"entry_weapon":null},"76561198120286262":{"kills":0,"headshots":0,"assists":0,"time_alive":-1,"damage":0,"objective":false,"entry":false,"entry_weapon":null},"76561197961085746":{"kills":0,"headshots":0,"assists":0,"time_alive":-1,"damage":0,"objective":false,"entry":false,"entry_weapon":null}}},{"round_start_time":1410.796875,"round_end_time":1415.796875,"t":"team_Samaly","ct":"team_noctias","winner":null,"players":{"0":{"kills":0,"headshots":0,"assists":0,"time_alive":-1,"damage":0,"objective":false,"entry":false,"entry_weapon":null},"76561198162875654":{"kills":0,"headshots":0,"assists":0,"time_alive":-1,"damage":0,"objective":false,"entry":false,"entry_weapon":null},"76561198033939559":{"kills":0,"headshots":0,"assists":0,"time_alive":-1,"damage":0,"objective":false,"entry":false,"entry_weapon":null},"76561198139429381":{"kills":0,"headshots":0,"assists":0,"time_alive":-1,"damage":0,"objective":false,"entry":false,"entry_weapon":null},"76561198020317127":{"kills":0,"headshots":0,"assists":0,"time_alive":-1,"damage":0,"objective":false,"entry":false,"entry_weapon":null},"76561197993761807":{"kills":0,"headshots":0,"assists":0,"time_alive":-1,"damage":0,"objective":false,"entry":false,"entry_weapon":null},"76561198062153950":{"kills":0,"headshots":0,"assists":0,"time_alive":-1,"damage":0,"objective":false,"entry":false,"entry_weapon":null},"76561198038246134":{"kills":0,"headshots":0,"assists":0,"time_alive":-1,"damage":0,"objective":false,"entry":false,"entry_weapon":null},"76561198842037276":{"kills":0,"headshots":0,"assists":0,"time_alive":-1,"damage":0,"objective":false,"entry":false,"entry_weapon":null},"76561198120286262":{"kills":0,"headshots":0,"assists":0,"time_alive":-1,"damage":0,"objective":false,"entry":false,"entry_weapon":null},"76561197961085746":{"kills":0,"headshots":0,"assists":0,"time_alive":-1,"damage":0,"objective":false,"entry":false,"entry_weapon":null}}},{"round_start_time":1496.9453125,"round_end_time":1511.9453125,"t":"team_Samaly","ct":"team_noctias","winner":null,"players":{"0":{"kills":0,"headshots":0,"assists":0,"time_alive":-1,"damage":0,"objective":false,"entry":false,"entry_weapon":null},"76561198162875654":{"kills":0,"headshots":0,"assists":0,"time_alive":-1,"damage":0,"objective":false,"entry":false,"entry_weapon":null},"76561198033939559":{"kills":0,"headshots":0,"assists":0,"time_alive":-1,"damage":0,"objective":false,"entry":false,"entry_weapon":null},"76561198139429381":{"kills":0,"headshots":0,"assists":0,"time_alive":-1,"damage":0,"objective":false,"entry":false,"entry_weapon":null},"76561198020317127":{"kills":0,"headshots":0,"assists":0,"time_alive":-1,"damage":0,"objective":false,"entry":false,"entry_weapon":null},"76561197993761807":{"kills":0,"headshots":0,"assists":0,"time_alive":-1,"damage":0,"objective":false,"entry":false,"entry_weapon":null},"76561198062153950":{"kills":0,"headshots":0,"assists":0,"time_alive":-1,"damage":0,"objective":false,"entry":false,"entry_weapon":null},"76561198038246134":{"kills":0,"headshots":0,"assists":0,"time_alive":-1,"damage":0,"objective":false,"entry":false,"entry_weapon":null},"76561198842037276":{"kills":0,"headshots":0,"assists":0,"time_alive":-1,"damage":0,"objective":false,"entry":false,"entry_weapon":null},"76561198120286262":{"kills":0,"headshots":0,"assists":0,"time_alive":-1,"damage":0,"objective":false,"entry":false,"entry_weapon":null},"76561197961085746":{"kills":0,"headshots":0,"assists":0,"time_alive":-1,"damage":0,"objective":false,"entry":false,"entry_weapon":null}}},{"round_start_time":1553.96875,"round_end_time":1558.96875,"t":"team_noctias","ct":"team_Samaly","winner":null,"players":{"0":{"kills":0,"headshots":0,"assists":0,"time_alive":-1,"damage":0,"objective":false,"entry":false,"entry_weapon":null},"76561198162875654":{"kills":0,"headshots":0,"assists":0,"time_alive":-1,"damage":0,"objective":false,"entry":false,"entry_weapon":null},"76561198033939559":{"kills":0,"headshots":0,"assists":0,"time_alive":-1,"damage":0,"objective":false,"entry":false,"entry_weapon":null},"76561198139429381":{"kills":0,"headshots":0,"assists":0,"time_alive":-1,"damage":0,"objective":false,"entry":false,"entry_weapon":null},"76561198020317127":{"kills":0,"headshots":0,"assists":0,"time_alive":-1,"damage":0,"objective":false,"entry":false,"entry_weapon":null},"76561197993761807":{"kills":0,"headshots":0,"assists":0,"time_alive":-1,"damage":0,"objective":false,"entry":false,"entry_weapon":null},"76561198062153950":{"kills":0,"headshots":0,"assists":0,"time_alive":-1,"damage":0,"objective":false,"entry":false,"entry_weapon":null},"76561198038246134":{"kills":0,"headshots":0,"assists":0,"time_alive":-1,"damage":0,"objective":false,"entry":false,"entry_weapon":null},"76561198842037276":{"kills":0,"headshots":0,"assists":0,"time_alive":-1,"damage":0,"objective":false,"entry":false,"entry_weapon":null},"76561198120286262":{"kills":0,"headshots":0,"assists":0,"time_alive":-1,"damage":0,"objective":false,"entry":false,"entry_weapon":null},"76561197961085746":{"kills":0,"headshots":0,"assists":0,"time_alive":-1,"damage":0,"objective":false,"entry":false,"entry_weapon":null}}},{"round_start_time":1622.71875,"round_end_time":1627.7734375,"t":"team_noctias","ct":"team_Samaly","winner":null,"players":{"0":{"kills":0,"headshots":0,"assists":0,"time_alive":-1,"damage":0,"objective":false,"entry":false,"entry_weapon":null},"76561198162875654":{"kills":0,"headshots":0,"assists":0,"time_alive":-1,"damage":0,"objective":false,"entry":false,"entry_weapon":null},"76561198033939559":{"kills":0,"headshots":0,"assists":0,"time_alive":-1,"damage":0,"objective":false,"entry":false,"entry_weapon":null},"76561198139429381":{"kills":0,"headshots":0,"assists":0,"time_alive":-1,"damage":0,"objective":false,"entry":false,"entry_weapon":null},"76561198020317127":{"kills":0,"headshots":0,"assists":0,"time_alive":-1,"damage":0,"objective":false,"entry":false,"entry_weapon":null},"76561197993761807":{"kills":0,"headshots":0,"assists":0,"time_alive":-1,"damage":0,"objective":false,"entry":false,"entry_weapon":null},"76561198062153950":{"kills":0,"headshots":0,"assists":0,"time_alive":-1,"damage":0,"objective":false,"entry":false,"entry_weapon":null},"76561198038246134":{"kills":0,"headshots":0,"assists":0,"time_alive":-1,"damage":0,"objective":false,"entry":false,"entry_weapon":null},"76561198842037276":{"kills":0,"headshots":0,"assists":0,"time_alive":-1,"damage":0,"objective":false,"entry":false,"entry_weapon":null},"76561198120286262":{"kills":0,"headshots":0,"assists":0,"time_alive":-1,"damage":0,"objective":false,"entry":false,"entry_weapon":null},"76561197961085746":{"kills":0,"headshots":0,"assists":0,"time_alive":-1,"damage":0,"objective":false,"entry":false,"entry_weapon":null}}},{"round_start_time":1707.203125,"round_end_time":1712.21875,"t":"team_noctias","ct":"team_Samaly","winner":null,"players":{"0":{"kills":0,"headshots":0,"assists":0,"time_alive":-1,"damage":0,"objective":false,"entry":false,"entry_weapon":null},"76561198162875654":{"kills":0,"headshots":0,"assists":0,"time_alive":-1,"damage":0,"objective":false,"entry":false,"entry_weapon":null},"76561198033939559":{"kills":0,"headshots":0,"assists":0,"time_alive":-1,"damage":0,"objective":false,"entry":false,"entry_weapon":null},"76561198139429381":{"kills":0,"headshots":0,"assists":0,"time_alive":-1,"damage":0,"objective":false,"entry":false,"entry_weapon":null},"76561198020317127":{"kills":0,"headshots":0,"assists":0,"time_alive":-1,"damage":0,"objective":false,"entry":false,"entry_weapon":null},"76561197993761807":{"kills":0,"headshots":0,"assists":0,"time_alive":-1,"damage":0,"objective":false,"entry":false,"entry_weapon":null},"76561198062153950":{"kills":0,"headshots":0,"assists":0,"time_alive":-1,"damage":0,"objective":false,"entry":false,"entry_weapon":null},"76561198038246134":{"kills":0,"headshots":0,"assists":0,"time_alive":-1,"damage":0,"objective":false,"entry":false,"entry_weapon":null},"76561198842037276":{"kills":0,"headshots":0,"assists":0,"time_alive":-1,"damage":0,"objective":false,"entry":false,"entry_weapon":null},"76561198120286262":{"kills":0,"headshots":0,"assists":0,"time_alive":-1,"damage":0,"objective":false,"entry":false,"entry_weapon":null},"76561197961085746":{"kills":0,"headshots":0,"assists":0,"time_alive":-1,"damage":0,"objective":false,"entry":false,"entry_weapon":null}}},{"round_start_time":1762.0703125,"round_end_time":1767.0859375,"t":"team_noctias","ct":"team_Samaly","winner":null,"players":{"0":{"kills":0,"headshots":0,"assists":0,"time_alive":-1,"damage":0,"objective":false,"entry":false,"entry_weapon":null},"76561197993761807":{"kills":0,"headshots":0,"assists":0,"time_alive":-1,"damage":0,"objective":true,"entry":false,"entry_weapon":null},"76561198162875654":{"kills":0,"headshots":0,"assists":0,"time_alive":-1,"damage":0,"objective":false,"entry":false,"entry_weapon":null},"76561198033939559":{"kills":0,"headshots":0,"assists":0,"time_alive":-1,"damage":0,"objective":false,"entry":false,"entry_weapon":null},"76561198139429381":{"kills":0,"headshots":0,"assists":0,"time_alive":-1,"damage":0,"objective":false,"entry":false,"entry_weapon":null},"76561198020317127":{"kills":0,"headshots":0,"assists":0,"time_alive":-1,"damage":0,"objective":false,"entry":false,"entry_weapon":null},"76561198062153950":{"kills":0,"headshots":0,"assists":0,"time_alive":-1,"damage":0,"objective":false,"entry":false,"entry_weapon":null},"76561198038246134":{"kills":0,"headshots":0,"assists":0,"time_alive":-1,"damage":0,"objective":false,"entry":false,"entry_weapon":null},"76561198842037276":{"kills":0,"headshots":0,"assists":0,"time_alive":-1,"damage":0,"objective":false,"entry":false,"entry_weapon":null},"76561198120286262":{"kills":0,"headshots":0,"assists":0,"time_alive":-1,"damage":0,"objective":false,"entry":false,"entry_weapon":null},"76561197961085746":{"kills":0,"headshots":0,"assists":0,"time_alive":-1,"damage":0,"objective":false,"entry":false,"entry_weapon":null}}},{"round_start_time":1846.765625,"round_end_time":1851.8203125,"t":"team_noctias","ct":"team_Samaly","winner":null,"players":{"0":{"kills":0,"headshots":0,"assists":0,"time_alive":-1,"damage":0,"objective":false,"entry":false,"entry_weapon":null},"76561198162875654":{"kills":0,"headshots":0,"assists":0,"time_alive":-1,"damage":0,"objective":false,"entry":false,"entry_weapon":null},"76561198033939559":{"kills":0,"headshots":0,"assists":0,"time_alive":-1,"damage":0,"objective":false,"entry":false,"entry_weapon":null},"76561198139429381":{"kills":0,"headshots":0,"assists":0,"time_alive":-1,"damage":0,"objective":false,"entry":false,"entry_weapon":null},"76561198020317127":{"kills":0,"headshots":0,"assists":0,"time_alive":-1,"damage":0,"objective":false,"entry":false,"entry_weapon":null},"76561197993761807":{"kills":0,"headshots":0,"assists":0,"time_alive":-1,"damage":0,"objective":false,"entry":false,"entry_weapon":null},"76561198062153950":{"kills":0,"headshots":0,"assists":0,"time_alive":-1,"damage":0,"objective":false,"entry":false,"entry_weapon":null},"76561198038246134":{"kills":0,"headshots":0,"assists":0,"time_alive":-1,"damage":0,"objective":false,"entry":false,"entry_weapon":null},"76561198842037276":{"kills":0,"headshots":0,"assists":0,"time_alive":-1,"damage":0,"objective":false,"entry":false,"entry_weapon":null},"76561198120286262":{"kills":0,"headshots":0,"assists":0,"time_alive":-1,"damage":0,"objective":false,"entry":false,"entry_weapon":null},"76561197961085746":{"kills":0,"headshots":0,"assists":0,"time_alive":-1,"damage":0,"objective":false,"entry":false,"entry_weapon":null}}},{"round_start_time":1943.203125,"round_end_time":1948.1875,"t":"team_noctias","ct":"team_Samaly","winner":null,"players":{"0":{"kills":0,"headshots":0,"assists":0,"time_alive":-1,"damage":0,"objective":false,"entry":false,"entry_weapon":null},"76561198120286262":{"kills":1,"headshots":0,"assists":0,"time_alive":3.546875,"damage":0,"objective":false,"entry":false,"entry_weapon":null,"wp_mp9":1,"wp_mp9_hs":0},"76561197961085746":{"kills":0,"headshots":0,"assists":1,"time_alive":-1,"damage":0,"objective":false,"entry":false,"entry_weapon":null},"76561198162875654":{"kills":0,"headshots":0,"assists":0,"time_alive":1.90625,"damage":0,"objective":false,"entry":false,"entry_weapon":null},"76561198038246134":{"kills":1,"headshots":0,"assists":0,"time_alive":-1,"damage":0,"objective":false,"entry":false,"entry_weapon":null,"wp_ak47":1,"wp_ak47_hs":0},"undefined":{"kills":0,"headshots":0,"assists":1,"time_alive":-1,"damage":0,"objective":false,"entry":false,"entry_weapon":null},"76561198033939559":{"kills":0,"headshots":0,"assists":0,"time_alive":-1,"damage":0,"objective":false,"entry":false,"entry_weapon":null},"76561198139429381":{"kills":0,"headshots":0,"assists":0,"time_alive":-1,"damage":0,"objective":false,"entry":false,"entry_weapon":null},"76561198020317127":{"kills":0,"headshots":0,"assists":0,"time_alive":-1,"damage":0,"objective":false,"entry":false,"entry_weapon":null},"76561197993761807":{"kills":0,"headshots":0,"assists":0,"time_alive":-1,"damage":0,"objective":false,"entry":false,"entry_weapon":null},"76561198062153950":{"kills":0,"headshots":0,"assists":0,"time_alive":-1,"damage":0,"objective":false,"entry":false,"entry_weapon":null},"76561198842037276":{"kills":0,"headshots":0,"assists":0,"time_alive":-1,"damage":0,"objective":false,"entry":false,"entry_weapon":null}}},{"round_start_time":2037.359375,"round_end_time":2042.4140625,"t":"team_noctias","ct":"team_Samaly","winner":null,"players":{"0":{"kills":0,"headshots":0,"assists":0,"time_alive":-1,"damage":0,"objective":false,"entry":false,"entry_weapon":null},"76561198162875654":{"kills":0,"headshots":0,"assists":0,"time_alive":-1,"damage":0,"objective":false,"entry":false,"entry_weapon":null},"76561198033939559":{"kills":0,"headshots":0,"assists":0,"time_alive":-1,"damage":0,"objective":false,"entry":false,"entry_weapon":null},"76561198139429381":{"kills":0,"headshots":0,"assists":0,"time_alive":-1,"damage":0,"objective":false,"entry":false,"entry_weapon":null},"76561198020317127":{"kills":0,"headshots":0,"assists":0,"time_alive":-1,"damage":0,"objective":false,"entry":false,"entry_weapon":null},"76561197993761807":{"kills":0,"headshots":0,"assists":0,"time_alive":-1,"damage":0,"objective":false,"entry":false,"entry_weapon":null},"76561198062153950":{"kills":0,"headshots":0,"assists":0,"time_alive":-1,"damage":0,"objective":false,"entry":false,"entry_weapon":null},"76561198038246134":{"kills":0,"headshots":0,"assists":0,"time_alive":-1,"damage":0,"objective":false,"entry":false,"entry_weapon":null},"76561198842037276":{"kills":0,"headshots":0,"assists":0,"time_alive":-1,"damage":0,"objective":false,"entry":false,"entry_weapon":null},"76561198120286262":{"kills":0,"headshots":0,"assists":0,"time_alive":-1,"damage":0,"objective":false,"entry":false,"entry_weapon":null},"76561197961085746":{"kills":0,"headshots":0,"assists":0,"time_alive":-1,"damage":0,"objective":false,"entry":false,"entry_weapon":null}}},{"round_start_time":2125.2421875,"round_end_time":2130.2578125,"t":"team_noctias","ct":"team_Samaly","winner":null,"players":{"0":{"kills":0,"headshots":0,"assists":0,"time_alive":-1,"damage":0,"objective":false,"entry":false,"entry_weapon":null},"76561198162875654":{"kills":0,"headshots":0,"assists":0,"time_alive":-1,"damage":0,"objective":false,"entry":false,"entry_weapon":null},"76561198033939559":{"kills":0,"headshots":0,"assists":0,"time_alive":-1,"damage":0,"objective":false,"entry":false,"entry_weapon":null},"76561198139429381":{"kills":0,"headshots":0,"assists":0,"time_alive":-1,"damage":0,"objective":false,"entry":false,"entry_weapon":null},"76561198020317127":{"kills":0,"headshots":0,"assists":0,"time_alive":-1,"damage":0,"objective":false,"entry":false,"entry_weapon":null},"76561197993761807":{"kills":0,"headshots":0,"assists":0,"time_alive":-1,"damage":0,"objective":false,"entry":false,"entry_weapon":null},"76561198062153950":{"kills":0,"headshots":0,"assists":0,"time_alive":-1,"damage":0,"objective":false,"entry":false,"entry_weapon":null},"76561198038246134":{"kills":0,"headshots":0,"assists":0,"time_alive":-1,"damage":0,"objective":false,"entry":false,"entry_weapon":null},"76561198842037276":{"kills":0,"headshots":0,"assists":0,"time_alive":-1,"damage":0,"objective":false,"entry":false,"entry_weapon":null},"76561198120286262":{"kills":0,"headshots":0,"assists":0,"time_alive":-1,"damage":0,"objective":false,"entry":false,"entry_weapon":null},"76561197961085746":{"kills":0,"headshots":0,"assists":0,"time_alive":-1,"damage":0,"objective":false,"entry":false,"entry_weapon":null}}},{"round_start_time":2208.46875,"round_end_time":2213.5234375,"t":"team_noctias","ct":"team_Samaly","winner":null,"players":{"0":{"kills":0,"headshots":0,"assists":0,"time_alive":-1,"damage":0,"objective":false,"entry":false,"entry_weapon":null},"76561198162875654":{"kills":0,"headshots":0,"assists":0,"time_alive":-1,"damage":0,"objective":false,"entry":false,"entry_weapon":null},"76561198033939559":{"kills":0,"headshots":0,"assists":0,"time_alive":-1,"damage":0,"objective":false,"entry":false,"entry_weapon":null},"76561198139429381":{"kills":0,"headshots":0,"assists":0,"time_alive":-1,"damage":0,"objective":false,"entry":false,"entry_weapon":null},"76561198020317127":{"kills":0,"headshots":0,"assists":0,"time_alive":-1,"damage":0,"objective":false,"entry":false,"entry_weapon":null},"76561197993761807":{"kills":0,"headshots":0,"assists":0,"time_alive":-1,"damage":0,"objective":false,"entry":false,"entry_weapon":null},"76561198062153950":{"kills":0,"headshots":0,"assists":0,"time_alive":-1,"damage":0,"objective":false,"entry":false,"entry_weapon":null},"76561198038246134":{"kills":0,"headshots":0,"assists":0,"time_alive":-1,"damage":0,"objective":false,"entry":false,"entry_weapon":null},"76561198842037276":{"kills":0,"headshots":0,"assists":0,"time_alive":-1,"damage":0,"objective":false,"entry":false,"entry_weapon":null},"76561198120286262":{"kills":0,"headshots":0,"assists":0,"time_alive":-1,"damage":0,"objective":false,"entry":false,"entry_weapon":null},"76561197961085746":{"kills":0,"headshots":0,"assists":0,"time_alive":-1,"damage":0,"objective":false,"entry":false,"entry_weapon":null}}},{"round_start_time":2273.7109375,"round_end_time":2278.765625,"t":"team_noctias","ct":"team_Samaly","winner":null,"players":{"0":{"kills":0,"headshots":0,"assists":0,"time_alive":-1,"damage":0,"objective":false,"entry":false,"entry_weapon":null},"76561198162875654":{"kills":0,"headshots":0,"assists":0,"time_alive":-1,"damage":0,"objective":false,"entry":false,"entry_weapon":null},"76561198033939559":{"kills":0,"headshots":0,"assists":0,"time_alive":-1,"damage":0,"objective":false,"entry":false,"entry_weapon":null},"76561198139429381":{"kills":0,"headshots":0,"assists":0,"time_alive":-1,"damage":0,"objective":false,"entry":false,"entry_weapon":null},"76561198020317127":{"kills":0,"headshots":0,"assists":0,"time_alive":-1,"damage":0,"objective":false,"entry":false,"entry_weapon":null},"76561197993761807":{"kills":0,"headshots":0,"assists":0,"time_alive":-1,"damage":0,"objective":false,"entry":false,"entry_weapon":null},"76561198062153950":{"kills":0,"headshots":0,"assists":0,"time_alive":-1,"damage":0,"objective":false,"entry":false,"entry_weapon":null},"76561198038246134":{"kills":0,"headshots":0,"assists":0,"time_alive":-1,"damage":0,"objective":false,"entry":false,"entry_weapon":null},"76561198842037276":{"kills":0,"headshots":0,"assists":0,"time_alive":-1,"damage":0,"objective":false,"entry":false,"entry_weapon":null},"76561198120286262":{"kills":0,"headshots":0,"assists":0,"time_alive":-1,"damage":0,"objective":false,"entry":false,"entry_weapon":null},"76561197961085746":{"kills":0,"headshots":0,"assists":0,"time_alive":-1,"damage":0,"objective":false,"entry":false,"entry_weapon":null}}}]}