{"date":"2019-03-19T06:50:56.616Z","map":"de_inferno","team1_name":"team_Seul_GI","team2_name":"team_Hero5k","team1_players":{"76561198066567567":"Seul_GI","76561198055350646":"Delib","76561198210808119":"ZawiszaGames","76561198035478071":"Chronos006","76561198045855183":"Zabiba"},"team2_players":{"76561198325440775":"Ryeocha","76561198046999713":"ワイヤード","76561198100925955":"Hero5k","76561198062484109":"TEEDOG16","76561198035140517":"jinsooerino"},"rounds":[{"round_start_time":101.4140625,"round_end_time":198.28125,"t":"team_Seul_GI","ct":"team_Hero5k","winner":"team_Hero5k","players":{"0":{"kills":0,"headshots":0,"assists":0,"time_alive":-1,"damage":0,"objective":false,"entry":false,"entry_weapon":null},"76561198062484109":{"kills":1,"headshots":1,"assists":0,"time_alive":26.234375,"damage":100,"objective":false,"entry":true,"entry_weapon":"usp_silencer","wp_usp_silencer":1,"wp_usp_silencer_hs":1},"undefined":{"kills":0,"headshots":0,"assists":5,"time_alive":-1,"damage":0,"objective":false,"entry":false,"entry_weapon":null},"76561198066567567":{"kills":0,"headshots":0,"assists":0,"time_alive":24.53125,"damage":0,"objective":false,"entry":false,"entry_weapon":null},"76561198210808119":{"kills":1,"headshots":1,"assists":0,"time_alive":82.6640625,"damage":26,"objective":true,"entry":false,"entry_weapon":null,"wp_glock":1,"wp_glock_hs":1},"76561198035478071":{"kills":1,"headshots":0,"assists":2,"time_alive":39.7890625,"damage":282,"objective":false,"entry":false,"entry_weapon":null,"wp_glock":1,"wp_glock_hs":0},"76561198325440775":{"kills":0,"headshots":0,"assists":1,"time_alive":32.59375,"damage":44,"objective":false,"entry":false,"entry_weapon":null},"76561198100925955":{"kills":1,"headshots":0,"assists":0,"time_alive":40.6796875,"damage":105,"objective":false,"entry":false,"entry_weapon":null,"wp_usp_silencer":1,"wp_usp_silencer_hs":0},"76561198035140517":{"kills":3,"headshots":3,"assists":0,"time_alive":-1,"damage":251,"objective":true,"entry":false,"entry_weapon":null,"wp_hkp2000":3,"wp_hkp2000_hs":3},"76561198055350646":{"kills":0,"headshots":0,"assists":0,"time_alive":40.2890625,"damage":0,"objective":false,"entry":false,"entry_weapon":null},"76561198045855183":{"kills":1,"headshots":1,"assists":0,"time_alive":42.0859375,"damage":104,"objective":false,"entry":false,"entry_weapon":null,"wp_glock":1,"wp_glock_hs":1},"76561198046999713":{"kills":0,"headshots":0,"assists":0,"time_alive":-1,"damage":0,"objective":false,"entry":false,"entry_weapon":null}}},{"round_start_time":203.328125,"round_end_time":251.875,"t":"team_Seul_GI","ct":"team_Hero5k","winner":"team_Hero5k","players":{"0":{"kills":0,"headshots":0,"assists":0,"time_alive":-1,"damage":0,"objective":false,"entry":false,"entry_weapon":null},"76561198062484109":{"kills":4,"headshots":3,"assists":0,"time_alive":-1,"damage":333,"objective":false,"entry":true,"entry_weapon":"famas","wp_famas":4,"wp_famas_hs":3},"undefined":{"kills":0,"headshots":0,"assists":5,"time_alive":-1,"damage":0,"objective":false,"entry":false,"entry_weapon":null},"76561198066567567":{"kills":0,"headshots":0,"assists":0,"time_alive":31.265625,"damage":0,"objective":false,"entry":false,"entry_weapon":null},"76561198035478071":{"kills":0,"headshots":0,"assists":0,"time_alive":38.078125,"damage":0,"objective":false,"entry":false,"entry_weapon":null},"76561198210808119":{"kills":0,"headshots":0,"assists":0,"time_alive":42.328125,"damage":91,"objective":false,"entry":false,"entry_weapon":null},"76561198055350646":{"kills":0,"headshots":0,"assists":0,"time_alive":44.796875,"damage":0,"objective":false,"entry":false,"entry_weapon":null},"76561198035140517":{"kills":1,"headshots":1,"assists":0,"time_alive":-1,"damage":100,"objective":false,"entry":false,"entry_weapon":null,"wp_m4a1":1,"wp_m4a1_hs":1},"76561198045855183":{"kills":0,"headshots":0,"assists":0,"time_alive":48.546875,"damage":57,"objective":false,"entry":false,"entry_weapon":null},"76561198325440775":{"kills":0,"headshots":0,"assists":0,"time_alive":-1,"damage":18,"objective":false,"entry":false,"entry_weapon":null},"76561198046999713":{"kills":0,"headshots":0,"assists":0,"time_alive":-1,"damage":16,"objective":false,"entry":false,"entry_weapon":null},"76561198100925955":{"kills":0,"headshots":0,"assists":0,"time_alive":-1,"damage":33,"objective":false,"entry":false,"entry_weapon":null}}},{"round_start_time":256.890625,"round_end_time":331.421875,"t":"team_Seul_GI","ct":"team_Hero5k","winner":"team_Seul_GI","players":{"0":{"kills":0,"headshots":0,"assists":0,"time_alive":-1,"damage":0,"objective":false,"entry":false,"entry_weapon":null},"76561198035140517":{"kills":2,"headshots":0,"assists":0,"time_alive":53.140625,"damage":130,"objective":false,"entry":true,"entry_weapon":"m4a1","wp_m4a1":2,"wp_m4a1_hs":0},"76561198046999713":{"kills":0,"headshots":0,"assists":2,"time_alive":55.828125,"damage":143,"objective":false,"entry":false,"entry_weapon":null},"76561198066567567":{"kills":0,"headshots":0,"assists":0,"time_alive":22.25,"damage":0,"objective":false,"entry":false,"entry_weapon":null},"undefined":{"kills":0,"headshots":0,"assists":5,"time_alive":-1,"damage":0,"objective":false,"entry":false,"entry_weapon":null},"76561198210808119":{"kills":0,"headshots":0,"assists":0,"time_alive":52.8125,"damage":26,"objective":false,"entry":false,"entry_weapon":null},"76561198055350646":{"kills":1,"headshots":1,"assists":0,"time_alive":61.203125,"damage":135,"objective":false,"entry":false,"entry_weapon":null,"wp_ak47":1,"wp_ak47_hs":1},"76561198035478071":{"kills":2,"headshots":0,"assists":0,"time_alive":-1,"damage":107,"objective":false,"entry":false,"entry_weapon":null,"wp_ak47":2,"wp_ak47_hs":0},"76561198045855183":{"kills":2,"headshots":0,"assists":1,"time_alive":-1,"damage":232,"objective":false,"entry":false,"entry_weapon":null,"wp_ak47":1,"wp_ak47_hs":0,"wp_glock":1,"wp_glock_hs":0},"76561198325440775":{"kills":0,"headshots":0,"assists":0,"time_alive":59.421875,"damage":33,"objective":false,"entry":false,"entry_weapon":null},"76561198062484109":{"kills":1,"headshots":0,"assists":0,"time_alive":74.53125,"damage":46,"objective":false,"entry":false,"entry_weapon":null,"wp_famas":1,"wp_famas_hs":0},"76561198100925955":{"kills":0,"headshots":0,"assists":0,"time_alive":69.296875,"damage":27,"objective":false,"entry":false,"entry_weapon":null}}},{"round_start_time":336.421875,"round_end_time":406.8046875,"t":"team_Seul_GI","ct":"team_Hero5k","winner":"team_Seul_GI","players":{"0":{"kills":0,"headshots":0,"assists":0,"time_alive":-1,"damage":0,"objective":false,"entry":false,"entry_weapon":null},"76561198325440775":{"kills":2,"headshots":0,"assists":0,"time_alive":46.0234375,"damage":220,"objective":false,"entry":true,"entry_weapon":"p250","wp_p250":2,"wp_p250_hs":0},"undefined":{"kills":0,"headshots":0,"assists":4,"time_alive":-1,"damage":0,"objective":false,"entry":false,"entry_weapon":null},"76561198210808119":{"kills":0,"headshots":0,"assists":0,"time_alive":24.7734375,"damage":0,"objective":false,"entry":false,"entry_weapon":null},"76561198045855183":{"kills":3,"headshots":1,"assists":0,"time_alive":-1,"damage":173,"objective":true,"entry":false,"entry_weapon":null,"wp_ak47":2,"wp_ak47_hs":1,"wp_hegrenade":1,"wp_hegrenade_hs":0},"76561198035140517":{"kills":0,"headshots":0,"assists":0,"time_alive":24.7890625,"damage":0,"objective":false,"entry":false,"entry_weapon":null},"76561198066567567":{"kills":0,"headshots":0,"assists":3,"time_alive":-1,"damage":203,"objective":false,"entry":false,"entry_weapon":null},"76561198100925955":{"kills":0,"headshots":0,"assists":0,"time_alive":32.3046875,"damage":3,"objective":false,"entry":false,"entry_weapon":null},"76561198035478071":{"kills":0,"headshots":0,"assists":0,"time_alive":45.3671875,"damage":0,"objective":false,"entry":false,"entry_weapon":null},"76561198055350646":{"kills":2,"headshots":0,"assists":0,"time_alive":-1,"damage":124,"objective":false,"entry":false,"entry_weapon":null,"wp_ak47":2,"wp_ak47_hs":0},"76561198046999713":{"kills":0,"headshots":0,"assists":0,"time_alive":50.6328125,"damage":90,"objective":false,"entry":false,"entry_weapon":null},"76561198062484109":{"kills":0,"headshots":0,"assists":0,"time_alive":70.3828125,"damage":10,"objective":false,"entry":false,"entry_weapon":null}}},{"round_start_time":411.8671875,"round_end_time":454.4375,"t":"team_Seul_GI","ct":"team_Hero5k","winner":"team_Hero5k","players":{"0":{"kills":0,"headshots":0,"assists":0,"time_alive":-1,"damage":0,"objective":false,"entry":false,"entry_weapon":null},"76561198035140517":{"kills":3,"headshots":2,"assists":0,"time_alive":-1,"damage":300,"objective":false,"entry":true,"entry_weapon":"awp","wp_awp":3,"wp_awp_hs":2},"undefined":{"kills":0,"headshots":0,"assists":5,"time_alive":-1,"damage":0,"objective":false,"entry":false,"entry_weapon":null},"76561198210808119":{"kills":0,"headshots":0,"assists":0,"time_alive":21.5234375,"damage":0,"objective":false,"entry":false,"entry_weapon":null},"76561198035478071":{"kills":0,"headshots":0,"assists":0,"time_alive":24.1953125,"damage":0,"objective":false,"entry":false,"entry_weapon":null},"76561198046999713":{"kills":1,"headshots":0,"assists":0,"time_alive":-1,"damage":100,"objective":false,"entry":false,"entry_weapon":null,"wp_m4a1_silencer":1,"wp_m4a1_silencer_hs":0},"76561198055350646":{"kills":0,"headshots":0,"assists":0,"time_alive":29.1484375,"damage":0,"objective":false,"entry":false,"entry_weapon":null},"76561198045855183":{"kills":0,"headshots":0,"assists":0,"time_alive":32.4296875,"damage":29,"objective":false,"entry":false,"entry_weapon":null},"76561198100925955":{"kills":1,"headshots":1,"assists":0,"time_alive":-1,"damage":100,"objective":false,"entry":false,"entry_weapon":null,"wp_m4a1":1,"wp_m4a1_hs":1},"76561198066567567":{"kills":0,"headshots":0,"assists":0,"time_alive":42.5703125,"damage":78,"objective":false,"entry":false,"entry_weapon":null},"76561198325440775":{"kills":0,"headshots":0,"assists":0,"time_alive":-1,"damage":0,"objective":false,"entry":false,"entry_weapon":null},"76561198062484109":{"kills":0,"headshots":0,"assists":0,"time_alive":-1,"damage":0,"objective":false,"entry":false,"entry_weapon":null}}},{"round_start_time":459.4375,"round_end_time":516.96875,"t":"team_Seul_GI","ct":"team_Hero5k","winner":"team_Seul_GI","players":{"0":{"kills":0,"headshots":0,"assists":0,"time_alive":-1,"damage":0,"objective":false,"entry":false,"entry_weapon":null},"76561198210808119":{"kills":2,"headshots":2,"assists":0,"time_alive":34.71875,"damage":200,"objective":false,"entry":true,"entry_weapon":"p250","wp_p250":2,"wp_p250_hs":2},"undefined":{"kills":0,"headshots":0,"assists":7,"time_alive":-1,"damage":0,"objective":false,"entry":false,"entry_weapon":null},"76561198035140517":{"kills":0,"headshots":0,"assists":0,"time_alive":32.625,"damage":28,"objective":false,"entry":false,"entry_weapon":null},"76561198046999713":{"kills":0,"headshots":0,"assists":0,"time_alive":34,"damage":0,"objective":false,"entry":false,"entry_weapon":null},"76561198062484109":{"kills":1,"headshots":0,"assists":0,"time_alive":38.03125,"damage":126,"objective":false,"entry":false,"entry_weapon":null,"wp_ak47":1,"wp_ak47_hs":0},"76561198045855183":{"kills":1,"headshots":0,"assists":0,"time_alive":-1,"damage":100,"objective":false,"entry":false,"entry_weapon":null,"wp_ak47":1,"wp_ak47_hs":0},"76561198055350646":{"kills":1,"headshots":0,"assists":0,"time_alive":-1,"damage":100,"objective":false,"entry":false,"entry_weapon":null,"wp_p250":1,"wp_p250_hs":0},"76561198325440775":{"kills":0,"headshots":0,"assists":0,"time_alive":41.484375,"damage":43,"objective":false,"entry":false,"entry_weapon":null},"76561198035478071":{"kills":1,"headshots":0,"assists":0,"time_alive":-1,"damage":100,"objective":true,"entry":false,"entry_weapon":null,"wp_awp":1,"wp_awp_hs":0},"76561198100925955":{"kills":1,"headshots":1,"assists":0,"time_alive":57.53125,"damage":100,"objective":false,"entry":false,"entry_weapon":null,"wp_ak47":1,"wp_ak47_hs":1},"76561198066567567":{"kills":0,"headshots":0,"assists":0,"time_alive":53.9375,"damage":0,"objective":false,"entry":false,"entry_weapon":null}}},{"round_start_time":522.046875,"round_end_time":593.25,"t":"team_Seul_GI","ct":"team_Hero5k","winner":"team_Seul_GI","players":{"0":{"kills":0,"headshots":0,"assists":0,"time_alive":-1,"damage":0,"objective":false,"entry":false,"entry_weapon":null},"76561198045855183":{"kills":2,"headshots":1,"assists":0,"time_alive":-1,"damage":135,"objective":false,"entry":true,"entry_weapon":"hegrenade","wp_hegrenade":1,"wp_hegrenade_hs":0,"wp_ak47":1,"wp_ak47_hs":1},"76561198210808119":{"kills":1,"headshots":0,"assists":1,"time_alive":-1,"damage":128,"objective":false,"entry":false,"entry_weapon":null,"wp_ak47":1,"wp_ak47_hs":0},"76561198035140517":{"kills":0,"headshots":0,"assists":0,"time_alive":23.59375,"damage":31,"objective":false,"entry":false,"entry_weapon":null},"76561198066567567":{"kills":1,"headshots":1,"assists":1,"time_alive":-1,"damage":191,"objective":true,"entry":false,"entry_weapon":null,"wp_ak47":1,"wp_ak47_hs":1},"undefined":{"kills":0,"headshots":0,"assists":3,"time_alive":-1,"damage":0,"objective":false,"entry":false,"entry_weapon":null},"76561198325440775":{"kills":0,"headshots":0,"assists":1,"time_alive":47.796875,"damage":98,"objective":false,"entry":false,"entry_weapon":null},"76561198100925955":{"kills":0,"headshots":0,"assists":0,"time_alive":50.46875,"damage":94,"objective":false,"entry":false,"entry_weapon":null},"76561198046999713":{"kills":1,"headshots":0,"assists":0,"time_alive":71.203125,"damage":29,"objective":false,"entry":false,"entry_weapon":null,"wp_mp9":1,"wp_mp9_hs":0},"76561198055350646":{"kills":0,"headshots":0,"assists":0,"time_alive":53.875,"damage":0,"objective":false,"entry":false,"entry_weapon":null},"76561198062484109":{"kills":0,"headshots":0,"assists":0,"time_alive":54.671875,"damage":0,"objective":false,"entry":false,"entry_weapon":null},"76561198035478071":{"kills":1,"headshots":0,"assists":0,"time_alive":-1,"damage":46,"objective":false,"entry":false,"entry_weapon":null,"wp_awp":1,"wp_awp_hs":0}}},{"round_start_time":598.265625,"round_end_time":691.796875,"t":"team_Seul_GI","ct":"team_Hero5k","winner":"team_Seul_GI","players":{"0":{"kills":0,"headshots":0,"assists":0,"time_alive":-1,"damage":0,"objective":false,"entry":false,"entry_weapon":null},"76561198046999713":{"kills":1,"headshots":1,"assists":1,"time_alive":37.046875,"damage":128,"objective":false,"entry":true,"entry_weapon":"m4a1_silencer","wp_m4a1_silencer":1,"wp_m4a1_silencer_hs":1},"76561198035140517":{"kills":0,"headshots":0,"assists":1,"time_alive":36.390625,"damage":88,"objective":false,"entry":false,"entry_weapon":null},"76561198066567567":{"kills":0,"headshots":0,"assists":0,"time_alive":35.640625,"damage":0,"objective":false,"entry":false,"entry_weapon":null},"76561198055350646":{"kills":1,"headshots":0,"assists":0,"time_alive":-1,"damage":100,"objective":true,"entry":false,"entry_weapon":null,"wp_ak47":1,"wp_ak47_hs":0},"undefined":{"kills":0,"headshots":0,"assists":4,"time_alive":-1,"damage":0,"objective":false,"entry":false,"entry_weapon":null},"76561198210808119":{"kills":1,"headshots":0,"assists":0,"time_alive":47.671875,"damage":105,"objective":false,"entry":false,"entry_weapon":null,"wp_ak47":1,"wp_ak47_hs":0},"76561198035478071":{"kills":1,"headshots":1,"assists":0,"time_alive":-1,"damage":184,"objective":false,"entry":false,"entry_weapon":null,"wp_p250":1,"wp_p250_hs":1},"76561198325440775":{"kills":0,"headshots":0,"assists":0,"time_alive":44.40625,"damage":0,"objective":false,"entry":false,"entry_weapon":null},"76561198062484109":{"kills":1,"headshots":0,"assists":0,"time_alive":49.6875,"damage":6,"objective":false,"entry":false,"entry_weapon":null,"wp_m4a1":1,"wp_m4a1_hs":0},"76561198045855183":{"kills":1,"headshots":0,"assists":0,"time_alive":-1,"damage":95,"objective":false,"entry":false,"entry_weapon":null,"wp_ak47":1,"wp_ak47_hs":0},"76561198100925955":{"kills":0,"headshots":0,"assists":0,"time_alive":-1,"damage":0,"objective":false,"entry":false,"entry_weapon":null}}},{"round_start_time":696.796875,"round_end_time":822.8671875,"t":"team_Seul_GI","ct":"team_Hero5k","winner":"team_Seul_GI","players":{"0":{"kills":0,"headshots":0,"assists":0,"time_alive":-1,"damage":0,"objective":false,"entry":false,"entry_weapon":null},"76561198100925955":{"kills":1,"headshots":0,"assists":0,"time_alive":91.6953125,"damage":100,"objective":false,"entry":true,"entry_weapon":"ak47","wp_ak47":1,"wp_ak47_hs":0},"undefined":{"kills":0,"headshots":0,"assists":7,"time_alive":-1,"damage":0,"objective":false,"entry":false,"entry_weapon":null},"76561198210808119":{"kills":0,"headshots":0,"assists":0,"time_alive":24.9140625,"damage":0,"objective":false,"entry":false,"entry_weapon":null},"76561198066567567":{"kills":1,"headshots":0,"assists":1,"time_alive":42.7578125,"damage":164,"objective":false,"entry":false,"entry_weapon":null,"wp_ak47":1,"wp_ak47_hs":0},"76561198062484109":{"kills":0,"headshots":0,"assists":1,"time_alive":38.4765625,"damage":73,"objective":false,"entry":false,"entry_weapon":null},"76561198055350646":{"kills":1,"headshots":0,"assists":0,"time_alive":41.5078125,"damage":36,"objective":false,"entry":false,"entry_weapon":null,"wp_ak47":1,"wp_ak47_hs":0},"76561198035140517":{"kills":0,"headshots":0,"assists":0,"time_alive":40.2109375,"damage":0,"objective":false,"entry":false,"entry_weapon":null},"76561198325440775":{"kills":4,"headshots":0,"assists":0,"time_alive":-1,"damage":327,"objective":false,"entry":false,"entry_weapon":null,"wp_famas":2,"wp_famas_hs":0,"wp_ak47":2,"wp_ak47_hs":0},"76561198045855183":{"kills":0,"headshots":0,"assists":0,"time_alive":113.5546875,"damage":59,"objective":true,"entry":false,"entry_weapon":null},"76561198035478071":{"kills":2,"headshots":0,"assists":0,"time_alive":111.1171875,"damage":200,"objective":false,"entry":false,"entry_weapon":null,"wp_awp":2,"wp_awp_hs":0},"76561198046999713":{"kills":0,"headshots":0,"assists":0,"time_alive":101.4296875,"damage":0,"objective":false,"entry":false,"entry_weapon":null}}},{"round_start_time":827.8671875,"round_end_time":889.4375,"t":"team_Seul_GI","ct":"team_Hero5k","winner":"team_Hero5k","players":{"0":{"kills":0,"headshots":0,"assists":0,"time_alive":-1,"damage":0,"objective":false,"entry":false,"entry_weapon":null},"76561198035478071":{"kills":1,"headshots":1,"assists":0,"time_alive":36.9609375,"damage":100,"objective":false,"entry":true,"entry_weapon":"ak47","wp_ak47":1,"wp_ak47_hs":1},"undefined":{"kills":0,"headshots":0,"assists":2,"time_alive":-1,"damage":0,"objective":false,"entry":false,"entry_weapon":null},"76561198035140517":{"kills":0,"headshots":0,"assists":1,"time_alive":34.3828125,"damage":85,"objective":false,"entry":false,"entry_weapon":null},"76561198066567567":{"kills":1,"headshots":0,"assists":0,"time_alive":34.7578125,"damage":0,"objective":false,"entry":false,"entry_weapon":null,"wp_inferno":1,"wp_inferno_hs":0},"76561198046999713":{"kills":1,"headshots":0,"assists":1,"time_alive":-1,"damage":85,"objective":false,"entry":false,"entry_weapon":null,"wp_m4a1_silencer":1,"wp_m4a1_silencer_hs":0},"76561198325440775":{"kills":1,"headshots":1,"assists":0,"time_alive":52.4921875,"damage":99,"objective":false,"entry":false,"entry_weapon":null,"wp_ak47":1,"wp_ak47_hs":1},"76561198055350646":{"kills":0,"headshots":0,"assists":1,"time_alive":39.6328125,"damage":61,"objective":false,"entry":false,"entry_weapon":null},"76561198062484109":{"kills":2,"headshots":0,"assists":0,"time_alive":-1,"damage":54,"objective":false,"entry":false,"entry_weapon":null,"wp_mag7":1,"wp_mag7_hs":0,"wp_p250":1,"wp_p250_hs":0},"76561198100925955":{"kills":0,"headshots":0,"assists":2,"time_alive":-1,"damage":146,"objective":false,"entry":false,"entry_weapon":null},"76561198210808119":{"kills":0,"headshots":0,"assists":0,"time_alive":48.2109375,"damage":0,"objective":false,"entry":false,"entry_weapon":null},"76561198045855183":{"kills":1,"headshots":0,"assists":0,"time_alive":61.5703125,"damage":102,"objective":false,"entry":false,"entry_weapon":null,"wp_ak47":1,"wp_ak47_hs":0}}},{"round_start_time":894.4765625,"round_end_time":1006.8359375,"t":"team_Seul_GI","ct":"team_Hero5k","winner":"team_Hero5k","players":{"0":{"kills":0,"headshots":0,"assists":0,"time_alive":-1,"damage":0,"objective":false,"entry":false,"entry_weapon":null},"76561198035140517":{"kills":1,"headshots":0,"assists":1,"time_alive":95.78125,"damage":155,"objective":false,"entry":true,"entry_weapon":"awp","wp_awp":1,"wp_awp_hs":0},"undefined":{"kills":0,"headshots":0,"assists":6,"time_alive":-1,"damage":0,"objective":false,"entry":false,"entry_weapon":null},"76561198035478071":{"kills":0,"headshots":0,"assists":0,"time_alive":60.546875,"damage":0,"objective":false,"entry":false,"entry_weapon":null},"76561198210808119":{"kills":1,"headshots":1,"assists":0,"time_alive":76.6875,"damage":100,"objective":false,"entry":false,"entry_weapon":null,"wp_deagle":1,"wp_deagle_hs":1},"76561198100925955":{"kills":0,"headshots":0,"assists":0,"time_alive":62.703125,"damage":0,"objective":false,"entry":false,"entry_weapon":null},"76561198062484109":{"kills":2,"headshots":1,"assists":0,"time_alive":-1,"damage":117,"objective":false,"entry":false,"entry_weapon":null,"wp_m4a1":2,"wp_m4a1_hs":1},"76561198045855183":{"kills":0,"headshots":0,"assists":0,"time_alive":68.5625,"damage":52,"objective":false,"entry":false,"entry_weapon":null},"76561198325440775":{"kills":1,"headshots":0,"assists":0,"time_alive":-1,"damage":91,"objective":false,"entry":false,"entry_weapon":null,"wp_famas":1,"wp_famas_hs":0},"76561198046999713":{"kills":1,"headshots":1,"assists":0,"time_alive":94.875,"damage":137,"objective":false,"entry":false,"entry_weapon":null,"wp_ak47":1,"wp_ak47_hs":1},"76561198055350646":{"kills":0,"headshots":0,"assists":1,"time_alive":85.640625,"damage":93,"objective":false,"entry":false,"entry_weapon":null},"76561198066567567":{"kills":2,"headshots":0,"assists":0,"time_alive":112.359375,"damage":91,"objective":false,"entry":false,"entry_weapon":null,"wp_deagle":2,"wp_deagle_hs":0}}},{"round_start_time":1011.8359375,"round_end_time":1083.25,"t":"team_Seul_GI","ct":"team_Hero5k","winner":"team_Hero5k","players":{"0":{"kills":0,"headshots":0,"assists":0,"time_alive":-1,"damage":0,"objective":false,"entry":false,"entry_weapon":null},"76561198035140517":{"kills":3,"headshots":1,"assists":0,"time_alive":-1,"damage":241,"objective":false,"entry":true,"entry_weapon":"awp","wp_awp":3,"wp_awp_hs":1},"undefined":{"kills":0,"headshots":0,"assists":6,"time_alive":-1,"damage":0,"objective":false,"entry":false,"entry_weapon":null},"76561198210808119":{"kills":0,"headshots":0,"assists":0,"time_alive":23.0234375,"damage":0,"objective":false,"entry":false,"entry_weapon":null},"76561198045855183":{"kills":0,"headshots":0,"assists":0,"time_alive":25.0703125,"damage":0,"objective":false,"entry":false,"entry_weapon":null},"76561198325440775":{"kills":1,"headshots":1,"assists":0,"time_alive":36.0546875,"damage":124,"objective":false,"entry":false,"entry_weapon":null,"wp_m4a1":1,"wp_m4a1_hs":1},"76561198035478071":{"kills":0,"headshots":0,"assists":0,"time_alive":32.1328125,"damage":0,"objective":false,"entry":false,"entry_weapon":null},"76561198066567567":{"kills":1,"headshots":0,"assists":0,"time_alive":68.5390625,"damage":215,"objective":false,"entry":false,"entry_weapon":null,"wp_ak47":1,"wp_ak47_hs":0},"76561198055350646":{"kills":1,"headshots":1,"assists":0,"time_alive":71.4140625,"damage":100,"objective":false,"entry":false,"entry_weapon":null,"wp_ak47":1,"wp_ak47_hs":1},"76561198062484109":{"kills":0,"headshots":0,"assists":1,"time_alive":67.5546875,"damage":59,"objective":false,"entry":false,"entry_weapon":null},"76561198046999713":{"kills":1,"headshots":0,"assists":0,"time_alive":-1,"damage":76,"objective":false,"entry":false,"entry_weapon":null,"wp_m4a1_silencer":1,"wp_m4a1_silencer_hs":0},"76561198100925955":{"kills":0,"headshots":0,"assists":0,"time_alive":-1,"damage":0,"objective":false,"entry":false,"entry_weapon":null}}},{"round_start_time":1088.25,"round_end_time":1160.3203125,"t":"team_Seul_GI","ct":"team_Hero5k","winner":"team_Hero5k","players":{"0":{"kills":0,"headshots":0,"assists":0,"time_alive":-1,"damage":0,"objective":false,"entry":false,"entry_weapon":null},"76561198035478071":{"kills":1,"headshots":1,"assists":0,"time_alive":33.8515625,"damage":100,"objective":false,"entry":true,"entry_weapon":"deagle","wp_deagle":1,"wp_deagle_hs":1},"undefined":{"kills":0,"headshots":0,"assists":7,"time_alive":-1,"damage":0,"objective":false,"entry":false,"entry_weapon":null},"76561198035140517":{"kills":0,"headshots":0,"assists":0,"time_alive":25.3515625,"damage":0,"objective":false,"entry":false,"entry_weapon":null},"76561198066567567":{"kills":1,"headshots":1,"assists":0,"time_alive":35.4453125,"damage":122,"objective":false,"entry":false,"entry_weapon":null,"wp_p250":1,"wp_p250_hs":1},"76561198062484109":{"kills":0,"headshots":0,"assists":1,"time_alive":26.4921875,"damage":92,"objective":false,"entry":false,"entry_weapon":null},"76561198325440775":{"kills":1,"headshots":0,"assists":0,"time_alive":59.6484375,"damage":140,"objective":false,"entry":false,"entry_weapon":null,"wp_xm1014":1,"wp_xm1014_hs":0},"76561198046999713":{"kills":3,"headshots":1,"assists":0,"time_alive":-1,"damage":208,"objective":true,"entry":false,"entry_weapon":null,"wp_m4a1_silencer":2,"wp_m4a1_silencer_hs":0,"wp_m4a1":1,"wp_m4a1_hs":1},"76561198045855183":{"kills":0,"headshots":0,"assists":0,"time_alive":34.1484375,"damage":0,"objective":false,"entry":false,"entry_weapon":null},"76561198210808119":{"kills":0,"headshots":0,"assists":0,"time_alive":60.1328125,"damage":20,"objective":true,"entry":false,"entry_weapon":null},"76561198055350646":{"kills":1,"headshots":0,"assists":0,"time_alive":64.2578125,"damage":100,"objective":false,"entry":false,"entry_weapon":null,"wp_awp":1,"wp_awp_hs":0},"76561198100925955":{"kills":1,"headshots":0,"assists":0,"time_alive":-1,"damage":60,"objective":false,"entry":false,"entry_weapon":null,"wp_p250":1,"wp_p250_hs":0}}},{"round_start_time":1165.3671875,"round_end_time":1237.5,"t":"team_Seul_GI","ct":"team_Hero5k","winner":"team_Hero5k","players":{"0":{"kills":0,"headshots":0,"assists":0,"time_alive":-1,"damage":0,"objective":false,"entry":false,"entry_weapon":null},"76561198100925955":{"kills":2,"headshots":0,"assists":0,"time_alive":-1,"damage":200,"objective":false,"entry":true,"entry_weapon":"awp","wp_awp":2,"wp_awp_hs":0},"undefined":{"kills":0,"headshots":0,"assists":6,"time_alive":-1,"damage":0,"objective":false,"entry":false,"entry_weapon":null},"76561198055350646":{"kills":0,"headshots":0,"assists":0,"time_alive":23.8203125,"damage":0,"objective":false,"entry":false,"entry_weapon":null},"76561198035140517":{"kills":1,"headshots":0,"assists":0,"time_alive":30.0078125,"damage":100,"objective":false,"entry":false,"entry_weapon":null,"wp_awp":1,"wp_awp_hs":0},"76561198066567567":{"kills":0,"headshots":0,"assists":0,"time_alive":29.9453125,"damage":26,"objective":false,"entry":false,"entry_weapon":null},"76561198035478071":{"kills":1,"headshots":1,"assists":0,"time_alive":43.4765625,"damage":100,"objective":false,"entry":false,"entry_weapon":null,"wp_ak47":1,"wp_ak47_hs":1},"76561198045855183":{"kills":0,"headshots":0,"assists":0,"time_alive":37.6484375,"damage":108,"objective":false,"entry":false,"entry_weapon":null},"76561198062484109":{"kills":2,"headshots":1,"assists":0,"time_alive":-1,"damage":200,"objective":true,"entry":false,"entry_weapon":null,"wp_xm1014":2,"wp_xm1014_hs":1},"76561198210808119":{"kills":0,"headshots":0,"assists":0,"time_alive":60.4765625,"damage":0,"objective":true,"entry":false,"entry_weapon":null},"76561198325440775":{"kills":0,"headshots":0,"assists":0,"time_alive":-1,"damage":0,"objective":false,"entry":false,"entry_weapon":null},"76561198046999713":{"kills":0,"headshots":0,"assists":0,"time_alive":-1,"damage":0,"objective":false,"entry":false,"entry_weapon":null}}},{"round_start_time":1242.5,"round_end_time":1346.578125,"t":"team_Seul_GI","ct":"team_Hero5k","winner":"team_Seul_GI","players":{"0":{"kills":0,"headshots":0,"assists":0,"time_alive":-1,"damage":0,"objective":false,"entry":false,"entry_weapon":null},"76561198035140517":{"kills":1,"headshots":1,"assists":0,"time_alive":63.296875,"damage":100,"objective":false,"entry":true,"entry_weapon":"awp","wp_awp":1,"wp_awp_hs":1},"undefined":{"kills":0,"headshots":0,"assists":5,"time_alive":-1,"damage":0,"objective":false,"entry":false,"entry_weapon":null},"76561198035478071":{"kills":0,"headshots":0,"assists":0,"time_alive":26.796875,"damage":0,"objective":false,"entry":false,"entry_weapon":null},"76561198066567567":{"kills":4,"headshots":1,"assists":0,"time_alive":-1,"damage":234,"objective":false,"entry":false,"entry_weapon":null,"wp_ak47":4,"wp_ak47_hs":1},"76561198210808119":{"kills":0,"headshots":0,"assists":1,"time_alive":96.640625,"damage":98,"objective":false,"entry":false,"entry_weapon":null},"76561198046999713":{"kills":0,"headshots":0,"assists":1,"time_alive":65.59375,"damage":118,"objective":false,"entry":false,"entry_weapon":null},"76561198045855183":{"kills":1,"headshots":1,"assists":1,"time_alive":103.90625,"damage":154,"objective":false,"entry":false,"entry_weapon":null,"wp_ak47":1,"wp_ak47_hs":1},"76561198062484109":{"kills":0,"headshots":0,"assists":0,"time_alive":66.765625,"damage":0,"objective":false,"entry":false,"entry_weapon":null},"76561198055350646":{"kills":0,"headshots":0,"assists":0,"time_alive":-1,"damage":14,"objective":true,"entry":false,"entry_weapon":null},"76561198325440775":{"kills":2,"headshots":2,"assists":0,"time_alive":104.078125,"damage":131,"objective":false,"entry":false,"entry_weapon":null,"wp_ak47":2,"wp_ak47_hs":2},"76561198100925955":{"kills":0,"headshots":0,"assists":0,"time_alive":103.484375,"damage":0,"objective":false,"entry":false,"entry_weapon":null}}},{"round_start_time":1361.578125,"round_end_time":1423.59375,"t":"team_Seul_GI","ct":"team_Hero5k","winner":"team_Hero5k","players":{"0":{"kills":0,"headshots":0,"assists":0,"time_alive":-1,"damage":0,"objective":false,"entry":false,"entry_weapon":null},"76561198100925955":{"kills":1,"headshots":1,"assists":0,"time_alive":60.640625,"damage":94,"objective":false,"entry":true,"entry_weapon":"glock","wp_glock":1,"wp_glock_hs":1},"undefined":{"kills":0,"headshots":0,"assists":8,"time_alive":-1,"damage":0,"objective":false,"entry":false,"entry_weapon":null},"76561198035478071":{"kills":0,"headshots":0,"assists":0,"time_alive":27.421875,"damage":0,"objective":false,"entry":false,"entry_weapon":null},"76561198045855183":{"kills":1,"headshots":1,"assists":0,"time_alive":31.5625,"damage":100,"objective":false,"entry":false,"entry_weapon":null,"wp_usp_silencer":1,"wp_usp_silencer_hs":1},"76561198325440775":{"kills":0,"headshots":0,"assists":0,"time_alive":30.953125,"damage":9,"objective":false,"entry":false,"entry_weapon":null},"76561198035140517":{"kills":3,"headshots":2,"assists":0,"time_alive":-1,"damage":300,"objective":true,"entry":false,"entry_weapon":null,"wp_glock":1,"wp_glock_hs":0,"wp_usp_silencer":2,"wp_usp_silencer_hs":2},"76561198210808119":{"kills":1,"headshots":1,"assists":0,"time_alive":45.875,"damage":132,"objective":false,"entry":false,"entry_weapon":null,"wp_usp_silencer":1,"wp_usp_silencer_hs":1},"76561198046999713":{"kills":0,"headshots":0,"assists":0,"time_alive":43.875,"damage":0,"objective":false,"entry":false,"entry_weapon":null},"76561198062484109":{"kills":1,"headshots":1,"assists":0,"time_alive":-1,"damage":97,"objective":false,"entry":false,"entry_weapon":null,"wp_glock":1,"wp_glock_hs":1},"76561198055350646":{"kills":0,"headshots":0,"assists":0,"time_alive":57.359375,"damage":28,"objective":false,"entry":false,"entry_weapon":null},"76561198066567567":{"kills":1,"headshots":1,"assists":0,"time_alive":62.015625,"damage":84,"objective":false,"entry":false,"entry_weapon":null,"wp_usp_silencer":1,"wp_usp_silencer_hs":1}}},{"round_start_time":1428.609375,"round_end_time":1494.3125,"t":"team_Hero5k","ct":"team_Seul_GI","winner":"team_Hero5k","players":{"0":{"kills":0,"headshots":0,"assists":0,"time_alive":-1,"damage":0,"objective":false,"entry":false,"entry_weapon":null},"76561198035140517":{"kills":1,"headshots":0,"assists":0,"time_alive":31.609375,"damage":77,"objective":false,"entry":true,"entry_weapon":"ump45","wp_ump45":1,"wp_ump45_hs":0},"undefined":{"kills":0,"headshots":0,"assists":6,"time_alive":-1,"damage":0,"objective":false,"entry":false,"entry_weapon":null},"76561198055350646":{"kills":0,"headshots":0,"assists":1,"time_alive":25.3125,"damage":65,"objective":false,"entry":false,"entry_weapon":null},"76561198045855183":{"kills":2,"headshots":0,"assists":0,"time_alive":65.703125,"damage":135,"objective":false,"entry":false,"entry_weapon":null,"wp_p250":2,"wp_p250_hs":0},"76561198046999713":{"kills":2,"headshots":0,"assists":0,"time_alive":65.328125,"damage":207,"objective":true,"entry":false,"entry_weapon":null,"wp_mac10":2,"wp_mac10_hs":0},"76561198210808119":{"kills":0,"headshots":0,"assists":0,"time_alive":36.84375,"damage":39,"objective":false,"entry":false,"entry_weapon":null},"76561198035478071":{"kills":1,"headshots":0,"assists":0,"time_alive":62.953125,"damage":20,"objective":false,"entry":false,"entry_weapon":null,"wp_usp_silencer":1,"wp_usp_silencer_hs":0},"76561198066567567":{"kills":0,"headshots":0,"assists":1,"time_alive":64.15625,"damage":80,"objective":false,"entry":false,"entry_weapon":null},"76561198100925955":{"kills":0,"headshots":0,"assists":0,"time_alive":39.96875,"damage":46,"objective":false,"entry":false,"entry_weapon":null},"76561198062484109":{"kills":2,"headshots":1,"assists":0,"time_alive":-1,"damage":170,"objective":false,"entry":false,"entry_weapon":null,"wp_mac10":2,"wp_mac10_hs":1},"76561198325440775":{"kills":0,"headshots":0,"assists":0,"time_alive":-1,"damage":0,"objective":false,"entry":false,"entry_weapon":null}}},{"round_start_time":1499.375,"round_end_time":1563.0546875,"t":"team_Hero5k","ct":"team_Seul_GI","winner":"team_Hero5k","players":{"0":{"kills":0,"headshots":0,"assists":0,"time_alive":-1,"damage":0,"objective":false,"entry":false,"entry_weapon":null},"76561198325440775":{"kills":3,"headshots":2,"assists":0,"time_alive":-1,"damage":300,"objective":false,"entry":true,"entry_weapon":"ak47","wp_ak47":3,"wp_ak47_hs":2},"undefined":{"kills":0,"headshots":0,"assists":8,"time_alive":-1,"damage":0,"objective":false,"entry":false,"entry_weapon":null},"76561198035478071":{"kills":0,"headshots":0,"assists":0,"time_alive":27.3984375,"damage":0,"objective":false,"entry":false,"entry_weapon":null},"76561198055350646":{"kills":0,"headshots":0,"assists":0,"time_alive":29.8046875,"damage":24,"objective":false,"entry":false,"entry_weapon":null},"76561198062484109":{"kills":1,"headshots":1,"assists":0,"time_alive":35.0234375,"damage":116,"objective":false,"entry":false,"entry_weapon":null,"wp_mac10":1,"wp_mac10_hs":1},"76561198045855183":{"kills":0,"headshots":0,"assists":0,"time_alive":32.7265625,"damage":0,"objective":false,"entry":false,"entry_weapon":null},"76561198210808119":{"kills":3,"headshots":1,"assists":0,"time_alive":63.6796875,"damage":354,"objective":false,"entry":false,"entry_weapon":null,"wp_m4a1":3,"wp_m4a1_hs":1},"76561198066567567":{"kills":0,"headshots":0,"assists":0,"time_alive":36.8984375,"damage":69,"objective":false,"entry":false,"entry_weapon":null},"76561198035140517":{"kills":0,"headshots":0,"assists":0,"time_alive":39.5546875,"damage":0,"objective":false,"entry":false,"entry_weapon":null},"76561198100925955":{"kills":0,"headshots":0,"assists":0,"time_alive":45.8203125,"damage":22,"objective":false,"entry":false,"entry_weapon":null},"76561198046999713":{"kills":1,"headshots":1,"assists":0,"time_alive":-1,"damage":62,"objective":false,"entry":false,"entry_weapon":null,"wp_ak47":1,"wp_ak47_hs":1}}},{"round_start_time":1568.0703125,"round_end_time":1598.96875,"t":"team_Hero5k","ct":"team_Seul_GI","winner":"team_Hero5k","players":{"0":{"kills":0,"headshots":0,"assists":0,"time_alive":-1,"damage":0,"objective":false,"entry":false,"entry_weapon":null},"76561198066567567":{"kills":1,"headshots":1,"assists":0,"time_alive":27.9453125,"damage":99,"objective":false,"entry":true,"entry_weapon":"usp_silencer","wp_usp_silencer":1,"wp_usp_silencer_hs":1},"undefined":{"kills":0,"headshots":0,"assists":3,"time_alive":-1,"damage":0,"objective":false,"entry":false,"entry_weapon":null},"76561198062484109":{"kills":0,"headshots":0,"assists":2,"time_alive":26.3515625,"damage":152,"objective":false,"entry":false,"entry_weapon":null},"76561198046999713":{"kills":4,"headshots":1,"assists":0,"time_alive":-1,"damage":143,"objective":false,"entry":false,"entry_weapon":null,"wp_ak47":4,"wp_ak47_hs":1},"76561198210808119":{"kills":0,"headshots":0,"assists":0,"time_alive":26.3828125,"damage":0,"objective":false,"entry":false,"entry_weapon":null},"76561198035478071":{"kills":0,"headshots":0,"assists":0,"time_alive":27.1640625,"damage":14,"objective":false,"entry":false,"entry_weapon":null},"76561198035140517":{"kills":1,"headshots":0,"assists":1,"time_alive":-1,"damage":188,"objective":false,"entry":false,"entry_weapon":null,"wp_mac10":1,"wp_mac10_hs":0},"76561198055350646":{"kills":0,"headshots":0,"assists":0,"time_alive":29.4453125,"damage":18,"objective":false,"entry":false,"entry_weapon":null},"76561198045855183":{"kills":0,"headshots":0,"assists":0,"time_alive":30.8984375,"damage":47,"objective":false,"entry":false,"entry_weapon":null},"76561198325440775":{"kills":0,"headshots":0,"assists":0,"time_alive":-1,"damage":0,"objective":false,"entry":false,"entry_weapon":null},"76561198100925955":{"kills":0,"headshots":0,"assists":0,"time_alive":-1,"damage":0,"objective":false,"entry":false,"entry_weapon":null}}},{"round_start_time":1603.984375,"round_end_time":1684.875,"t":"team_Hero5k","ct":"team_Seul_GI","winner":"team_Hero5k","players":{"0":{"kills":0,"headshots":0,"assists":0,"time_alive":-1,"damage":0,"objective":false,"entry":false,"entry_weapon":null},"76561198035140517":{"kills":2,"headshots":2,"assists":0,"time_alive":41.59375,"damage":200,"objective":false,"entry":true,"entry_weapon":"ak47","wp_ak47":2,"wp_ak47_hs":2},"undefined":{"kills":0,"headshots":0,"assists":6,"time_alive":-1,"damage":0,"objective":false,"entry":false,"entry_weapon":null},"76561198210808119":{"kills":0,"headshots":0,"assists":0,"time_alive":28.421875,"damage":0,"objective":false,"entry":false,"entry_weapon":null},"76561198045855183":{"kills":0,"headshots":0,"assists":0,"time_alive":32.953125,"damage":50,"objective":false,"entry":false,"entry_weapon":null},"76561198035478071":{"kills":1,"headshots":0,"assists":0,"time_alive":71.21875,"damage":100,"objective":false,"entry":false,"entry_weapon":null,"wp_awp":1,"wp_awp_hs":0},"76561198325440775":{"kills":0,"headshots":0,"assists":1,"time_alive":36.671875,"damage":54,"objective":false,"entry":false,"entry_weapon":null},"76561198100925955":{"kills":0,"headshots":0,"assists":0,"time_alive":-1,"damage":0,"objective":true,"entry":false,"entry_weapon":null},"76561198055350646":{"kills":1,"headshots":0,"assists":0,"time_alive":44.640625,"damage":65,"objective":false,"entry":false,"entry_weapon":null,"wp_m4a1":1,"wp_m4a1_hs":0},"76561198062484109":{"kills":1,"headshots":0,"assists":0,"time_alive":72.640625,"damage":100,"objective":false,"entry":false,"entry_weapon":null,"wp_ak47":1,"wp_ak47_hs":0},"76561198046999713":{"kills":1,"headshots":1,"assists":0,"time_alive":-1,"damage":46,"objective":false,"entry":false,"entry_weapon":null,"wp_ak47":1,"wp_ak47_hs":1},"76561198066567567":{"kills":1,"headshots":0,"assists":0,"time_alive":-1,"damage":85,"objective":false,"entry":false,"entry_weapon":null,"wp_m4a1":1,"wp_m4a1_hs":0}}},{"round_start_time":1689.921875,"round_end_time":1784.75,"t":"team_Hero5k","ct":"team_Seul_GI","winner":"team_Hero5k","players":{"0":{"kills":0,"headshots":0,"assists":0,"time_alive":-1,"damage":0,"objective":false,"entry":false,"entry_weapon":null},"76561198035140517":{"kills":1,"headshots":1,"assists":0,"time_alive":60,"damage":47,"objective":false,"entry":true,"entry_weapon":"awp","wp_awp":1,"wp_awp_hs":1},"76561198046999713":{"kills":1,"headshots":1,"assists":1,"time_alive":-1,"damage":120,"objective":false,"entry":false,"entry_weapon":null,"wp_ak47":1,"wp_ak47_hs":1},"76561198055350646":{"kills":0,"headshots":0,"assists":0,"time_alive":33.265625,"damage":24,"objective":false,"entry":false,"entry_weapon":null},"76561198062484109":{"kills":1,"headshots":0,"assists":0,"time_alive":35.9375,"damage":96,"objective":false,"entry":false,"entry_weapon":null,"wp_ak47":1,"wp_ak47_hs":0},"undefined":{"kills":0,"headshots":0,"assists":6,"time_alive":-1,"damage":0,"objective":false,"entry":false,"entry_weapon":null},"76561198066567567":{"kills":0,"headshots":0,"assists":0,"time_alive":34.9375,"damage":9,"objective":false,"entry":false,"entry_weapon":null},"76561198210808119":{"kills":3,"headshots":2,"assists":0,"time_alive":80.921875,"damage":220,"objective":false,"entry":false,"entry_weapon":null,"wp_p250":2,"wp_p250_hs":2,"wp_awp":1,"wp_awp_hs":0},"76561198035478071":{"kills":0,"headshots":0,"assists":0,"time_alive":45.984375,"damage":81,"objective":false,"entry":false,"entry_weapon":null},"76561198325440775":{"kills":1,"headshots":0,"assists":0,"time_alive":-1,"damage":104,"objective":true,"entry":false,"entry_weapon":null,"wp_ak47":1,"wp_ak47_hs":0},"76561198100925955":{"kills":0,"headshots":0,"assists":0,"time_alive":74.9375,"damage":33,"objective":false,"entry":false,"entry_weapon":null},"76561198045855183":{"kills":0,"headshots":0,"assists":0,"time_alive":-1,"damage":22,"objective":false,"entry":false,"entry_weapon":null}}},{"round_start_time":1789.75,"round_end_time":1870.5234375,"t":"team_Hero5k","ct":"team_Seul_GI","winner":"team_Hero5k","players":{"0":{"kills":0,"headshots":0,"assists":0,"time_alive":-1,"damage":0,"objective":false,"entry":false,"entry_weapon":null},"76561198325440775":{"kills":2,"headshots":0,"assists":0,"time_alive":-1,"damage":234,"objective":true,"entry":true,"entry_weapon":"awp","wp_awp":2,"wp_awp_hs":0},"undefined":{"kills":0,"headshots":0,"assists":8,"time_alive":-1,"damage":0,"objective":false,"entry":false,"entry_weapon":null},"76561198066567567":{"kills":0,"headshots":0,"assists":0,"time_alive":21.4921875,"damage":0,"objective":false,"entry":false,"entry_weapon":null},"76561198210808119":{"kills":3,"headshots":0,"assists":0,"time_alive":52.7578125,"damage":260,"objective":false,"entry":false,"entry_weapon":null,"wp_awp":3,"wp_awp_hs":0},"76561198035140517":{"kills":0,"headshots":0,"assists":0,"time_alive":33.3359375,"damage":0,"objective":false,"entry":false,"entry_weapon":null},"76561198046999713":{"kills":1,"headshots":1,"assists":0,"time_alive":36.8671875,"damage":100,"objective":false,"entry":false,"entry_weapon":null,"wp_ak47":1,"wp_ak47_hs":1},"76561198055350646":{"kills":0,"headshots":0,"assists":0,"time_alive":33.9609375,"damage":40,"objective":false,"entry":false,"entry_weapon":null},"76561198100925955":{"kills":0,"headshots":0,"assists":0,"time_alive":48.7890625,"damage":0,"objective":false,"entry":false,"entry_weapon":null},"76561198062484109":{"kills":2,"headshots":1,"assists":0,"time_alive":-1,"damage":166,"objective":false,"entry":false,"entry_weapon":null,"wp_ak47":2,"wp_ak47_hs":1},"76561198045855183":{"kills":0,"headshots":0,"assists":0,"time_alive":71.6640625,"damage":0,"objective":false,"entry":false,"entry_weapon":null},"76561198035478071":{"kills":0,"headshots":0,"assists":0,"time_alive":80.7734375,"damage":0,"objective":false,"entry":false,"entry_weapon":null}}},{"round_start_time":1875.5234375,"round_end_time":1945.59375,"t":"team_Hero5k","ct":"team_Seul_GI","winner":"team_Seul_GI","players":{"0":{"kills":0,"headshots":0,"assists":0,"time_alive":-1,"damage":0,"objective":false,"entry":false,"entry_weapon":null},"76561198100925955":{"kills":1,"headshots":0,"assists":0,"time_alive":35.6015625,"damage":127,"objective":false,"entry":true,"entry_weapon":"ak47","wp_ak47":1,"wp_ak47_hs":0},"undefined":{"kills":0,"headshots":0,"assists":5,"time_alive":-1,"damage":0,"objective":false,"entry":false,"entry_weapon":null},"76561198035478071":{"kills":0,"headshots":0,"assists":0,"time_alive":21.8828125,"damage":0,"objective":false,"entry":false,"entry_weapon":null},"76561198210808119":{"kills":1,"headshots":1,"assists":1,"time_alive":38.7265625,"damage":93,"objective":false,"entry":false,"entry_weapon":null,"wp_m4a1":1,"wp_m4a1_hs":1},"76561198045855183":{"kills":1,"headshots":0,"assists":1,"time_alive":64.6171875,"damage":107,"objective":false,"entry":false,"entry_weapon":null,"wp_p250":1,"wp_p250_hs":0},"76561198062484109":{"kills":0,"headshots":0,"assists":1,"time_alive":28.5390625,"damage":99,"objective":false,"entry":false,"entry_weapon":null},"76561198066567567":{"kills":2,"headshots":1,"assists":0,"time_alive":38.9921875,"damage":254,"objective":false,"entry":false,"entry_weapon":null,"wp_deagle":1,"wp_deagle_hs":0,"wp_ak47":1,"wp_ak47_hs":1},"76561198035140517":{"kills":0,"headshots":0,"assists":0,"time_alive":37.7109375,"damage":0,"objective":false,"entry":false,"entry_weapon":null},"76561198325440775":{"kills":1,"headshots":0,"assists":0,"time_alive":45.2421875,"damage":86,"objective":false,"entry":false,"entry_weapon":null,"wp_awp":1,"wp_awp_hs":0},"76561198046999713":{"kills":2,"headshots":0,"assists":0,"time_alive":-1,"damage":181,"objective":true,"entry":false,"entry_weapon":null,"wp_ak47":2,"wp_ak47_hs":0},"76561198055350646":{"kills":0,"headshots":0,"assists":0,"time_alive":-1,"damage":0,"objective":true,"entry":false,"entry_weapon":null}}},{"round_start_time":1950.6484375,"round_end_time":1987.234375,"t":"team_Hero5k","ct":"team_Seul_GI","winner":"team_Seul_GI","players":{"0":{"kills":0,"headshots":0,"assists":0,"time_alive":-1,"damage":0,"objective":false,"entry":false,"entry_weapon":null},"76561198055350646":{"kills":1,"headshots":0,"assists":0,"time_alive":24.9765625,"damage":102,"objective":false,"entry":true,"entry_weapon":"m4a1","wp_m4a1":1,"wp_m4a1_hs":0},"undefined":{"kills":0,"headshots":0,"assists":6,"time_alive":-1,"damage":0,"objective":false,"entry":false,"entry_weapon":null},"76561198035140517":{"kills":0,"headshots":0,"assists":0,"time_alive":23.7421875,"damage":0,"objective":false,"entry":false,"entry_weapon":null},"76561198062484109":{"kills":2,"headshots":1,"assists":0,"time_alive":27.2421875,"damage":258,"objective":false,"entry":false,"entry_weapon":null,"wp_inferno":1,"wp_inferno_hs":0,"wp_mac10":1,"wp_mac10_hs":1},"76561198210808119":{"kills":0,"headshots":0,"assists":1,"time_alive":25.0078125,"damage":88,"objective":false,"entry":false,"entry_weapon":null},"76561198045855183":{"kills":2,"headshots":0,"assists":0,"time_alive":-1,"damage":110,"objective":false,"entry":false,"entry_weapon":null,"wp_m4a1":2,"wp_m4a1_hs":0},"76561198035478071":{"kills":1,"headshots":1,"assists":0,"time_alive":-1,"damage":100,"objective":false,"entry":false,"entry_weapon":null,"wp_famas":1,"wp_famas_hs":1},"76561198325440775":{"kills":0,"headshots":0,"assists":0,"time_alive":29.9921875,"damage":0,"objective":false,"entry":false,"entry_weapon":null},"76561198066567567":{"kills":1,"headshots":0,"assists":0,"time_alive":-1,"damage":100,"objective":false,"entry":false,"entry_weapon":null,"wp_m4a1":1,"wp_m4a1_hs":0},"76561198100925955":{"kills":0,"headshots":0,"assists":0,"time_alive":35.6640625,"damage":0,"objective":false,"entry":false,"entry_weapon":null},"76561198046999713":{"kills":0,"headshots":0,"assists":0,"time_alive":36.5859375,"damage":0,"objective":false,"entry":false,"entry_weapon":null}}},{"round_start_time":1992.296875,"round_end_time":2038.8515625,"t":"team_Hero5k","ct":"team_Seul_GI","winner":"team_Hero5k","players":{"0":{"kills":0,"headshots":0,"assists":0,"time_alive":-1,"damage":0,"objective":false,"entry":false,"entry_weapon":null},"76561198035140517":{"kills":1,"headshots":1,"assists":0,"time_alive":29.2109375,"damage":100,"objective":false,"entry":true,"entry_weapon":"ak47","wp_ak47":1,"wp_ak47_hs":1},"undefined":{"kills":0,"headshots":0,"assists":7,"time_alive":-1,"damage":0,"objective":false,"entry":false,"entry_weapon":null},"76561198055350646":{"kills":0,"headshots":0,"assists":0,"time_alive":25.8671875,"damage":0,"objective":false,"entry":false,"entry_weapon":null},"76561198045855183":{"kills":2,"headshots":0,"assists":1,"time_alive":41.3046875,"damage":312,"objective":false,"entry":false,"entry_weapon":null,"wp_ak47":2,"wp_ak47_hs":0},"76561198062484109":{"kills":3,"headshots":2,"assists":0,"time_alive":-1,"damage":208,"objective":false,"entry":false,"entry_weapon":null,"wp_ak47":3,"wp_ak47_hs":2},"76561198066567567":{"kills":0,"headshots":0,"assists":0,"time_alive":30.0859375,"damage":0,"objective":false,"entry":false,"entry_weapon":null},"76561198325440775":{"kills":0,"headshots":0,"assists":1,"time_alive":31.7421875,"damage":111,"objective":false,"entry":false,"entry_weapon":null},"76561198035478071":{"kills":2,"headshots":1,"assists":0,"time_alive":43.3984375,"damage":88,"objective":false,"entry":false,"entry_weapon":null,"wp_ak47":2,"wp_ak47_hs":1},"76561198100925955":{"kills":0,"headshots":0,"assists":0,"time_alive":38.4609375,"damage":33,"objective":false,"entry":false,"entry_weapon":null},"76561198046999713":{"kills":1,"headshots":0,"assists":0,"time_alive":42.5546875,"damage":33,"objective":false,"entry":false,"entry_weapon":null,"wp_ak47":1,"wp_ak47_hs":0},"76561198210808119":{"kills":0,"headshots":0,"assists":0,"time_alive":46.5546875,"damage":83,"objective":false,"entry":false,"entry_weapon":null}}}],"rounds_end":[{"round_start_time":198.28125,"round_end_time":203.328125,"t":"team_Seul_GI","ct":"team_Hero5k","winner":null,"players":{"0":{"kills":0,"headshots":0,"assists":0,"time_alive":-1,"damage":0,"objective":false,"entry":false,"entry_weapon":null},"76561198325440775":{"kills":0,"headshots":0,"assists":0,"time_alive":-1,"damage":0,"objective":false,"entry":false,"entry_weapon":null},"76561198046999713":{"kills":0,"headshots":0,"assists":0,"time_alive":-1,"damage":0,"objective":false,"entry":false,"entry_weapon":null},"76561198066567567":{"kills":0,"headshots":0,"assists":0,"time_alive":-1,"damage":0,"objective":false,"entry":false,"entry_weapon":null},"76561198100925955":{"kills":0,"headshots":0,"assists":0,"time_alive":-1,"damage":0,"objective":false,"entry":false,"entry_weapon":null},"76561198062484109":{"kills":0,"headshots":0,"assists":0,"time_alive":-1,"damage":0,"objective":false,"entry":false,"entry_weapon":null},"76561198055350646":{"kills":0,"headshots":0,"assists":0,"time_alive":-1,"damage":0,"objective":false,"entry":false,"entry_weapon":null},"76561198210808119":{"kills":0,"headshots":0,"assists":0,"time_alive":-1,"damage":0,"objective":false,"entry":false,"entry_weapon":null},"76561198035478071":{"kills":0,"headshots":0,"assists":0,"time_alive":-1,"damage":0,"objective":false,"entry":false,"entry_weapon":null},"76561198035140517":{"kills":0,"headshots":0,"assists":0,"time_alive":-1,"damage":0,"objective":false,"entry":false,"entry_weapon":null},"76561198045855183":{"kills":0,"headshots":0,"assists":0,"time_alive":-1,"damage":0,"objective":false,"entry":false,"entry_weapon":null}}},{"round_start_time":251.875,"round_end_time":256.890625,"t":"team_Seul_GI","ct":"team_Hero5k","winner":null,"players":{"0":{"kills":0,"headshots":0,"assists":0,"time_alive":-1,"damage":0,"objective":false,"entry":false,"entry_weapon":null},"76561198325440775":{"kills":0,"headshots":0,"assists":0,"time_alive":-1,"damage":0,"objective":false,"entry":false,"entry_weapon":null},"76561198046999713":{"kills":0,"headshots":0,"assists":0,"time_alive":-1,"damage":0,"objective":false,"entry":false,"entry_weapon":null},"76561198066567567":{"kills":0,"headshots":0,"assists":0,"time_alive":-1,"damage":0,"objective":false,"entry":false,"entry_weapon":null},"76561198100925955":{"kills":0,"headshots":0,"assists":0,"time_alive":-1,"damage":0,"objective":false,"entry":false,"entry_weapon":null},"76561198062484109":{"kills":0,"headshots":0,"assists":0,"time_alive":-1,"damage":0,"objective":false,"entry":false,"entry_weapon":null},"76561198055350646":{"kills":0,"headshots":0,"assists":0,"time_alive":-1,"damage":0,"objective":false,"entry":false,"entry_weapon":null},"76561198210808119":{"kills":0,"headshots":0,"assists":0,"time_alive":-1,"damage":0,"objective":false,"entry":false,"entry_weapon":null},"76561198035478071":{"kills":0,"headshots":0,"assists":0,"time_alive":-1,"damage":0,"objective":false,"entry":false,"entry_weapon":null},"76561198035140517":{"kills":0,"headshots":0,"assists":0,"time_alive":-1,"damage":0,"objective":false,"entry":false,"entry_weapon":null},"76561198045855183":{"kills":0,"headshots":0,"assists":0,"time_alive":-1,"damage":0,"objective":false,"entry":false,"entry_weapon":null}}},{"round_start_time":331.421875,"round_end_time":336.421875,"t":"team_Seul_GI","ct":"team_Hero5k","winner":null,"players":{"0":{"kills":0,"headshots":0,"assists":0,"time_alive":-1,"damage":0,"objective":false,"entry":false,"entry_weapon":null},"76561198325440775":{"kills":0,"headshots":0,"assists":0,"time_alive":-1,"damage":0,"objective":false,"entry":false,"entry_weapon":null},"76561198046999713":{"kills":0,"headshots":0,"assists":0,"time_alive":-1,"damage":0,"objective":false,"entry":false,"entry_weapon":null},"76561198066567567":{"kills":0,"headshots":0,"assists":0,"time_alive":-1,"damage":0,"objective":false,"entry":false,"entry_weapon":null},"76561198100925955":{"kills":0,"headshots":0,"assists":0,"time_alive":-1,"damage":0,"objective":false,"entry":false,"entry_weapon":null},"76561198062484109":{"kills":0,"headshots":0,"assists":0,"time_alive":-1,"damage":0,"objective":false,"entry":false,"entry_weapon":null},"76561198055350646":{"kills":0,"headshots":0,"assists":0,"time_alive":-1,"damage":0,"objective":false,"entry":false,"entry_weapon":null},"76561198210808119":{"kills":0,"headshots":0,"assists":0,"time_alive":-1,"damage":0,"objective":false,"entry":false,"entry_weapon":null},"76561198035478071":{"kills":0,"headshots":0,"assists":0,"time_alive":-1,"damage":0,"objective":false,"entry":false,"entry_weapon":null},"76561198035140517":{"kills":0,"headshots":0,"assists":0,"time_alive":-1,"damage":0,"objective":false,"entry":false,"entry_weapon":null},"76561198045855183":{"kills":0,"headshots":0,"assists":0,"time_alive":-1,"damage":0,"objective":false,"entry":false,"entry_weapon":null}}},{"round_start_time":406.8046875,"round_end_time":411.8671875,"t":"team_Seul_GI","ct":"team_Hero5k","winner":null,"players":{"0":{"kills":0,"headshots":0,"assists":0,"time_alive":-1,"damage":0,"objective":false,"entry":false,"entry_weapon":null},"76561198325440775":{"kills":0,"headshots":0,"assists":0,"time_alive":-1,"damage":0,"objective":false,"entry":false,"entry_weapon":null},"76561198046999713":{"kills":0,"headshots":0,"assists":0,"time_alive":-1,"damage":0,"objective":false,"entry":false,"entry_weapon":null},"76561198066567567":{"kills":0,"headshots":0,"assists":0,"time_alive":-1,"damage":0,"objective":false,"entry":false,"entry_weapon":null},"76561198100925955":{"kills":0,"headshots":0,"assists":0,"time_alive":-1,"damage":0,"objective":false,"entry":false,"entry_weapon":null},"76561198062484109":{"kills":0,"headshots":0,"assists":0,"time_alive":-1,"damage":0,"objective":false,"entry":false,"entry_weapon":null},"76561198055350646":{"kills":0,"headshots":0,"assists":0,"time_alive":-1,"damage":0,"objective":false,"entry":false,"entry_weapon":null},"76561198210808119":{"kills":0,"headshots":0,"assists":0,"time_alive":-1,"damage":0,"objective":false,"entry":false,"entry_weapon":null},"76561198035478071":{"kills":0,"headshots":0,"assists":0,"time_alive":-1,"damage":0,"objective":false,"entry":false,"entry_weapon":null},"76561198035140517":{"kills":0,"headshots":0,"assists":0,"time_alive":-1,"damage":0,"objective":false,"entry":false,"entry_weapon":null},"76561198045855183":{"kills":0,"headshots":0,"assists":0,"time_alive":-1,"damage":0,"objective":false,"entry":false,"entry_weapon":null}}},{"round_start_time":454.4375,"round_end_time":459.4375,"t":"team_Seul_GI","ct":"team_Hero5k","winner":null,"players":{"0":{"kills":0,"headshots":0,"assists":0,"time_alive":-1,"damage":0,"objective":false,"entry":false,"entry_weapon":null},"76561198325440775":{"kills":0,"headshots":0,"assists":0,"time_alive":-1,"damage":0,"objective":false,"entry":false,"entry_weapon":null},"76561198046999713":{"kills":0,"headshots":0,"assists":0,"time_alive":-1,"damage":0,"objective":false,"entry":false,"entry_weapon":null},"76561198066567567":{"kills":0,"headshots":0,"assists":0,"time_alive":-1,"damage":0,"objective":false,"entry":false,"entry_weapon":null},"76561198100925955":{"kills":0,"headshots":0,"assists":0,"time_alive":-1,"damage":0,"objective":false,"entry":false,"entry_weapon":null},"76561198062484109":{"kills":0,"headshots":0,"assists":0,"time_alive":-1,"damage":0,"objective":false,"entry":false,"entry_weapon":null},"76561198055350646":{"kills":0,"headshots":0,"assists":0,"time_alive":-1,"damage":0,"objective":false,"entry":false,"entry_weapon":null},"76561198210808119":{"kills":0,"headshots":0,"assists":0,"time_alive":-1,"damage":0,"objective":false,"entry":false,"entry_weapon":null},"76561198035478071":{"kills":0,"headshots":0,"assists":0,"time_alive":-1,"damage":0,"objective":false,"entry":false,"entry_weapon":null},"76561198035140517":{"kills":0,"headshots":0,"assists":0,"time_alive":-1,"damage":0,"objective":false,"entry":false,"entry_weapon":null},"76561198045855183":{"kills":0,"headshots":0,"assists":0,"time_alive":-1,"damage":0,"objective":false,"entry":false,"entry_weapon":null}}},{"round_start_time":516.96875,"round_end_time":522.046875,"t":"team_Seul_GI","ct":"team_Hero5k","winner":null,"players":{"0":{"kills":0,"headshots":0,"assists":0,"time_alive":-1,"damage":0,"objective":false,"entry":false,"entry_weapon":null},"76561198325440775":{"kills":0,"headshots":0,"assists":0,"time_alive":-1,"damage":0,"objective":false,"entry":false,"entry_weapon":null},"76561198046999713":{"kills":0,"headshots":0,"assists":0,"time_alive":-1,"damage":0,"objective":false,"entry":false,"entry_weapon":null},"76561198066567567":{"kills":0,"headshots":0,"assists":0,"time_alive":-1,"damage":0,"objective":false,"entry":false,"entry_weapon":null},"76561198100925955":{"kills":0,"headshots":0,"assists":0,"time_alive":-1,"damage":0,"objective":false,"entry":false,"entry_weapon":null},"76561198062484109":{"kills":0,"headshots":0,"assists":0,"time_alive":-1,"damage":0,"objective":false,"entry":false,"entry_weapon":null},"76561198055350646":{"kills":0,"headshots":0,"assists":0,"time_alive":-1,"damage":0,"objective":false,"entry":false,"entry_weapon":null},"76561198210808119":{"kills":0,"headshots":0,"assists":0,"time_alive":-1,"damage":0,"objective":false,"entry":false,"entry_weapon":null},"76561198035478071":{"kills":0,"headshots":0,"assists":0,"time_alive":-1,"damage":0,"objective":false,"entry":false,"entry_weapon":null},"76561198035140517":{"kills":0,"headshots":0,"assists":0,"time_alive":-1,"damage":0,"objective":false,"entry":false,"entry_weapon":null},"76561198045855183":{"kills":0,"headshots":0,"assists":0,"time_alive":-1,"damage":0,"objective":false,"entry":false,"entry_weapon":null}}},{"round_start_time":593.25,"round_end_time":598.265625,"t":"team_Seul_GI","ct":"team_Hero5k","winner":null,"players":{"0":{"kills":0,"headshots":0,"assists":0,"time_alive":-1,"damage":0,"objective":false,"entry":false,"entry_weapon":null},"76561198325440775":{"kills":0,"headshots":0,"assists":0,"time_alive":-1,"damage":0,"objective":false,"entry":false,"entry_weapon":null},"76561198046999713":{"kills":0,"headshots":0,"assists":0,"time_alive":-1,"damage":0,"objective":false,"entry":false,"entry_weapon":null},"76561198066567567":{"kills":0,"headshots":0,"assists":0,"time_alive":-1,"damage":0,"objective":false,"entry":false,"entry_weapon":null},"76561198100925955":{"kills":0,"headshots":0,"assists":0,"time_alive":-1,"damage":0,"objective":false,"entry":false,"entry_weapon":null},"76561198062484109":{"kills":0,"headshots":0,"assists":0,"time_alive":-1,"damage":0,"objective":false,"entry":false,"entry_weapon":null},"76561198055350646":{"kills":0,"headshots":0,"assists":0,"time_alive":-1,"damage":0,"objective":false,"entry":false,"entry_weapon":null},"76561198210808119":{"kills":0,"headshots":0,"assists":0,"time_alive":-1,"damage":0,"objective":false,"entry":false,"entry_weapon":null},"76561198035478071":{"kills":0,"headshots":0,"assists":0,"time_alive":-1,"damage":0,"objective":false,"entry":false,"entry_weapon":null},"76561198035140517":{"kills":0,"headshots":0,"assists":0,"time_alive":-1,"damage":0,"objective":false,"entry":false,"entry_weapon":null},"76561198045855183":{"kills":0,"headshots":0,"assists":0,"time_alive":-1,"damage":0,"objective":false,"entry":false,"entry_weapon":null}}},{"round_start_time":691.796875,"round_end_time":696.796875,"t":"team_Seul_GI","ct":"team_Hero5k","winner":null,"players":{"0":{"kills":0,"headshots":0,"assists":0,"time_alive":-1,"damage":0,"objective":false,"entry":false,"entry_weapon":null},"76561198100925955":{"kills":1,"headshots":0,"assists":0,"time_alive":-1,"damage":0,"objective":false,"entry":false,"entry_weapon":null,"wp_m4a1":1,"wp_m4a1_hs":0},"undefined":{"kills":0,"headshots":0,"assists":1,"time_alive":-1,"damage":0,"objective":false,"entry":false,"entry_weapon":null},"76561198055350646":{"kills":0,"headshots":0,"assists":0,"time_alive":0.984375,"damage":0,"objective":false,"entry":false,"entry_weapon":null},"76561198325440775":{"kills":0,"headshots":0,"assists":0,"time_alive":-1,"damage":0,"objective":false,"entry":false,"entry_weapon":null},"76561198046999713":{"kills":0,"headshots":0,"assists":0,"time_alive":-1,"damage":0,"objective":false,"entry":false,"entry_weapon":null},"76561198066567567":{"kills":0,"headshots":0,"assists":0,"time_alive":-1,"damage":0,"objective":false,"entry":false,"entry_weapon":null},"76561198062484109":{"kills":0,"headshots":0,"assists":0,"time_alive":-1,"damage":0,"objective":false,"entry":false,"entry_weapon":null},"76561198210808119":{"kills":0,"headshots":0,"assists":0,"time_alive":-1,"damage":0,"objective":false,"entry":false,"entry_weapon":null},"76561198035478071":{"kills":0,"headshots":0,"assists":0,"time_alive":-1,"damage":0,"objective":false,"entry":false,"entry_weapon":null},"76561198035140517":{"kills":0,"headshots":0,"assists":0,"time_alive":-1,"damage":0,"objective":false,"entry":false,"entry_weapon":null},"76561198045855183":{"kills":0,"headshots":0,"assists":0,"time_alive":-1,"damage":0,"objective":false,"entry":false,"entry_weapon":null}}},{"round_start_time":822.8671875,"round_end_time":827.8671875,"t":"team_Seul_GI","ct":"team_Hero5k","winner":null,"players":{"0":{"kills":0,"headshots":0,"assists":0,"time_alive":-1,"damage":0,"objective":false,"entry":false,"entry_weapon":null},"76561198325440775":{"kills":0,"headshots":0,"assists":0,"time_alive":-1,"damage":0,"objective":false,"entry":false,"entry_weapon":null},"76561198046999713":{"kills":0,"headshots":0,"assists":0,"time_alive":-1,"damage":0,"objective":false,"entry":false,"entry_weapon":null},"76561198066567567":{"kills":0,"headshots":0,"assists":0,"time_alive":-1,"damage":0,"objective":false,"entry":false,"entry_weapon":null},"76561198100925955":{"kills":0,"headshots":0,"assists":0,"time_alive":-1,"damage":0,"objective":false,"entry":false,"entry_weapon":null},"76561198062484109":{"kills":0,"headshots":0,"assists":0,"time_alive":-1,"damage":0,"objective":false,"entry":false,"entry_weapon":null},"76561198055350646":{"kills":0,"headshots":0,"assists":0,"time_alive":-1,"damage":0,"objective":false,"entry":false,"entry_weapon":null},"76561198210808119":{"kills":0,"headshots":0,"assists":0,"time_alive":-1,"damage":0,"objective":false,"entry":false,"entry_weapon":null},"76561198035478071":{"kills":0,"headshots":0,"assists":0,"time_alive":-1,"damage":0,"objective":false,"entry":false,"entry_weapon":null},"76561198035140517":{"kills":0,"headshots":0,"assists":0,"time_alive":-1,"damage":0,"objective":false,"entry":false,"entry_weapon":null},"76561198045855183":{"kills":0,"headshots":0,"assists":0,"time_alive":-1,"damage":0,"objective":false,"entry":false,"entry_weapon":null}}},{"round_start_time":889.4375,"round_end_time":894.4765625,"t":"team_Seul_GI","ct":"team_Hero5k","winner":null,"players":{"0":{"kills":0,"headshots":0,"assists":0,"time_alive":-1,"damage":0,"objective":false,"entry":false,"entry_weapon":null},"76561198325440775":{"kills":0,"headshots":0,"assists":0,"time_alive":-1,"damage":0,"objective":false,"entry":false,"entry_weapon":null},"76561198046999713":{"kills":0,"headshots":0,"assists":0,"time_alive":-1,"damage":0,"objective":false,"entry":false,"entry_weapon":null},"76561198066567567":{"kills":0,"headshots":0,"assists":0,"time_alive":-1,"damage":0,"objective":false,"entry":false,"entry_weapon":null},"76561198100925955":{"kills":0,"headshots":0,"assists":0,"time_alive":-1,"damage":0,"objective":false,"entry":false,"entry_weapon":null},"76561198062484109":{"kills":0,"headshots":0,"assists":0,"time_alive":-1,"damage":0,"objective":false,"entry":false,"entry_weapon":null},"76561198055350646":{"kills":0,"headshots":0,"assists":0,"time_alive":-1,"damage":0,"objective":false,"entry":false,"entry_weapon":null},"76561198210808119":{"kills":0,"headshots":0,"assists":0,"time_alive":-1,"damage":0,"objective":false,"entry":false,"entry_weapon":null},"76561198035478071":{"kills":0,"headshots":0,"assists":0,"time_alive":-1,"damage":0,"objective":false,"entry":false,"entry_weapon":null},"76561198035140517":{"kills":0,"headshots":0,"assists":0,"time_alive":-1,"damage":0,"objective":false,"entry":false,"entry_weapon":null},"76561198045855183":{"kills":0,"headshots":0,"assists":0,"time_alive":-1,"damage":0,"objective":false,"entry":false,"entry_weapon":null}}},{"round_start_time":1006.8359375,"round_end_time":1011.8359375,"t":"team_Seul_GI","ct":"team_Hero5k","winner":null,"players":{"0":{"kills":0,"headshots":0,"assists":0,"time_alive":-1,"damage":0,"objective":false,"entry":false,"entry_weapon":null},"76561198325440775":{"kills":0,"headshots":0,"assists":0,"time_alive":-1,"damage":0,"objective":false,"entry":false,"entry_weapon":null},"76561198046999713":{"kills":0,"headshots":0,"assists":0,"time_alive":-1,"damage":0,"objective":false,"entry":false,"entry_weapon":null},"76561198066567567":{"kills":0,"headshots":0,"assists":0,"time_alive":-1,"damage":0,"objective":false,"entry":false,"entry_weapon":null},"76561198100925955":{"kills":0,"headshots":0,"assists":0,"time_alive":-1,"damage":0,"objective":false,"entry":false,"entry_weapon":null},"76561198062484109":{"kills":0,"headshots":0,"assists":0,"time_alive":-1,"damage":0,"objective":false,"entry":false,"entry_weapon":null},"76561198055350646":{"kills":0,"headshots":0,"assists":0,"time_alive":-1,"damage":0,"objective":false,"entry":false,"entry_weapon":null},"76561198210808119":{"kills":0,"headshots":0,"assists":0,"time_alive":-1,"damage":0,"objective":false,"entry":false,"entry_weapon":null},"76561198035478071":{"kills":0,"headshots":0,"assists":0,"time_alive":-1,"damage":0,"objective":false,"entry":false,"entry_weapon":null},"76561198035140517":{"kills":0,"headshots":0,"assists":0,"time_alive":-1,"damage":0,"objective":false,"entry":false,"entry_weapon":null},"76561198045855183":{"kills":0,"headshots":0,"assists":0,"time_alive":-1,"damage":0,"objective":false,"entry":false,"entry_weapon":null}}},{"round_start_time":1083.25,"round_end_time":1088.25,"t":"team_Seul_GI","ct":"team_Hero5k","winner":null,"players":{"0":{"kills":0,"headshots":0,"assists":0,"time_alive":-1,"damage":0,"objective":false,"entry":false,"entry_weapon":null},"76561198325440775":{"kills":0,"headshots":0,"assists":0,"time_alive":-1,"damage":0,"objective":false,"entry":false,"entry_weapon":null},"76561198046999713":{"kills":0,"headshots":0,"assists":0,"time_alive":-1,"damage":0,"objective":false,"entry":false,"entry_weapon":null},"76561198066567567":{"kills":0,"headshots":0,"assists":0,"time_alive":-1,"damage":0,"objective":false,"entry":false,"entry_weapon":null},"76561198100925955":{"kills":0,"headshots":0,"assists":0,"time_alive":-1,"damage":0,"objective":false,"entry":false,"entry_weapon":null},"76561198062484109":{"kills":0,"headshots":0,"assists":0,"time_alive":-1,"damage":0,"objective":false,"entry":false,"entry_weapon":null},"76561198055350646":{"kills":0,"headshots":0,"assists":0,"time_alive":-1,"damage":0,"objective":false,"entry":false,"entry_weapon":null},"76561198210808119":{"kills":0,"headshots":0,"assists":0,"time_alive":-1,"damage":0,"objective":false,"entry":false,"entry_weapon":null},"76561198035478071":{"kills":0,"headshots":0,"assists":0,"time_alive":-1,"damage":0,"objective":false,"entry":false,"entry_weapon":null},"76561198035140517":{"kills":0,"headshots":0,"assists":0,"time_alive":-1,"damage":0,"objective":false,"entry":false,"entry_weapon":null},"76561198045855183":{"kills":0,"headshots":0,"assists":0,"time_alive":-1,"damage":0,"objective":false,"entry":false,"entry_weapon":null}}},{"round_start_time":1160.3203125,"round_end_time":1165.3671875,"t":"team_Seul_GI","ct":"team_Hero5k","winner":null,"players":{"0":{"kills":0,"headshots":0,"assists":0,"time_alive":-1,"damage":0,"objective":false,"entry":false,"entry_weapon":null},"76561198325440775":{"kills":0,"headshots":0,"assists":0,"time_alive":-1,"damage":0,"objective":false,"entry":false,"entry_weapon":null},"76561198046999713":{"kills":0,"headshots":0,"assists":0,"time_alive":-1,"damage":0,"objective":false,"entry":false,"entry_weapon":null},"76561198066567567":{"kills":0,"headshots":0,"assists":0,"time_alive":-1,"damage":0,"objective":false,"entry":false,"entry_weapon":null},"76561198100925955":{"kills":0,"headshots":0,"assists":0,"time_alive":-1,"damage":0,"objective":false,"entry":false,"entry_weapon":null},"76561198062484109":{"kills":0,"headshots":0,"assists":0,"time_alive":-1,"damage":0,"objective":false,"entry":false,"entry_weapon":null},"76561198055350646":{"kills":0,"headshots":0,"assists":0,"time_alive":-1,"damage":0,"objective":false,"entry":false,"entry_weapon":null},"76561198210808119":{"kills":0,"headshots":0,"assists":0,"time_alive":-1,"damage":0,"objective":false,"entry":false,"entry_weapon":null},"76561198035478071":{"kills":0,"headshots":0,"assists":0,"time_alive":-1,"damage":0,"objective":false,"entry":false,"entry_weapon":null},"76561198035140517":{"kills":0,"headshots":0,"assists":0,"time_alive":-1,"damage":0,"objective":false,"entry":false,"entry_weapon":null},"76561198045855183":{"kills":0,"headshots":0,"assists":0,"time_alive":-1,"damage":0,"objective":false,"entry":false,"entry_weapon":null}}},{"round_start_time":1237.5,"round_end_time":1242.5,"t":"team_Seul_GI","ct":"team_Hero5k","winner":null,"players":{"0":{"kills":0,"headshots":0,"assists":0,"time_alive":-1,"damage":0,"objective":false,"entry":false,"entry_weapon":null},"76561198325440775":{"kills":0,"headshots":0,"assists":0,"time_alive":-1,"damage":0,"objective":false,"entry":false,"entry_weapon":null},"76561198046999713":{"kills":0,"headshots":0,"assists":0,"time_alive":-1,"damage":0,"objective":false,"entry":false,"entry_weapon":null},"76561198066567567":{"kills":0,"headshots":0,"assists":0,"time_alive":-1,"damage":0,"objective":false,"entry":false,"entry_weapon":null},"76561198100925955":{"kills":0,"headshots":0,"assists":0,"time_alive":-1,"damage":0,"objective":false,"entry":false,"entry_weapon":null},"76561198062484109":{"kills":0,"headshots":0,"assists":0,"time_alive":-1,"damage":0,"objective":false,"entry":false,"entry_weapon":null},"76561198055350646":{"kills":0,"headshots":0,"assists":0,"time_alive":-1,"damage":0,"objective":false,"entry":false,"entry_weapon":null},"76561198210808119":{"kills":0,"headshots":0,"assists":0,"time_alive":-1,"damage":0,"objective":false,"entry":false,"entry_weapon":null},"76561198035478071":{"kills":0,"headshots":0,"assists":0,"time_alive":-1,"damage":0,"objective":false,"entry":false,"entry_weapon":null},"76561198035140517":{"kills":0,"headshots":0,"assists":0,"time_alive":-1,"damage":0,"objective":false,"entry":false,"entry_weapon":null},"76561198045855183":{"kills":0,"headshots":0,"assists":0,"time_alive":-1,"damage":0,"objective":false,"entry":false,"entry_weapon":null}}},{"round_start_time":1346.578125,"round_end_time":1361.578125,"t":"team_Seul_GI","ct":"team_Hero5k","winner":null,"players":{"0":{"kills":0,"headshots":0,"assists":0,"time_alive":-1,"damage":0,"objective":false,"entry":false,"entry_weapon":null},"76561198325440775":{"kills":0,"headshots":0,"assists":0,"time_alive":-1,"damage":0,"objective":false,"entry":false,"entry_weapon":null},"76561198046999713":{"kills":0,"headshots":0,"assists":0,"time_alive":-1,"damage":0,"objective":false,"entry":false,"entry_weapon":null},"76561198066567567":{"kills":0,"headshots":0,"assists":0,"time_alive":-1,"damage":0,"objective":false,"entry":false,"entry_weapon":null},"76561198100925955":{"kills":0,"headshots":0,"assists":0,"time_alive":-1,"damage":0,"objective":false,"entry":false,"entry_weapon":null},"76561198062484109":{"kills":0,"headshots":0,"assists":0,"time_alive":-1,"damage":0,"objective":false,"entry":false,"entry_weapon":null},"76561198055350646":{"kills":0,"headshots":0,"assists":0,"time_alive":-1,"damage":0,"objective":false,"entry":false,"entry_weapon":null},"76561198210808119":{"kills":0,"headshots":0,"assists":0,"time_alive":-1,"damage":0,"objective":false,"entry":false,"entry_weapon":null},"76561198035478071":{"kills":0,"headshots":0,"assists":0,"time_alive":-1,"damage":0,"objective":false,"entry":false,"entry_weapon":null},"76561198035140517":{"kills":0,"headshots":0,"assists":0,"time_alive":-1,"damage":0,"objective":false,"entry":false,"entry_weapon":null},"76561198045855183":{"kills":0,"headshots":0,"assists":0,"time_alive":-1,"damage":0,"objective":false,"entry":false,"entry_weapon":null}}},{"round_start_time":1423.59375,"round_end_time":1428.609375,"t":"team_Hero5k","ct":"team_Seul_GI","winner":null,"players":{"0":{"kills":0,"headshots":0,"assists":0,"time_alive":-1,"damage":0,"objective":false,"entry":false,"entry_weapon":null},"76561198325440775":{"kills":0,"headshots":0,"assists":0,"time_alive":-1,"damage":0,"objective":false,"entry":false,"entry_weapon":null},"76561198046999713":{"kills":0,"headshots":0,"assists":0,"time_alive":-1,"damage":0,"objective":false,"entry":false,"entry_weapon":null},"76561198066567567":{"kills":0,"headshots":0,"assists":0,"time_alive":-1,"damage":0,"objective":false,"entry":false,"entry_weapon":null},"76561198100925955":{"kills":0,"headshots":0,"assists":0,"time_alive":-1,"damage":0,"objective":false,"entry":false,"entry_weapon":null},"76561198062484109":{"kills":0,"headshots":0,"assists":0,"time_alive":-1,"damage":0,"objective":false,"entry":false,"entry_weapon":null},"76561198055350646":{"kills":0,"headshots":0,"assists":0,"time_alive":-1,"damage":0,"objective":false,"entry":false,"entry_weapon":null},"76561198210808119":{"kills":0,"headshots":0,"assists":0,"time_alive":-1,"damage":0,"objective":false,"entry":false,"entry_weapon":null},"76561198035478071":{"kills":0,"headshots":0,"assists":0,"time_alive":-1,"damage":0,"objective":false,"entry":false,"entry_weapon":null},"76561198035140517":{"kills":0,"headshots":0,"assists":0,"time_alive":-1,"damage":0,"objective":false,"entry":false,"entry_weapon":null},"76561198045855183":{"kills":0,"headshots":0,"assists":0,"time_alive":-1,"damage":0,"objective":false,"entry":false,"entry_weapon":null}}},{"round_start_time":1494.3125,"round_end_time":1499.375,"t":"team_Hero5k","ct":"team_Seul_GI","winner":null,"players":{"0":{"kills":0,"headshots":0,"assists":0,"time_alive":-1,"damage":0,"objective":false,"entry":false,"entry_weapon":null},"76561198325440775":{"kills":0,"headshots":0,"assists":0,"time_alive":-1,"damage":0,"objective":false,"entry":false,"entry_weapon":null},"76561198046999713":{"kills":0,"headshots":0,"assists":0,"time_alive":-1,"damage":0,"objective":false,"entry":false,"entry_weapon":null},"76561198066567567":{"kills":0,"headshots":0,"assists":0,"time_alive":-1,"damage":0,"objective":false,"entry":false,"entry_weapon":null},"76561198100925955":{"kills":0,"headshots":0,"assists":0,"time_alive":-1,"damage":0,"objective":false,"entry":false,"entry_weapon":null},"76561198062484109":{"kills":0,"headshots":0,"assists":0,"time_alive":-1,"damage":0,"objective":false,"entry":false,"entry_weapon":null},"76561198055350646":{"kills":0,"headshots":0,"assists":0,"time_alive":-1,"damage":0,"objective":false,"entry":false,"entry_weapon":null},"76561198210808119":{"kills":0,"headshots":0,"assists":0,"time_alive":-1,"damage":0,"objective":false,"entry":false,"entry_weapon":null},"76561198035478071":{"kills":0,"headshots":0,"assists":0,"time_alive":-1,"damage":0,"objective":false,"entry":false,"entry_weapon":null},"76561198035140517":{"kills":0,"headshots":0,"assists":0,"time_alive":-1,"damage":0,"objective":false,"entry":false,"entry_weapon":null},"76561198045855183":{"kills":0,"headshots":0,"assists":0,"time_alive":-1,"damage":0,"objective":false,"entry":false,"entry_weapon":null}}},{"round_start_time":1563.0546875,"round_end_time":1568.0703125,"t":"team_Hero5k","ct":"team_Seul_GI","winner":null,"players":{"0":{"kills":0,"headshots":0,"assists":0,"time_alive":-1,"damage":0,"objective":false,"entry":false,"entry_weapon":null},"76561198325440775":{"kills":0,"headshots":0,"assists":0,"time_alive":-1,"damage":0,"objective":false,"entry":false,"entry_weapon":null},"76561198046999713":{"kills":0,"headshots":0,"assists":0,"time_alive":-1,"damage":0,"objective":false,"entry":false,"entry_weapon":null},"76561198066567567":{"kills":0,"headshots":0,"assists":0,"time_alive":-1,"damage":0,"objective":false,"entry":false,"entry_weapon":null},"76561198100925955":{"kills":0,"headshots":0,"assists":0,"time_alive":-1,"damage":0,"objective":false,"entry":false,"entry_weapon":null},"76561198062484109":{"kills":0,"headshots":0,"assists":0,"time_alive":-1,"damage":0,"objective":false,"entry":false,"entry_weapon":null},"76561198055350646":{"kills":0,"headshots":0,"assists":0,"time_alive":-1,"damage":0,"objective":false,"entry":false,"entry_weapon":null},"76561198210808119":{"kills":0,"headshots":0,"assists":0,"time_alive":-1,"damage":0,"objective":false,"entry":false,"entry_weapon":null},"76561198035478071":{"kills":0,"headshots":0,"assists":0,"time_alive":-1,"damage":0,"objective":false,"entry":false,"entry_weapon":null},"76561198035140517":{"kills":0,"headshots":0,"assists":0,"time_alive":-1,"damage":0,"objective":false,"entry":false,"entry_weapon":null},"76561198045855183":{"kills":0,"headshots":0,"assists":0,"time_alive":-1,"damage":0,"objective":false,"entry":false,"entry_weapon":null}}},{"round_start_time":1598.96875,"round_end_time":1603.984375,"t":"team_Hero5k","ct":"team_Seul_GI","winner":null,"players":{"0":{"kills":0,"headshots":0,"assists":0,"time_alive":-1,"damage":0,"objective":false,"entry":false,"entry_weapon":null},"76561198325440775":{"kills":0,"headshots":0,"assists":0,"time_alive":-1,"damage":0,"objective":false,"entry":false,"entry_weapon":null},"76561198046999713":{"kills":0,"headshots":0,"assists":0,"time_alive":-1,"damage":0,"objective":false,"entry":false,"entry_weapon":null},"76561198066567567":{"kills":0,"headshots":0,"assists":0,"time_alive":-1,"damage":0,"objective":false,"entry":false,"entry_weapon":null},"76561198100925955":{"kills":0,"headshots":0,"assists":0,"time_alive":-1,"damage":0,"objective":false,"entry":false,"entry_weapon":null},"76561198062484109":{"kills":0,"headshots":0,"assists":0,"time_alive":-1,"damage":0,"objective":false,"entry":false,"entry_weapon":null},"76561198055350646":{"kills":0,"headshots":0,"assists":0,"time_alive":-1,"damage":0,"objective":false,"entry":false,"entry_weapon":null},"76561198210808119":{"kills":0,"headshots":0,"assists":0,"time_alive":-1,"damage":0,"objective":false,"entry":false,"entry_weapon":null},"76561198035478071":{"kills":0,"headshots":0,"assists":0,"time_alive":-1,"damage":0,"objective":false,"entry":false,"entry_weapon":null},"76561198035140517":{"kills":0,"headshots":0,"assists":0,"time_alive":-1,"damage":0,"objective":false,"entry":false,"entry_weapon":null},"76561198045855183":{"kills":0,"headshots":0,"assists":0,"time_alive":-1,"damage":0,"objective":false,"entry":false,"entry_weapon":null}}},{"round_start_time":1684.875,"round_end_time":1689.921875,"t":"team_Hero5k","ct":"team_Seul_GI","winner":null,"players":{"0":{"kills":0,"headshots":0,"assists":0,"time_alive":-1,"damage":0,"objective":false,"entry":false,"entry_weapon":null},"76561198100925955":{"kills":1,"headshots":0,"assists":0,"time_alive":-1,"damage":0,"objective":false,"entry":false,"entry_weapon":null,"wp_ak47":1,"wp_ak47_hs":0},"undefined":{"kills":0,"headshots":0,"assists":1,"time_alive":-1,"damage":0,"objective":false,"entry":false,"entry_weapon":null},"76561198066567567":{"kills":0,"headshots":0,"assists":0,"time_alive":0.984375,"damage":0,"objective":false,"entry":false,"entry_weapon":null},"76561198325440775":{"kills":0,"headshots":0,"assists":0,"time_alive":-1,"damage":0,"objective":false,"entry":false,"entry_weapon":null},"76561198046999713":{"kills":0,"headshots":0,"assists":0,"time_alive":-1,"damage":0,"objective":false,"entry":false,"entry_weapon":null},"76561198062484109":{"kills":0,"headshots":0,"assists":0,"time_alive":-1,"damage":0,"objective":false,"entry":false,"entry_weapon":null},"76561198055350646":{"kills":0,"headshots":0,"assists":0,"time_alive":-1,"damage":0,"objective":false,"entry":false,"entry_weapon":null},"76561198210808119":{"kills":0,"headshots":0,"assists":0,"time_alive":-1,"damage":0,"objective":false,"entry":false,"entry_weapon":null},"76561198035478071":{"kills":0,"headshots":0,"assists":0,"time_alive":-1,"damage":0,"objective":false,"entry":false,"entry_weapon":null},"76561198035140517":{"kills":0,"headshots":0,"assists":0,"time_alive":-1,"damage":0,"objective":false,"entry":false,"entry_weapon":null},"76561198045855183":{"kills":0,"headshots":0,"assists":0,"time_alive":-1,"damage":0,"objective":false,"entry":false,"entry_weapon":null}}},{"round_start_time":1784.75,"round_end_time":1789.75,"t":"team_Hero5k","ct":"team_Seul_GI","winner":null,"players":{"0":{"kills":0,"headshots":0,"assists":0,"time_alive":-1,"damage":0,"objective":false,"entry":false,"entry_weapon":null},"76561198325440775":{"kills":0,"headshots":0,"assists":0,"time_alive":-1,"damage":0,"objective":false,"entry":false,"entry_weapon":null},"76561198046999713":{"kills":0,"headshots":0,"assists":0,"time_alive":-1,"damage":0,"objective":false,"entry":false,"entry_weapon":null},"76561198066567567":{"kills":0,"headshots":0,"assists":0,"time_alive":-1,"damage":0,"objective":false,"entry":false,"entry_weapon":null},"76561198100925955":{"kills":0,"headshots":0,"assists":0,"time_alive":-1,"damage":0,"objective":false,"entry":false,"entry_weapon":null},"76561198062484109":{"kills":0,"headshots":0,"assists":0,"time_alive":-1,"damage":0,"objective":false,"entry":false,"entry_weapon":null},"76561198055350646":{"kills":0,"headshots":0,"assists":0,"time_alive":-1,"damage":0,"objective":false,"entry":false,"entry_weapon":null},"76561198210808119":{"kills":0,"headshots":0,"assists":0,"time_alive":-1,"damage":0,"objective":false,"entry":false,"entry_weapon":null},"76561198035478071":{"kills":0,"headshots":0,"assists":0,"time_alive":-1,"damage":0,"objective":false,"entry":false,"entry_weapon":null},"76561198035140517":{"kills":0,"headshots":0,"assists":0,"time_alive":-1,"damage":0,"objective":false,"entry":false,"entry_weapon":null},"76561198045855183":{"kills":0,"headshots":0,"assists":0,"time_alive":-1,"damage":0,"objective":false,"entry":false,"entry_weapon":null}}},{"round_start_time":1870.5234375,"round_end_time":1875.5234375,"t":"team_Hero5k","ct":"team_Seul_GI","winner":null,"players":{"0":{"kills":0,"headshots":0,"assists":0,"time_alive":-1,"damage":0,"objective":false,"entry":false,"entry_weapon":null},"76561198325440775":{"kills":0,"headshots":0,"assists":0,"time_alive":-1,"damage":0,"objective":false,"entry":false,"entry_weapon":null},"76561198046999713":{"kills":0,"headshots":0,"assists":0,"time_alive":-1,"damage":0,"objective":false,"entry":false,"entry_weapon":null},"76561198066567567":{"kills":0,"headshots":0,"assists":0,"time_alive":-1,"damage":0,"objective":false,"entry":false,"entry_weapon":null},"76561198100925955":{"kills":0,"headshots":0,"assists":0,"time_alive":-1,"damage":0,"objective":false,"entry":false,"entry_weapon":null},"76561198062484109":{"kills":0,"headshots":0,"assists":0,"time_alive":-1,"damage":0,"objective":false,"entry":false,"entry_weapon":null},"76561198055350646":{"kills":0,"headshots":0,"assists":0,"time_alive":-1,"damage":0,"objective":false,"entry":false,"entry_weapon":null},"76561198210808119":{"kills":0,"headshots":0,"assists":0,"time_alive":-1,"damage":0,"objective":false,"entry":false,"entry_weapon":null},"76561198035478071":{"kills":0,"headshots":0,"assists":0,"time_alive":-1,"damage":0,"objective":false,"entry":false,"entry_weapon":null},"76561198035140517":{"kills":0,"headshots":0,"assists":0,"time_alive":-1,"damage":0,"objective":false,"entry":false,"entry_weapon":null},"76561198045855183":{"kills":0,"headshots":0,"assists":0,"time_alive":-1,"damage":0,"objective":false,"entry":false,"entry_weapon":null}}},{"round_start_time":1945.59375,"round_end_time":1950.6484375,"t":"team_Hero5k","ct":"team_Seul_GI","winner":null,"players":{"0":{"kills":0,"headshots":0,"assists":0,"time_alive":-1,"damage":0,"objective":false,"entry":false,"entry_weapon":null},"76561198046999713":{"kills":1,"headshots":0,"assists":0,"time_alive":-1,"damage":0,"objective":false,"entry":false,"entry_weapon":null,"wp_p250":1,"wp_p250_hs":0},"undefined":{"kills":0,"headshots":0,"assists":1,"time_alive":-1,"damage":0,"objective":false,"entry":false,"entry_weapon":null},"76561198055350646":{"kills":0,"headshots":0,"assists":0,"time_alive":1.421875,"damage":0,"objective":false,"entry":false,"entry_weapon":null},"76561198325440775":{"kills":0,"headshots":0,"assists":0,"time_alive":-1,"damage":0,"objective":false,"entry":false,"entry_weapon":null},"76561198066567567":{"kills":0,"headshots":0,"assists":0,"time_alive":-1,"damage":0,"objective":false,"entry":false,"entry_weapon":null},"76561198100925955":{"kills":0,"headshots":0,"assists":0,"time_alive":-1,"damage":0,"objective":false,"entry":false,"entry_weapon":null},"76561198062484109":{"kills":0,"headshots":0,"assists":0,"time_alive":-1,"damage":0,"objective":false,"entry":false,"entry_weapon":null},"76561198210808119":{"kills":0,"headshots":0,"assists":0,"time_alive":-1,"damage":0,"objective":false,"entry":false,"entry_weapon":null},"76561198035478071":{"kills":0,"headshots":0,"assists":0,"time_alive":-1,"damage":0,"objective":false,"entry":false,"entry_weapon":null},"76561198035140517":{"kills":0,"headshots":0,"assists":0,"time_alive":-1,"damage":0,"objective":false,"entry":false,"entry_weapon":null},"76561198045855183":{"kills":0,"headshots":0,"assists":0,"time_alive":-1,"damage":0,"objective":false,"entry":false,"entry_weapon":null}}},{"round_start_time":1987.234375,"round_end_time":1992.296875,"t":"team_Hero5k","ct":"team_Seul_GI","winner":null,"players":{"0":{"kills":0,"headshots":0,"assists":0,"time_alive":-1,"damage":0,"objective":false,"entry":false,"entry_weapon":null},"76561198325440775":{"kills":0,"headshots":0,"assists":0,"time_alive":-1,"damage":0,"objective":false,"entry":false,"entry_weapon":null},"76561198046999713":{"kills":0,"headshots":0,"assists":0,"time_alive":-1,"damage":0,"objective":false,"entry":false,"entry_weapon":null},"76561198066567567":{"kills":0,"headshots":0,"assists":0,"time_alive":-1,"damage":0,"objective":false,"entry":false,"entry_weapon":null},"76561198100925955":{"kills":0,"headshots":0,"assists":0,"time_alive":-1,"damage":0,"objective":false,"entry":false,"entry_weapon":null},"76561198062484109":{"kills":0,"headshots":0,"assists":0,"time_alive":-1,"damage":0,"objective":false,"entry":false,"entry_weapon":null},"76561198055350646":{"kills":0,"headshots":0,"assists":0,"time_alive":-1,"damage":0,"objective":false,"entry":false,"entry_weapon":null},"76561198210808119":{"kills":0,"headshots":0,"assists":0,"time_alive":-1,"damage":0,"objective":false,"entry":false,"entry_weapon":null},"76561198035478071":{"kills":0,"headshots":0,"assists":0,"time_alive":-1,"damage":0,"objective":false,"entry":false,"entry_weapon":null},"76561198035140517":{"kills":0,"headshots":0,"assists":0,"time_alive":-1,"damage":0,"objective":false,"entry":false,"entry_weapon":null},"76561198045855183":{"kills":0,"headshots":0,"assists":0,"time_alive":-1,"damage":0,"objective":false,"entry":false,"entry_weapon":null}}}]}